{
    "anime1": {
        "info": {
            "title": "Different Kings",
            "story": "مانجا Different Kings مترجمةDifferent Kings فى عام 2023 ، هالة قوية قامت بتغطية الارض كاملة وجميع الكائنات على الارض تأثرو منها البشر بدأو فى ايقاظ القوة والكائنات غير البشر تطورت بسرعة شديدة بسبب الها...",
            "image": "https://olympustaff.com/images/manga/2114249845900925715.jpg"
        },
        "chapters": [
            {
                "chapter": "1",
                "images": [
                    "https://olympustaff.com/uploads/manga_16790/1/00.webp",
                    "https://olympustaff.com/uploads/manga_16790/1/01.webp",
                    "https://olympustaff.com/uploads/manga_16790/1/02.webp",
                    "https://olympustaff.com/uploads/manga_16790/1/03.webp",
                    "https://olympustaff.com/uploads/manga_16790/1/04.webp"
                ]
            },
            {
                "chapter": "2",
                "images": [
                    "https://olympustaff.com/uploads/manga_16790/2/00.webp",
                    "https://olympustaff.com/uploads/manga_16790/2/01.webp",
                    "https://olympustaff.com/uploads/manga_16790/2/02.webp"
                ]
            },
            {
                "chapter": "3",
                "images": [
                    "https://olympustaff.com/uploads/manga_16790/3/00.webp",
                    "https://olympustaff.com/uploads/manga_16790/3/01.webp"
                ]
            },
            {
                "chapter": "4",
                "images": [
                    "https://olympustaff.com/uploads/manga_16790/4/00.webp",
                    "https://olympustaff.com/uploads/manga_16790/4/01.webp"
                ]
            },
            {
                "chapter": "5",
                "images": [
                    "https://olympustaff.com/uploads/manga_16790/5/00.webp",
                    "https://olympustaff.com/uploads/manga_16790/5/01.webp"
                ]
            },
            {
                "chapter": "6",
                "images": [
                    "https://olympustaff.com/uploads/manga_16790/6/00.webp",
                    "https://olympustaff.com/uploads/manga_16790/6/01.webp"
                ]
            },
            {
                "chapter": "7",
                "images": [
                    "https://olympustaff.com/uploads/manga_16790/7/00.webp",
                    "https://olympustaff.com/uploads/manga_16790/7/01.webp",
                    "https://olympustaff.com/uploads/manga_16790/7/02.webp",
                    "https://olympustaff.com/uploads/manga_16790/7/03.webp"
                ]
            },
            {
                "chapter": "8",
                "images": [
                    "https://olympustaff.com/uploads/manga_16790/8/00.webp",
                    "https://olympustaff.com/uploads/manga_16790/8/01.webp",
                    "https://olympustaff.com/uploads/manga_16790/8/02.webp"
                ]
            },
            {
                "chapter": "9",
                "images": [
                    "https://olympustaff.com/uploads/manga_16790/9/00.webp",
                    "https://olympustaff.com/uploads/manga_16790/9/01.webp",
                    "https://olympustaff.com/uploads/manga_16790/9/02.webp",
                    "https://olympustaff.com/uploads/manga_16790/9/03.webp"
                ]
            },
            {
                "chapter": "10",
                "images": [
                    "https://olympustaff.com/uploads/manga_16790/10/00.webp",
                    "https://olympustaff.com/uploads/manga_16790/10/01.webp",
                    "https://olympustaff.com/uploads/manga_16790/10/02.webp",
                    "https://olympustaff.com/uploads/manga_16790/10/03.webp",
                    "https://olympustaff.com/uploads/manga_16790/10/04.webp"
                ]
            },
            {
                "chapter": "11",
                "images": [
                    "https://olympustaff.com/uploads/manga_16790/11/00.webp",
                    "https://olympustaff.com/uploads/manga_16790/11/01.webp",
                    "https://olympustaff.com/uploads/manga_16790/11/02.webp",
                    "https://olympustaff.com/uploads/manga_16790/11/03.webp",
                    "https://olympustaff.com/uploads/manga_16790/11/04.webp"
                ]
            },
            {
                "chapter": "12",
                "images": [
                    "https://olympustaff.com/uploads/manga_16790/12/00.webp",
                    "https://olympustaff.com/uploads/manga_16790/12/01.webp",
                    "https://olympustaff.com/uploads/manga_16790/12/02.webp",
                    "https://olympustaff.com/uploads/manga_16790/12/03.webp",
                    "https://olympustaff.com/uploads/manga_16790/12/04.webp"
                ]
            },
            {
                "chapter": "13",
                "images": [
                    "https://olympustaff.com/uploads/manga_16790/13/00.webp",
                    "https://olympustaff.com/uploads/manga_16790/13/01.webp",
                    "https://olympustaff.com/uploads/manga_16790/13/02.webp",
                    "https://olympustaff.com/uploads/manga_16790/13/03.webp"
                ]
            },
            {
                "chapter": "14",
                "images": [
                    "https://olympustaff.com/uploads/manga_16790/14/00.webp",
                    "https://olympustaff.com/uploads/manga_16790/14/01.webp",
                    "https://olympustaff.com/uploads/manga_16790/14/02.webp"
                ]
            },
            {
                "chapter": "15",
                "images": [
                    "https://olympustaff.com/uploads/manga_16790/15/00.webp",
                    "https://olympustaff.com/uploads/manga_16790/15/01.webp",
                    "https://olympustaff.com/uploads/manga_16790/15/02.webp",
                    "https://olympustaff.com/uploads/manga_16790/15/03.webp"
                ]
            },
            {
                "chapter": "16",
                "images": [
                    "https://olympustaff.com/uploads/manga_16790/16/00.webp",
                    "https://olympustaff.com/uploads/manga_16790/16/01.webp",
                    "https://olympustaff.com/uploads/manga_16790/16/02.webp"
                ]
            },
            {
                "chapter": "17",
                "images": [
                    "https://olympustaff.com/uploads/manga_16790/17/00.webp",
                    "https://olympustaff.com/uploads/manga_16790/17/01.webp",
                    "https://olympustaff.com/uploads/manga_16790/17/02.webp",
                    "https://olympustaff.com/uploads/manga_16790/17/03.webp"
                ]
            },
            {
                "chapter": "18",
                "images": [
                    "https://olympustaff.com/uploads/manga_16790/18/00.webp",
                    "https://olympustaff.com/uploads/manga_16790/18/01.webp",
                    "https://olympustaff.com/uploads/manga_16790/18/02.webp"
                ]
            },
            {
                "chapter": "19",
                "images": [
                    "https://olympustaff.com/uploads/manga_16790/19/00.webp",
                    "https://olympustaff.com/uploads/manga_16790/19/01.webp",
                    "https://olympustaff.com/uploads/manga_16790/19/02.webp",
                    "https://olympustaff.com/uploads/manga_16790/19/03.webp"
                ]
            },
            {
                "chapter": "20",
                "images": [
                    "https://olympustaff.com/uploads/manga_16790/20/00.webp",
                    "https://olympustaff.com/uploads/manga_16790/20/01.webp",
                    "https://olympustaff.com/uploads/manga_16790/20/02.webp",
                    "https://olympustaff.com/uploads/manga_16790/20/03.webp"
                ]
            },
            {
                "chapter": "21",
                "images": [
                    "https://olympustaff.com/uploads/manga_16790/21/00.webp",
                    "https://olympustaff.com/uploads/manga_16790/21/01.webp",
                    "https://olympustaff.com/uploads/manga_16790/21/02.webp",
                    "https://olympustaff.com/uploads/manga_16790/21/03.webp"
                ]
            },
            {
                "chapter": "22",
                "images": [
                    "https://olympustaff.com/uploads/manga_16790/22/00.webp",
                    "https://olympustaff.com/uploads/manga_16790/22/01.webp",
                    "https://olympustaff.com/uploads/manga_16790/22/02.webp"
                ]
            },
            {
                "chapter": "23",
                "images": [
                    "https://olympustaff.com/uploads/manga_16790/23/00.webp",
                    "https://olympustaff.com/uploads/manga_16790/23/01.webp",
                    "https://olympustaff.com/uploads/manga_16790/23/02.webp",
                    "https://olympustaff.com/uploads/manga_16790/23/03.webp"
                ]
            },
            {
                "chapter": "24",
                "images": [
                    "https://olympustaff.com/uploads/manga_16790/24/00.webp",
                    "https://olympustaff.com/uploads/manga_16790/24/01.webp",
                    "https://olympustaff.com/uploads/manga_16790/24/02.webp"
                ]
            },
            {
                "chapter": "25",
                "images": [
                    "https://olympustaff.com/uploads/manga_16790/25/00.webp",
                    "https://olympustaff.com/uploads/manga_16790/25/01.webp",
                    "https://olympustaff.com/uploads/manga_16790/25/02.webp",
                    "https://olympustaff.com/uploads/manga_16790/25/03.webp"
                ]
            },
            {
                "chapter": "26",
                "images": [
                    "https://olympustaff.com/uploads/manga_16790/26/00.webp",
                    "https://olympustaff.com/uploads/manga_16790/26/01.webp",
                    "https://olympustaff.com/uploads/manga_16790/26/02.webp",
                    "https://olympustaff.com/uploads/manga_16790/26/03.webp"
                ]
            },
            {
                "chapter": "27",
                "images": [
                    "https://olympustaff.com/uploads/manga_16790/27/00.webp",
                    "https://olympustaff.com/uploads/manga_16790/27/01.webp",
                    "https://olympustaff.com/uploads/manga_16790/27/02.webp",
                    "https://olympustaff.com/uploads/manga_16790/27/03.webp"
                ]
            },
            {
                "chapter": "28",
                "images": [
                    "https://olympustaff.com/uploads/manga_16790/28/00.webp",
                    "https://olympustaff.com/uploads/manga_16790/28/01.webp",
                    "https://olympustaff.com/uploads/manga_16790/28/02.webp",
                    "https://olympustaff.com/uploads/manga_16790/28/03.webp"
                ]
            },
            {
                "chapter": "29",
                "images": [
                    "https://olympustaff.com/uploads/manga_16790/29/00.webp",
                    "https://olympustaff.com/uploads/manga_16790/29/01.webp",
                    "https://olympustaff.com/uploads/manga_16790/29/02.webp",
                    "https://olympustaff.com/uploads/manga_16790/29/03.webp"
                ]
            },
            {
                "chapter": "30",
                "images": [
                    "https://olympustaff.com/uploads/manga_16790/30/00.webp",
                    "https://olympustaff.com/uploads/manga_16790/30/01.webp",
                    "https://olympustaff.com/uploads/manga_16790/30/02.webp",
                    "https://olympustaff.com/uploads/manga_16790/30/03.webp"
                ]
            },
            {
                "chapter": "31",
                "images": [
                    "https://olympustaff.com/uploads/manga_16790/31/00.webp",
                    "https://olympustaff.com/uploads/manga_16790/31/01.webp",
                    "https://olympustaff.com/uploads/manga_16790/31/02.webp",
                    "https://olympustaff.com/uploads/manga_16790/31/03.webp"
                ]
            },
            {
                "chapter": "32",
                "images": [
                    "https://olympustaff.com/uploads/manga_16790/32/00.webp",
                    "https://olympustaff.com/uploads/manga_16790/32/01.webp",
                    "https://olympustaff.com/uploads/manga_16790/32/02.webp",
                    "https://olympustaff.com/uploads/manga_16790/32/03.webp"
                ]
            },
            {
                "chapter": "33",
                "images": [
                    "https://olympustaff.com/uploads/manga_16790/33/00.webp",
                    "https://olympustaff.com/uploads/manga_16790/33/01.webp",
                    "https://olympustaff.com/uploads/manga_16790/33/02.webp",
                    "https://olympustaff.com/uploads/manga_16790/33/03.webp"
                ]
            },
            {
                "chapter": "34",
                "images": [
                    "https://olympustaff.com/uploads/manga_16790/34/00.webp",
                    "https://olympustaff.com/uploads/manga_16790/34/01.webp",
                    "https://olympustaff.com/uploads/manga_16790/34/02.webp",
                    "https://olympustaff.com/uploads/manga_16790/34/03.webp"
                ]
            },
            {
                "chapter": "35",
                "images": [
                    "https://olympustaff.com/uploads/manga_16790/35/00.webp",
                    "https://olympustaff.com/uploads/manga_16790/35/01.webp",
                    "https://olympustaff.com/uploads/manga_16790/35/02.webp"
                ]
            },
            {
                "chapter": "36",
                "images": [
                    "https://olympustaff.com/uploads/manga_16790/36/00.webp",
                    "https://olympustaff.com/uploads/manga_16790/36/01.webp",
                    "https://olympustaff.com/uploads/manga_16790/36/02.webp",
                    "https://olympustaff.com/uploads/manga_16790/36/03.webp"
                ]
            },
            {
                "chapter": "37",
                "images": [
                    "https://olympustaff.com/uploads/manga_16790/37/00.webp",
                    "https://olympustaff.com/uploads/manga_16790/37/01.webp",
                    "https://olympustaff.com/uploads/manga_16790/37/02.webp"
                ]
            },
            {
                "chapter": "38",
                "images": [
                    "https://olympustaff.com/uploads/manga_16790/38/00.webp",
                    "https://olympustaff.com/uploads/manga_16790/38/01.webp",
                    "https://olympustaff.com/uploads/manga_16790/38/02.webp"
                ]
            },
            {
                "chapter": "39",
                "images": [
                    "https://olympustaff.com/uploads/manga_16790/39/00.webp",
                    "https://olympustaff.com/uploads/manga_16790/39/01.webp",
                    "https://olympustaff.com/uploads/manga_16790/39/02.webp",
                    "https://olympustaff.com/uploads/manga_16790/39/03.webp",
                    "https://olympustaff.com/uploads/manga_16790/39/04.webp"
                ]
            },
            {
                "chapter": "40",
                "images": [
                    "https://olympustaff.com/uploads/manga_16790/40/00.webp",
                    "https://olympustaff.com/uploads/manga_16790/40/01.webp",
                    "https://olympustaff.com/uploads/manga_16790/40/02.webp"
                ]
            },
            {
                "chapter": "41",
                "images": [
                    "https://olympustaff.com/uploads/manga_16790/41/00.webp",
                    "https://olympustaff.com/uploads/manga_16790/41/01.webp"
                ]
            },
            {
                "chapter": "42",
                "images": [
                    "https://olympustaff.com/uploads/manga_16790/42/00.webp",
                    "https://olympustaff.com/uploads/manga_16790/42/01.webp",
                    "https://olympustaff.com/uploads/manga_16790/42/02.webp"
                ]
            },
            {
                "chapter": "43",
                "images": [
                    "https://olympustaff.com/uploads/manga_16790/43/00.webp",
                    "https://olympustaff.com/uploads/manga_16790/43/01.webp",
                    "https://olympustaff.com/uploads/manga_16790/43/02.webp",
                    "https://olympustaff.com/uploads/manga_16790/43/03.webp"
                ]
            },
            {
                "chapter": "44",
                "images": [
                    "https://olympustaff.com/uploads/manga_16790/44/00.webp",
                    "https://olympustaff.com/uploads/manga_16790/44/01.webp",
                    "https://olympustaff.com/uploads/manga_16790/44/02.webp"
                ]
            },
            {
                "chapter": "45",
                "images": [
                    "https://olympustaff.com/uploads/manga_16790/45/00.webp",
                    "https://olympustaff.com/uploads/manga_16790/45/01.webp"
                ]
            },
            {
                "chapter": "46",
                "images": [
                    "https://olympustaff.com/uploads/manga_16790/46/00.webp",
                    "https://olympustaff.com/uploads/manga_16790/46/01.webp",
                    "https://olympustaff.com/uploads/manga_16790/46/02.webp"
                ]
            },
            {
                "chapter": "47",
                "images": [
                    "https://olympustaff.com/uploads/manga_16790/47/00.webp",
                    "https://olympustaff.com/uploads/manga_16790/47/01.webp",
                    "https://olympustaff.com/uploads/manga_16790/47/02.webp"
                ]
            },
            {
                "chapter": "48",
                "images": [
                    "https://olympustaff.com/uploads/manga_16790/48/00.webp",
                    "https://olympustaff.com/uploads/manga_16790/48/01.webp",
                    "https://olympustaff.com/uploads/manga_16790/48/02.webp"
                ]
            },
            {
                "chapter": "49",
                "images": [
                    "https://olympustaff.com/uploads/manga_16790/49/00.webp",
                    "https://olympustaff.com/uploads/manga_16790/49/01.webp",
                    "https://olympustaff.com/uploads/manga_16790/49/02.webp"
                ]
            },
            {
                "chapter": "50",
                "images": [
                    "https://olympustaff.com/uploads/manga_16790/50/00.webp",
                    "https://olympustaff.com/uploads/manga_16790/50/01.webp",
                    "https://olympustaff.com/uploads/manga_16790/50/02.webp"
                ]
            },
            {
                "chapter": "51",
                "images": [
                    "https://olympustaff.com/uploads/manga_16790/51/00.webp",
                    "https://olympustaff.com/uploads/manga_16790/51/01.webp",
                    "https://olympustaff.com/uploads/manga_16790/51/02.webp"
                ]
            },
            {
                "chapter": "52",
                "images": [
                    "https://olympustaff.com/uploads/manga_16790/52/00.webp",
                    "https://olympustaff.com/uploads/manga_16790/52/01.webp",
                    "https://olympustaff.com/uploads/manga_16790/52/02.webp"
                ]
            },
            {
                "chapter": "53",
                "images": [
                    "https://olympustaff.com/uploads/manga_16790/53/00.webp",
                    "https://olympustaff.com/uploads/manga_16790/53/01.webp",
                    "https://olympustaff.com/uploads/manga_16790/53/02.webp"
                ]
            },
            {
                "chapter": "54",
                "images": [
                    "https://olympustaff.com/uploads/manga_16790/54/00.webp",
                    "https://olympustaff.com/uploads/manga_16790/54/01.webp",
                    "https://olympustaff.com/uploads/manga_16790/54/02.webp"
                ]
            },
            {
                "chapter": "55",
                "images": [
                    "https://olympustaff.com/uploads/manga_16790/55/5143ae00c0ae85eb6b84bd6b53284c68.00.jpg",
                    "https://olympustaff.com/uploads/manga_16790/55/ba99bee175366e5d27c7a18e3ba06bcc.01.jpg",
                    "https://olympustaff.com/uploads/manga_16790/55/5230f5994a6648a9f64852d9a831277b.02.jpg"
                ]
            },
            {
                "chapter": "56",
                "images": [
                    "https://olympustaff.com/uploads/manga_16790/56/00.webp",
                    "https://olympustaff.com/uploads/manga_16790/56/01.webp"
                ]
            },
            {
                "chapter": "57",
                "images": [
                    "https://olympustaff.com/uploads/manga_16790/57/57df80b22618aebaf29b136e3cef4318.00.jpg",
                    "https://olympustaff.com/uploads/manga_16790/57/d4411cbd0cbbe10b4ca2b3ccbb794e85.01.jpg"
                ]
            },
            {
                "chapter": "58",
                "images": [
                    "https://olympustaff.com/uploads/manga_16790/58/aaa4faaed45c499dceeb50af958d85b0.00.jpg",
                    "https://olympustaff.com/uploads/manga_16790/58/3a2b06bb5f9d8cdc4123176e452b4dd7.01.jpg",
                    "https://olympustaff.com/uploads/manga_16790/58/989c0df30bd68d0a9f19d3482a43d8dd.02.jpg"
                ]
            },
            {
                "chapter": "59",
                "images": [
                    "https://olympustaff.com/uploads/manga_16790/59/b678274697154c55ab97e36556e4e94a.00.jpg",
                    "https://olympustaff.com/uploads/manga_16790/59/4e74ef3a000c6f0b6a852a5afff7ebbf.01.jpg",
                    "https://olympustaff.com/uploads/manga_16790/59/bcb905e342e39e3b40df007ac3b3ec89.02.jpg"
                ]
            },
            {
                "chapter": "60",
                "images": [
                    "https://olympustaff.com/uploads/manga_16790/60/ffb0fc1fa91001d0af2be1f33d5551df.00.jpg",
                    "https://olympustaff.com/uploads/manga_16790/60/c3fc6ee14d669eecd42e81a575f11742.01.jpg",
                    "https://olympustaff.com/uploads/manga_16790/60/e83167f39452c935702e32de2af5000c.02.jpg",
                    "https://olympustaff.com/uploads/manga_16790/60/ff4beb939ef08a661d8f1d6333b24015.03.jpg"
                ]
            },
            {
                "chapter": "61",
                "images": [
                    "https://olympustaff.com/uploads/manga_16790/61/82ef2f230053116a9e5df938565c561f.00.jpg",
                    "https://olympustaff.com/uploads/manga_16790/61/b9452ed365741c29a50b458682449fd4.01.jpg",
                    "https://olympustaff.com/uploads/manga_16790/61/a7b8cdbf8cc51286ddfe67b1fb54df56.02.jpg",
                    "https://olympustaff.com/uploads/manga_16790/61/47c1c6b957209c618531b3ff88ca57ff.03.jpg",
                    "https://olympustaff.com/uploads/manga_16790/61/32e67ad4599d5199874ef12f120dba4b.04.jpg"
                ]
            },
            {
                "chapter": "62",
                "images": [
                    "https://olympustaff.com/uploads/manga_16790/62/00.webp",
                    "https://olympustaff.com/uploads/manga_16790/62/01.webp",
                    "https://olympustaff.com/uploads/manga_16790/62/02.webp",
                    "https://olympustaff.com/uploads/manga_16790/62/03.webp"
                ]
            },
            {
                "chapter": "63",
                "images": [
                    "https://olympustaff.com/uploads/manga_16790/63/00.webp",
                    "https://olympustaff.com/uploads/manga_16790/63/01.webp"
                ]
            },
            {
                "chapter": "64",
                "images": [
                    "https://olympustaff.com/uploads/manga_16790/64/df0770fa1f919a3334981c9e79fe8cf1.00.jpg",
                    "https://olympustaff.com/uploads/manga_16790/64/09a643c43f9ab904930cc884f433a32d.01.jpg",
                    "https://olympustaff.com/uploads/manga_16790/64/2a809be7695e4ed8a9b23c7693e58b64.02.jpg",
                    "https://olympustaff.com/uploads/manga_16790/64/fd6c134b01f1e42f97e8357958677931.03.jpg"
                ]
            },
            {
                "chapter": "65",
                "images": [
                    "https://olympustaff.com/uploads/manga_16790/65/86e889002bf1d11185ab66151282a162.00.jpg",
                    "https://olympustaff.com/uploads/manga_16790/65/e4e9511fe7d255206b08397aebaf41f8.01.jpg",
                    "https://olympustaff.com/uploads/manga_16790/65/2cf6ddffb8f0464fa29b19de169d006e.02.jpg",
                    "https://olympustaff.com/uploads/manga_16790/65/e9f03baf83a2219ebedade69add3395c.03.jpg",
                    "https://olympustaff.com/uploads/manga_16790/65/8f12fa797d125775fbb380c4133a6e6d.04.jpg",
                    "https://olympustaff.com/uploads/manga_16790/65/2296c0aff45443992648efa1e33baa7b.05.jpg"
                ]
            },
            {
                "chapter": "66",
                "images": [
                    "https://olympustaff.com/uploads/manga_16790/66/00.webp",
                    "https://olympustaff.com/uploads/manga_16790/66/01.webp",
                    "https://olympustaff.com/uploads/manga_16790/66/02.webp"
                ]
            },
            {
                "chapter": "67",
                "images": [
                    "https://olympustaff.com/uploads/manga_16790/67/00.webp",
                    "https://olympustaff.com/uploads/manga_16790/67/01.webp",
                    "https://olympustaff.com/uploads/manga_16790/67/02.webp",
                    "https://olympustaff.com/uploads/manga_16790/67/03.webp",
                    "https://olympustaff.com/uploads/manga_16790/67/04.webp",
                    "https://olympustaff.com/uploads/manga_16790/67/05.webp",
                    "https://olympustaff.com/uploads/manga_16790/67/06.webp"
                ]
            },
            {
                "chapter": "68",
                "images": [
                    "https://olympustaff.com/uploads/manga_16790/68/00.webp",
                    "https://olympustaff.com/uploads/manga_16790/68/01.webp",
                    "https://olympustaff.com/uploads/manga_16790/68/02.webp",
                    "https://olympustaff.com/uploads/manga_16790/68/03.webp"
                ]
            },
            {
                "chapter": "69",
                "images": [
                    "https://olympustaff.com/uploads/manga_16790/69/00.webp",
                    "https://olympustaff.com/uploads/manga_16790/69/01.webp"
                ]
            },
            {
                "chapter": "70",
                "images": [
                    "https://olympustaff.com/uploads/manga_16790/70/00.webp",
                    "https://olympustaff.com/uploads/manga_16790/70/01.webp",
                    "https://olympustaff.com/uploads/manga_16790/70/02.webp"
                ]
            },
            {
                "chapter": "71",
                "images": [
                    "https://olympustaff.com/uploads/manga_16790/71/ac286bbbf2c41cc83621b03a715dd02a.00.jpg",
                    "https://olympustaff.com/uploads/manga_16790/71/740dc77a4d9de98203c7d9cdbd646fdd.01.jpg"
                ]
            },
            {
                "chapter": "72",
                "images": [
                    "https://olympustaff.com/uploads/manga_16790/72/e1ab1343e7159d214cc180cbcd68e452.00.jpg",
                    "https://olympustaff.com/uploads/manga_16790/72/48aff8cba1b1b9d1ebbb33571505a14a.01.jpg"
                ]
            },
            {
                "chapter": "73",
                "images": [
                    "https://olympustaff.com/uploads/manga_16790/73/4860b246bad8af224a0305b36b925898.00.jpg",
                    "https://olympustaff.com/uploads/manga_16790/73/f9d37f66a9e689146f20cbd528cb32be.01.jpg"
                ]
            },
            {
                "chapter": "74",
                "images": [
                    "https://olympustaff.com/uploads/manga_16790/74/622755c18c90cae004e905e7ebc3d1e2.00.jpg",
                    "https://olympustaff.com/uploads/manga_16790/74/cb5c32862557f387ff4be87ced961ff7.01.jpg"
                ]
            },
            {
                "chapter": "75",
                "images": [
                    "https://olympustaff.com/uploads/manga_16790/75/b2080b60c071d92b44ea13960615ed26.00.jpg",
                    "https://olympustaff.com/uploads/manga_16790/75/a8270d117999b0e50e3d866851c07a76.01.jpg"
                ]
            },
            {
                "chapter": "76",
                "images": [
                    "https://olympustaff.com/uploads/manga_16790/76/00.webp",
                    "https://olympustaff.com/uploads/manga_16790/76/01.webp"
                ]
            },
            {
                "chapter": "77",
                "images": [
                    "https://olympustaff.com/uploads/manga_16790/77/00.webp",
                    "https://olympustaff.com/uploads/manga_16790/77/01.webp",
                    "https://olympustaff.com/uploads/manga_16790/77/02.webp"
                ]
            },
            {
                "chapter": "78",
                "images": [
                    "https://olympustaff.com/uploads/manga_16790/78/00.webp",
                    "https://olympustaff.com/uploads/manga_16790/78/01.webp"
                ]
            },
            {
                "chapter": "79",
                "images": [
                    "https://olympustaff.com/uploads/manga_16790/79/00.webp",
                    "https://olympustaff.com/uploads/manga_16790/79/01.webp"
                ]
            },
            {
                "chapter": "80",
                "images": [
                    "https://olympustaff.com/uploads/manga_16790/80/00.webp",
                    "https://olympustaff.com/uploads/manga_16790/80/01.webp"
                ]
            },
            {
                "chapter": "81",
                "images": [
                    "https://olympustaff.com/uploads/manga_16790/81/00.webp",
                    "https://olympustaff.com/uploads/manga_16790/81/01.webp",
                    "https://olympustaff.com/uploads/manga_16790/81/02.webp"
                ]
            },
            {
                "chapter": "82",
                "images": [
                    "https://olympustaff.com/uploads/manga_16790/82/00.webp",
                    "https://olympustaff.com/uploads/manga_16790/82/01.webp"
                ]
            },
            {
                "chapter": "83",
                "images": [
                    "https://olympustaff.com/uploads/manga_16790/83/00.webp",
                    "https://olympustaff.com/uploads/manga_16790/83/01.webp",
                    "https://olympustaff.com/uploads/manga_16790/83/02.webp"
                ]
            },
            {
                "chapter": "84",
                "images": [
                    "https://olympustaff.com/uploads/manga_16790/84/00.webp",
                    "https://olympustaff.com/uploads/manga_16790/84/01.webp",
                    "https://olympustaff.com/uploads/manga_16790/84/02.webp",
                    "https://olympustaff.com/uploads/manga_16790/84/03.webp"
                ]
            },
            {
                "chapter": "85",
                "images": [
                    "https://olympustaff.com/uploads/manga_16790/85/00.webp",
                    "https://olympustaff.com/uploads/manga_16790/85/01.webp",
                    "https://olympustaff.com/uploads/manga_16790/85/02.webp",
                    "https://olympustaff.com/uploads/manga_16790/85/03.webp"
                ]
            },
            {
                "chapter": "86",
                "images": [
                    "https://olympustaff.com/uploads/manga_16790/86/00.webp",
                    "https://olympustaff.com/uploads/manga_16790/86/01.webp",
                    "https://olympustaff.com/uploads/manga_16790/86/02.webp",
                    "https://olympustaff.com/uploads/manga_16790/86/03.webp"
                ]
            },
            {
                "chapter": "87",
                "images": [
                    "https://olympustaff.com/uploads/manga_16790/87/00.webp",
                    "https://olympustaff.com/uploads/manga_16790/87/01.webp",
                    "https://olympustaff.com/uploads/manga_16790/87/02.webp",
                    "https://olympustaff.com/uploads/manga_16790/87/03.webp"
                ]
            },
            {
                "chapter": "88",
                "images": [
                    "https://olympustaff.com/uploads/manga_16790/88/00.webp",
                    "https://olympustaff.com/uploads/manga_16790/88/01.webp",
                    "https://olympustaff.com/uploads/manga_16790/88/02.webp"
                ]
            },
            {
                "chapter": "89",
                "images": [
                    "https://olympustaff.com/uploads/manga_16790/89/00.webp",
                    "https://olympustaff.com/uploads/manga_16790/89/01.webp",
                    "https://olympustaff.com/uploads/manga_16790/89/02.webp"
                ]
            },
            {
                "chapter": "90",
                "images": [
                    "https://olympustaff.com/uploads/manga_16790/90/00.webp",
                    "https://olympustaff.com/uploads/manga_16790/90/01.webp",
                    "https://olympustaff.com/uploads/manga_16790/90/02.webp"
                ]
            },
            {
                "chapter": "91",
                "images": [
                    "https://olympustaff.com/uploads/manga_16790/91/00.webp",
                    "https://olympustaff.com/uploads/manga_16790/91/01.webp",
                    "https://olympustaff.com/uploads/manga_16790/91/02.webp"
                ]
            },
            {
                "chapter": "92",
                "images": [
                    "https://olympustaff.com/uploads/manga_16790/92/00.webp",
                    "https://olympustaff.com/uploads/manga_16790/92/01.webp",
                    "https://olympustaff.com/uploads/manga_16790/92/02.webp"
                ]
            },
            {
                "chapter": "93",
                "images": [
                    "https://olympustaff.com/uploads/manga_16790/93/00.webp",
                    "https://olympustaff.com/uploads/manga_16790/93/01.webp",
                    "https://olympustaff.com/uploads/manga_16790/93/02.webp"
                ]
            },
            {
                "chapter": "94",
                "images": [
                    "https://olympustaff.com/uploads/manga_16790/94/00.webp",
                    "https://olympustaff.com/uploads/manga_16790/94/01.webp"
                ]
            },
            {
                "chapter": "95",
                "images": [
                    "https://olympustaff.com/uploads/manga_16790/95/00.webp",
                    "https://olympustaff.com/uploads/manga_16790/95/01.webp"
                ]
            },
            {
                "chapter": "96",
                "images": [
                    "https://olympustaff.com/uploads/manga_16790/96/4ce2899c52a791442680e6edf555d393.00.jpg",
                    "https://olympustaff.com/uploads/manga_16790/96/effdb2efdb1b0b273e3cc5f8cfe4b8b7.01.jpg"
                ]
            },
            {
                "chapter": "97",
                "images": [
                    "https://olympustaff.com/uploads/manga_16790/97/00.webp",
                    "https://olympustaff.com/uploads/manga_16790/97/01.webp"
                ]
            },
            {
                "chapter": "98",
                "images": [
                    "https://olympustaff.com/uploads/manga_16790/98/00.webp",
                    "https://olympustaff.com/uploads/manga_16790/98/01.webp"
                ]
            },
            {
                "chapter": "99",
                "images": [
                    "https://olympustaff.com/uploads/manga_16790/99/00.webp",
                    "https://olympustaff.com/uploads/manga_16790/99/01.webp"
                ]
            },
            {
                "chapter": "100",
                "images": [
                    "https://olympustaff.com/uploads/manga_16790/100/00.webp",
                    "https://olympustaff.com/uploads/manga_16790/100/01.webp"
                ]
            },
            {
                "chapter": "101",
                "images": [
                    "https://olympustaff.com/uploads/manga_16790/101/00.webp",
                    "https://olympustaff.com/uploads/manga_16790/101/01.webp"
                ]
            },
            {
                "chapter": "102",
                "images": [
                    "https://olympustaff.com/uploads/manga_16790/102/00.webp",
                    "https://olympustaff.com/uploads/manga_16790/102/01.webp"
                ]
            },
            {
                "chapter": "103",
                "images": [
                    "https://olympustaff.com/uploads/manga_16790/103/dfc6ffb903cf48202bf196138fc74494.00.jpg",
                    "https://olympustaff.com/uploads/manga_16790/103/ee39a3c6c53b880f1504b23db753194b.01.jpg",
                    "https://olympustaff.com/uploads/manga_16790/103/1d602005deb795bdbb2d33c4225c58e7.02.jpg"
                ]
            },
            {
                "chapter": "104",
                "images": [
                    "https://olympustaff.com/uploads/manga_16790/104/00.webp",
                    "https://olympustaff.com/uploads/manga_16790/104/01.webp",
                    "https://olympustaff.com/uploads/manga_16790/104/02.webp"
                ]
            },
            {
                "chapter": "105",
                "images": [
                    "https://olympustaff.com/uploads/manga_16790/105/1.webp",
                    "https://olympustaff.com/uploads/manga_16790/105/2.webp",
                    "https://olympustaff.com/uploads/manga_16790/105/3.webp"
                ]
            },
            {
                "chapter": "106",
                "images": [
                    "https://olympustaff.com/uploads/manga_16790/106/656d88d4ef853517f8b68cfbc6c71293.00.jpg",
                    "https://olympustaff.com/uploads/manga_16790/106/2d94beef131a4b8f91e6d1b7a24ccdc4.01.jpg",
                    "https://olympustaff.com/uploads/manga_16790/106/49ace0495506057796b452ad0c83b174.02.jpg"
                ]
            },
            {
                "chapter": "107",
                "images": [
                    "https://olympustaff.com/uploads/manga_16790/107/00.webp",
                    "https://olympustaff.com/uploads/manga_16790/107/01.webp",
                    "https://olympustaff.com/uploads/manga_16790/107/02.webp"
                ]
            },
            {
                "chapter": "108",
                "images": [
                    "https://olympustaff.com/uploads/manga_16790/108/07d770b9a913350f9a3bf077d2b4d70f.00.jpg",
                    "https://olympustaff.com/uploads/manga_16790/108/9a2e6b53c57fc091da8766496bcc045c.01.jpg",
                    "https://olympustaff.com/uploads/manga_16790/108/4f06ffdb0ff231c88a5bf63efc43afff.02.jpg"
                ]
            },
            {
                "chapter": "109",
                "images": [
                    "https://olympustaff.com/uploads/manga_16790/109/00.webp",
                    "https://olympustaff.com/uploads/manga_16790/109/01.webp",
                    "https://olympustaff.com/uploads/manga_16790/109/02.webp"
                ]
            },
            {
                "chapter": "110",
                "images": [
                    "https://olympustaff.com/uploads/manga_16790/110/364e3a7fe0f1adc71612c91a53d907b4.00.jpg",
                    "https://olympustaff.com/uploads/manga_16790/110/8e10c8c4df00d0d9264211838a18e1f8.01.jpg",
                    "https://olympustaff.com/uploads/manga_16790/110/cf1fbe23a401827fab6949c0b20557dd.02.jpg"
                ]
            },
            {
                "chapter": "111",
                "images": [
                    "https://olympustaff.com/uploads/manga_16790/111/00.webp",
                    "https://olympustaff.com/uploads/manga_16790/111/01.webp"
                ]
            },
            {
                "chapter": "112",
                "images": [
                    "https://olympustaff.com/uploads/manga_16790/112/2de4ecf0f9a6c474abaf92336e3cfb93.00.jpg",
                    "https://olympustaff.com/uploads/manga_16790/112/7f487ec6048c53756ea2e1c9e3e79d2a.01.jpg"
                ]
            },
            {
                "chapter": "113",
                "images": [
                    "https://olympustaff.com/uploads/manga_16790/113/0fe4e6fbdcf8c12b55cff00d127dd0a6.00.jpg",
                    "https://olympustaff.com/uploads/manga_16790/113/49bf0d467bfda779215e72755c329eab.01.jpg",
                    "https://olympustaff.com/uploads/manga_16790/113/676aed3742211dcef4b2ff0b5ababf02.02.jpg"
                ]
            },
            {
                "chapter": "114",
                "images": [
                    "https://olympustaff.com/uploads/manga_16790/114/00.webp",
                    "https://olympustaff.com/uploads/manga_16790/114/01.webp"
                ]
            },
            {
                "chapter": "115",
                "images": [
                    "https://olympustaff.com/uploads/manga_16790/115/00.webp",
                    "https://olympustaff.com/uploads/manga_16790/115/01.webp",
                    "https://olympustaff.com/uploads/manga_16790/115/02.webp"
                ]
            },
            {
                "chapter": "116",
                "images": [
                    "https://olympustaff.com/uploads/manga_16790/116/00.webp",
                    "https://olympustaff.com/uploads/manga_16790/116/01.webp"
                ]
            },
            {
                "chapter": "117",
                "images": [
                    "https://olympustaff.com/uploads/manga_16790/117/00.webp",
                    "https://olympustaff.com/uploads/manga_16790/117/01.webp"
                ]
            },
            {
                "chapter": "118",
                "images": [
                    "https://olympustaff.com/uploads/manga_16790/118/00.webp",
                    "https://olympustaff.com/uploads/manga_16790/118/01.webp"
                ]
            },
            {
                "chapter": "119",
                "images": [
                    "https://olympustaff.com/uploads/manga_16790/119/00.webp",
                    "https://olympustaff.com/uploads/manga_16790/119/01.webp"
                ]
            },
            {
                "chapter": "120",
                "images": [
                    "https://olympustaff.com/uploads/manga_16790/120/00.webp",
                    "https://olympustaff.com/uploads/manga_16790/120/01.webp",
                    "https://olympustaff.com/uploads/manga_16790/120/02.webp",
                    "https://olympustaff.com/uploads/manga_16790/120/03.webp"
                ]
            },
            {
                "chapter": "121",
                "images": [
                    "https://olympustaff.com/uploads/manga_16790/121/00.webp",
                    "https://olympustaff.com/uploads/manga_16790/121/01.webp",
                    "https://olympustaff.com/uploads/manga_16790/121/02.webp"
                ]
            },
            {
                "chapter": "122",
                "images": [
                    "https://olympustaff.com/uploads/manga_16790/122/00.webp",
                    "https://olympustaff.com/uploads/manga_16790/122/01.webp",
                    "https://olympustaff.com/uploads/manga_16790/122/02.webp"
                ]
            },
            {
                "chapter": "123",
                "images": [
                    "https://olympustaff.com/uploads/manga_16790/123/00.webp",
                    "https://olympustaff.com/uploads/manga_16790/123/01.webp",
                    "https://olympustaff.com/uploads/manga_16790/123/02.webp"
                ]
            },
            {
                "chapter": "124",
                "images": [
                    "https://olympustaff.com/uploads/manga_16790/124/00.webp",
                    "https://olympustaff.com/uploads/manga_16790/124/01.webp",
                    "https://olympustaff.com/uploads/manga_16790/124/02.webp"
                ]
            },
            {
                "chapter": "125",
                "images": [
                    "https://olympustaff.com/uploads/manga_16790/125/00.webp",
                    "https://olympustaff.com/uploads/manga_16790/125/01.webp",
                    "https://olympustaff.com/uploads/manga_16790/125/02.webp"
                ]
            },
            {
                "chapter": "126",
                "images": [
                    "https://olympustaff.com/uploads/manga_16790/126/00.webp",
                    "https://olympustaff.com/uploads/manga_16790/126/01.webp",
                    "https://olympustaff.com/uploads/manga_16790/126/02.webp"
                ]
            },
            {
                "chapter": "127",
                "images": [
                    "https://olympustaff.com/uploads/manga_16790/127/00.webp",
                    "https://olympustaff.com/uploads/manga_16790/127/01.webp",
                    "https://olympustaff.com/uploads/manga_16790/127/02.webp"
                ]
            },
            {
                "chapter": "128",
                "images": [
                    "https://olympustaff.com/uploads/manga_16790/128/00.webp",
                    "https://olympustaff.com/uploads/manga_16790/128/01.webp",
                    "https://olympustaff.com/uploads/manga_16790/128/02.webp"
                ]
            },
            {
                "chapter": "129",
                "images": [
                    "https://olympustaff.com/uploads/manga_16790/129/00.webp",
                    "https://olympustaff.com/uploads/manga_16790/129/01.webp",
                    "https://olympustaff.com/uploads/manga_16790/129/02.webp",
                    "https://olympustaff.com/uploads/manga_16790/129/03.webp"
                ]
            },
            {
                "chapter": "130",
                "images": [
                    "https://olympustaff.com/uploads/manga_16790/130/00.webp",
                    "https://olympustaff.com/uploads/manga_16790/130/01.webp",
                    "https://olympustaff.com/uploads/manga_16790/130/02.webp"
                ]
            },
            {
                "chapter": "131",
                "images": [
                    "https://olympustaff.com/uploads/manga_16790/131/00.webp",
                    "https://olympustaff.com/uploads/manga_16790/131/01.webp",
                    "https://olympustaff.com/uploads/manga_16790/131/02.webp",
                    "https://olympustaff.com/uploads/manga_16790/131/03.webp"
                ]
            },
            {
                "chapter": "132",
                "images": [
                    "https://olympustaff.com/uploads/manga_16790/132/00.webp",
                    "https://olympustaff.com/uploads/manga_16790/132/01.webp",
                    "https://olympustaff.com/uploads/manga_16790/132/02.webp",
                    "https://olympustaff.com/uploads/manga_16790/132/03.webp"
                ]
            },
            {
                "chapter": "133",
                "images": [
                    "https://olympustaff.com/uploads/manga_16790/133/946f1af7d7b4ba097ae6510923bd3a90.00.jpg",
                    "https://olympustaff.com/uploads/manga_16790/133/81d8dc28abdd97a67bfaa28f0f2880a5.01.jpg",
                    "https://olympustaff.com/uploads/manga_16790/133/0fb71225f9ad15c7ee158465b703b963.02.jpg",
                    "https://olympustaff.com/uploads/manga_16790/133/9a8382d0e5967893d0c12224f81b9811.03.jpg"
                ]
            },
            {
                "chapter": "134",
                "images": [
                    "https://olympustaff.com/uploads/manga_16790/134/00.webp",
                    "https://olympustaff.com/uploads/manga_16790/134/01.webp",
                    "https://olympustaff.com/uploads/manga_16790/134/02.webp",
                    "https://olympustaff.com/uploads/manga_16790/134/03.webp"
                ]
            },
            {
                "chapter": "135",
                "images": [
                    "https://olympustaff.com/uploads/manga_16790/135/00.webp",
                    "https://olympustaff.com/uploads/manga_16790/135/01.webp",
                    "https://olympustaff.com/uploads/manga_16790/135/02.webp",
                    "https://olympustaff.com/uploads/manga_16790/135/03.webp"
                ]
            },
            {
                "chapter": "136",
                "images": [
                    "https://olympustaff.com/uploads/manga_16790/136/00.webp",
                    "https://olympustaff.com/uploads/manga_16790/136/01.webp",
                    "https://olympustaff.com/uploads/manga_16790/136/02.webp",
                    "https://olympustaff.com/uploads/manga_16790/136/03.webp"
                ]
            },
            {
                "chapter": "137",
                "images": [
                    "https://olympustaff.com/uploads/manga_16790/137/00.webp",
                    "https://olympustaff.com/uploads/manga_16790/137/01.webp",
                    "https://olympustaff.com/uploads/manga_16790/137/02.webp",
                    "https://olympustaff.com/uploads/manga_16790/137/03.webp"
                ]
            },
            {
                "chapter": "138",
                "images": [
                    "https://olympustaff.com/uploads/manga_16790/138/6b2e08059c3f98949e779b11bbc6c3d4.00.jpg",
                    "https://olympustaff.com/uploads/manga_16790/138/73c9ec95cf983d5f0b2a18cb665b2929.01.jpg",
                    "https://olympustaff.com/uploads/manga_16790/138/5d2c1b28b4c14c1f285c18efb6b1cd60.02.jpg",
                    "https://olympustaff.com/uploads/manga_16790/138/0b615544f0764241e123ba05d91de2c2.03.jpg"
                ]
            },
            {
                "chapter": "139",
                "images": [
                    "https://olympustaff.com/uploads/manga_16790/139/d4896b4512a8c04883eb892ceec93c88.00.jpg",
                    "https://olympustaff.com/uploads/manga_16790/139/3eaefb336cf64167ed79bfe98776263f.01.jpg",
                    "https://olympustaff.com/uploads/manga_16790/139/eda42be780872130c199e7ae7058cfc5.02.jpg"
                ]
            },
            {
                "chapter": "140",
                "images": [
                    "https://olympustaff.com/uploads/manga_16790/140/00.webp",
                    "https://olympustaff.com/uploads/manga_16790/140/01.webp",
                    "https://olympustaff.com/uploads/manga_16790/140/02.webp",
                    "https://olympustaff.com/uploads/manga_16790/140/03.webp",
                    "https://olympustaff.com/uploads/manga_16790/140/04.webp",
                    "https://olympustaff.com/uploads/manga_16790/140/05.webp",
                    "https://olympustaff.com/uploads/manga_16790/140/06.webp",
                    "https://olympustaff.com/uploads/manga_16790/140/07.webp",
                    "https://olympustaff.com/uploads/manga_16790/140/08.webp",
                    "https://olympustaff.com/uploads/manga_16790/140/09.webp",
                    "https://olympustaff.com/uploads/manga_16790/140/010.webp",
                    "https://olympustaff.com/uploads/manga_16790/140/011.webp",
                    "https://olympustaff.com/uploads/manga_16790/140/012.webp",
                    "https://olympustaff.com/uploads/manga_16790/140/013.webp",
                    "https://olympustaff.com/uploads/manga_16790/140/014.webp",
                    "https://olympustaff.com/uploads/manga_16790/140/015.webp",
                    "https://olympustaff.com/uploads/manga_16790/140/016.webp"
                ]
            },
            {
                "chapter": "141",
                "images": [
                    "https://olympustaff.com/uploads/manga_16790/141/00.webp",
                    "https://olympustaff.com/uploads/manga_16790/141/01.webp",
                    "https://olympustaff.com/uploads/manga_16790/141/02.webp"
                ]
            },
            {
                "chapter": "142",
                "images": [
                    "https://olympustaff.com/uploads/manga_16790/142/eadad4cf7092606c7540532a252b249a.00.jpg",
                    "https://olympustaff.com/uploads/manga_16790/142/fe8526979c48abb1c48792f702324f92.01.jpg",
                    "https://olympustaff.com/uploads/manga_16790/142/95215b86725f857b819fd5a5a060c63d.02.jpg"
                ]
            },
            {
                "chapter": "143",
                "images": [
                    "https://olympustaff.com/uploads/manga_16790/143/00.webp",
                    "https://olympustaff.com/uploads/manga_16790/143/01.webp",
                    "https://olympustaff.com/uploads/manga_16790/143/02.webp"
                ]
            },
            {
                "chapter": "144",
                "images": [
                    "https://olympustaff.com/uploads/manga_16790/144/00.webp",
                    "https://olympustaff.com/uploads/manga_16790/144/01.webp",
                    "https://olympustaff.com/uploads/manga_16790/144/02.webp"
                ]
            },
            {
                "chapter": "145",
                "images": [
                    "https://olympustaff.com/uploads/manga_16790/145/00.webp"
                ]
            },
            {
                "chapter": "146",
                "images": [
                    "https://olympustaff.com/uploads/manga_16790/146/00.webp",
                    "https://olympustaff.com/uploads/manga_16790/146/01.webp"
                ]
            },
            {
                "chapter": "147",
                "images": [
                    "https://olympustaff.com/uploads/manga_16790/147/00.webp",
                    "https://olympustaff.com/uploads/manga_16790/147/01.webp",
                    "https://olympustaff.com/uploads/manga_16790/147/02.webp",
                    "https://olympustaff.com/uploads/manga_16790/147/03.webp",
                    "https://olympustaff.com/uploads/manga_16790/147/04.webp",
                    "https://olympustaff.com/uploads/manga_16790/147/05.webp",
                    "https://olympustaff.com/uploads/manga_16790/147/06.webp",
                    "https://olympustaff.com/uploads/manga_16790/147/07.webp",
                    "https://olympustaff.com/uploads/manga_16790/147/08.webp",
                    "https://olympustaff.com/uploads/manga_16790/147/09.webp",
                    "https://olympustaff.com/uploads/manga_16790/147/010.webp",
                    "https://olympustaff.com/uploads/manga_16790/147/011.webp",
                    "https://olympustaff.com/uploads/manga_16790/147/012.webp"
                ]
            },
            {
                "chapter": "148",
                "images": [
                    "https://olympustaff.com/uploads/manga_16790/148/00.webp",
                    "https://olympustaff.com/uploads/manga_16790/148/01.webp"
                ]
            },
            {
                "chapter": "149",
                "images": [
                    "https://olympustaff.com/uploads/manga_16790/149/00.webp",
                    "https://olympustaff.com/uploads/manga_16790/149/01.webp",
                    "https://olympustaff.com/uploads/manga_16790/149/02.webp",
                    "https://olympustaff.com/uploads/manga_16790/149/03.webp",
                    "https://olympustaff.com/uploads/manga_16790/149/04.webp",
                    "https://olympustaff.com/uploads/manga_16790/149/05.webp",
                    "https://olympustaff.com/uploads/manga_16790/149/06.webp",
                    "https://olympustaff.com/uploads/manga_16790/149/07.webp",
                    "https://olympustaff.com/uploads/manga_16790/149/08.webp",
                    "https://olympustaff.com/uploads/manga_16790/149/09.webp",
                    "https://olympustaff.com/uploads/manga_16790/149/010.webp",
                    "https://olympustaff.com/uploads/manga_16790/149/011.webp",
                    "https://olympustaff.com/uploads/manga_16790/149/012.webp",
                    "https://olympustaff.com/uploads/manga_16790/149/013.webp",
                    "https://olympustaff.com/uploads/manga_16790/149/014.webp",
                    "https://olympustaff.com/uploads/manga_16790/149/015.webp"
                ]
            },
            {
                "chapter": "150",
                "images": [
                    "https://olympustaff.com/uploads/manga_16790/150/00.webp",
                    "https://olympustaff.com/uploads/manga_16790/150/01.webp",
                    "https://olympustaff.com/uploads/manga_16790/150/02.webp",
                    "https://olympustaff.com/uploads/manga_16790/150/03.webp",
                    "https://olympustaff.com/uploads/manga_16790/150/04.webp",
                    "https://olympustaff.com/uploads/manga_16790/150/05.webp",
                    "https://olympustaff.com/uploads/manga_16790/150/06.webp",
                    "https://olympustaff.com/uploads/manga_16790/150/07.webp",
                    "https://olympustaff.com/uploads/manga_16790/150/08.webp",
                    "https://olympustaff.com/uploads/manga_16790/150/09.webp",
                    "https://olympustaff.com/uploads/manga_16790/150/010.webp",
                    "https://olympustaff.com/uploads/manga_16790/150/011.webp",
                    "https://olympustaff.com/uploads/manga_16790/150/012.webp",
                    "https://olympustaff.com/uploads/manga_16790/150/013.webp",
                    "https://olympustaff.com/uploads/manga_16790/150/014.webp",
                    "https://olympustaff.com/uploads/manga_16790/150/015.webp",
                    "https://olympustaff.com/uploads/manga_16790/150/016.webp"
                ]
            },
            {
                "chapter": "151",
                "images": [
                    "https://olympustaff.com/uploads/manga_16790/151/00.webp",
                    "https://olympustaff.com/uploads/manga_16790/151/01.webp",
                    "https://olympustaff.com/uploads/manga_16790/151/02.webp",
                    "https://olympustaff.com/uploads/manga_16790/151/03.webp",
                    "https://olympustaff.com/uploads/manga_16790/151/04.webp",
                    "https://olympustaff.com/uploads/manga_16790/151/05.webp",
                    "https://olympustaff.com/uploads/manga_16790/151/06.webp",
                    "https://olympustaff.com/uploads/manga_16790/151/07.webp",
                    "https://olympustaff.com/uploads/manga_16790/151/08.webp",
                    "https://olympustaff.com/uploads/manga_16790/151/09.webp",
                    "https://olympustaff.com/uploads/manga_16790/151/010.webp",
                    "https://olympustaff.com/uploads/manga_16790/151/011.webp",
                    "https://olympustaff.com/uploads/manga_16790/151/012.webp",
                    "https://olympustaff.com/uploads/manga_16790/151/013.webp",
                    "https://olympustaff.com/uploads/manga_16790/151/014.webp",
                    "https://olympustaff.com/uploads/manga_16790/151/015.webp",
                    "https://olympustaff.com/uploads/manga_16790/151/016.webp"
                ]
            },
            {
                "chapter": "152",
                "images": [
                    "https://olympustaff.com/uploads/manga_16790/152/05da1fcfee20b2c6e5cb8452de0f18e3.webp",
                    "https://olympustaff.com/uploads/manga_16790/152/289eaf2a16683a54be75923d847b962d.webp",
                    "https://olympustaff.com/uploads/manga_16790/152/455072a8378295799f96c4aa53b7be7a.webp"
                ]
            },
            {
                "chapter": "153",
                "images": [
                    "https://olympustaff.com/uploads/manga_16790/153/a1a544e61708c807344f3694f3dbce7e.webp",
                    "https://olympustaff.com/uploads/manga_16790/153/0661ee871c2b19ce358028caeef667f0.webp",
                    "https://olympustaff.com/uploads/manga_16790/153/8b9bd61e1373449ad73acf6f5fdb6222.webp"
                ]
            },
            {
                "chapter": "154",
                "images": [
                    "https://olympustaff.com/uploads/manga_16790/154/5e2f1cbd225ce2a1730e39d62c514670.webp",
                    "https://olympustaff.com/uploads/manga_16790/154/1967d8e6dc2cd8b9ed96f170954a86f4.webp",
                    "https://olympustaff.com/uploads/manga_16790/154/0c7b23d9487189944a8e031b5b5e66fd.webp"
                ]
            },
            {
                "chapter": "155",
                "images": [
                    "https://olympustaff.com/uploads/manga_16790/155/dfc762db2cdbe8507bf9c9876e48d0ba.webp",
                    "https://olympustaff.com/uploads/manga_16790/155/789d6767deacad5fb8f8d3f1473a6948.webp",
                    "https://olympustaff.com/uploads/manga_16790/155/22ec9da9785391ad29485e9842939284.webp"
                ]
            },
            {
                "chapter": "156",
                "images": [
                    "https://olympustaff.com/uploads/manga_16790/156/7e2c09eee0c9dd79f5ec2bcd5e2506af.webp",
                    "https://olympustaff.com/uploads/manga_16790/156/8e4f61fd0c0cefe49f2bbc4d3b8e18b3.01.webp",
                    "https://olympustaff.com/uploads/manga_16790/156/3faf6063c3f534cc1a32a10b83db9374.webp"
                ]
            },
            {
                "chapter": "157",
                "images": [
                    "https://olympustaff.com/uploads/manga_16790/157/f5df46d4b69d5d38a33d33eadf160834.jpg",
                    "https://olympustaff.com/uploads/manga_16790/157/0d5f9fedba1f4512865315174ea19a82.jpg",
                    "https://olympustaff.com/uploads/manga_16790/157/4540849a6cd7a25596da69184363fb86.jpg",
                    "https://olympustaff.com/uploads/manga_16790/157/de7d970240b3daee1660836636018403.jpg"
                ]
            },
            {
                "chapter": "158",
                "images": [
                    "https://olympustaff.com/uploads/manga_16790/158/66064e933b1c9a42848e6632d83d5a90.jpg",
                    "https://olympustaff.com/uploads/manga_16790/158/34e396fff5e2c97b01a231a6236768c3.jpg",
                    "https://olympustaff.com/uploads/manga_16790/158/dc125fbf4937b7ca82cb942a0675fbcd.jpeg"
                ]
            },
            {
                "chapter": "159",
                "images": [
                    "https://olympustaff.com/uploads/manga_16790/159/1bbd7e28cd9c32befb69dfb73804b0bd.jpg",
                    "https://olympustaff.com/uploads/manga_16790/159/2744719d1885eee7705d9f0c1b8860e2.jpg",
                    "https://olympustaff.com/uploads/manga_16790/159/3d5968cbcca7e3f89e7dcad6b5c1c76c.jpg",
                    "https://olympustaff.com/uploads/manga_16790/159/3ee9cb7523558b539773ae156226ef72.jpg",
                    "https://olympustaff.com/uploads/manga_16790/159/568aaa194749104352fc3b7b018286af.jpg",
                    "https://olympustaff.com/uploads/manga_16790/159/a04f466f1e2fa9761f83b1a0ceaf754c.jpg",
                    "https://olympustaff.com/uploads/manga_16790/159/d6b4d2f8dadcd2d45b2eb8b66d08ccf1.jpg",
                    "https://olympustaff.com/uploads/manga_16790/159/3a32dea81de5366bd3a4321497baa2c5.jpg",
                    "https://olympustaff.com/uploads/manga_16790/159/caf3c5045e7d1583b3c981d246ad124a.jpg",
                    "https://olympustaff.com/uploads/manga_16790/159/d6b4fdc8bc5ffa4ed808837a1b44dacd.jpg"
                ]
            },
            {
                "chapter": "160",
                "images": [
                    "https://olympustaff.com/uploads/manga_16790/160/c06fa38d85f5de20c9221fa77d8ccd85.jpg",
                    "https://olympustaff.com/uploads/manga_16790/160/5da23cf346b9f79c9d77fda969f6abf4.jpg",
                    "https://olympustaff.com/uploads/manga_16790/160/22f76499532365ea5931f8c7c93765d9.jpg",
                    "https://olympustaff.com/uploads/manga_16790/160/bb6efb06992a36b2c4a3bfa9c2cd5b4d.jpg",
                    "https://olympustaff.com/uploads/manga_16790/160/c8bbf83827277d9892abb8cc446ec104.jpg",
                    "https://olympustaff.com/uploads/manga_16790/160/b1736d6d5f24ba88ad45b61748b6a6a3.jpg",
                    "https://olympustaff.com/uploads/manga_16790/160/25f6d67a4767229a1a8385c4c9119a3e.jpg",
                    "https://olympustaff.com/uploads/manga_16790/160/f1ba4c39afb09f29b7065e73b6ff9f4f.jpg"
                ]
            },
            {
                "chapter": "161",
                "images": [
                    "https://olympustaff.com/uploads/manga_16790/161/48469c2be9954fc2518fa3347198f0c5.jpg",
                    "https://olympustaff.com/uploads/manga_16790/161/d51e2ef72f4eaaa5d45b671d836498bd.jpg",
                    "https://olympustaff.com/uploads/manga_16790/161/90f9d958ef9c7007d4671e3ef9982641.jpg",
                    "https://olympustaff.com/uploads/manga_16790/161/a9b9b0a328a7c27202d51003ac090679.jpg",
                    "https://olympustaff.com/uploads/manga_16790/161/ad0f751a88e056141c0c0da5863ee363.jpg",
                    "https://olympustaff.com/uploads/manga_16790/161/5d89b02fe9fe401c9a346b7d5cb0febc.jpg",
                    "https://olympustaff.com/uploads/manga_16790/161/ff5601cafb70c42b789f610131ce5af6.jpg",
                    "https://olympustaff.com/uploads/manga_16790/161/c0a66db425994850b5d472560a482492.jpg"
                ]
            },
            {
                "chapter": "162",
                "images": [
                    "https://olympustaff.com/uploads/manga_16790/162/6c62b19324b21257707ebe8e8e9c3853.png",
                    "https://olympustaff.com/uploads/manga_16790/162/a6f5de1205d90c0936c02d412eb505ce.jpg",
                    "https://olympustaff.com/uploads/manga_16790/162/9ff576be5ba8cbe10910af2bd1f60826.jpg",
                    "https://olympustaff.com/uploads/manga_16790/162/614adad6b5494c92b131bcf3f9882ad8.jpg",
                    "https://olympustaff.com/uploads/manga_16790/162/21c915a6765aab508a673836d6a77a64.jpg",
                    "https://olympustaff.com/uploads/manga_16790/162/12bf771339122b9c0143e4f393a047e2.jpg",
                    "https://olympustaff.com/uploads/manga_16790/162/af9500f8ee591265f42bfb5cf2b09426.jpg",
                    "https://olympustaff.com/uploads/manga_16790/162/776c79ee6e033d99958da7b4e857305f.jpg",
                    "https://olympustaff.com/uploads/manga_16790/162/2d9f7f42581786a71f76983bb2a363c1.jpg",
                    "https://olympustaff.com/uploads/manga_16790/162/36186fb081647b8c6b1cc7bd716d78f2.jpg",
                    "https://olympustaff.com/uploads/manga_16790/162/c092dfde3b706d4e09d19621126ade85.jpg",
                    "https://olympustaff.com/uploads/manga_16790/162/4e0b96af7a4ab5a1e8282d0d737e854d.jpg",
                    "https://olympustaff.com/uploads/manga_16790/162/d2aeb929de58bf18af3a827db4e8f619.jpg"
                ]
            },
            {
                "chapter": "163",
                "images": [
                    "https://olympustaff.com/uploads/manga_16790/163/d797153245fec3ed8144ce2f89c4ef72.jpg",
                    "https://olympustaff.com/uploads/manga_16790/163/0fa2e6cca850c4dbe8770a0743cef0d2.jpg",
                    "https://olympustaff.com/uploads/manga_16790/163/4a05f9041271b7cd953ec8d4a648bbce.jpg",
                    "https://olympustaff.com/uploads/manga_16790/163/15a8956cddee405d3a299d3974321479.jpg",
                    "https://olympustaff.com/uploads/manga_16790/163/c056c121df910ea8fce3aeb0fd09ca79.jpg",
                    "https://olympustaff.com/uploads/manga_16790/163/9c252fe802dacd0d9a04c2556b8fba58.jpg",
                    "https://olympustaff.com/uploads/manga_16790/163/73e376b3a127bd9b254dea5fd80b9a61.jpg",
                    "https://olympustaff.com/uploads/manga_16790/163/c7ca5a03181fad0b8ffc53ed275d1fe2.jpg",
                    "https://olympustaff.com/uploads/manga_16790/163/7374f86b7558c26b35b131d5bd75811d.jpg",
                    "https://olympustaff.com/uploads/manga_16790/163/d5f2ee5a78e47340d638f7d6582df53a.jpg",
                    "https://olympustaff.com/uploads/manga_16790/163/7046d1b0a5567e622cec669f40a93b7d.jpg",
                    "https://olympustaff.com/uploads/manga_16790/163/29fa6eef4e2abc9c502446a4e49d76fc.jpg",
                    "https://olympustaff.com/uploads/manga_16790/163/db63267f8d2f29ba5b5b051474e0e6ac.jpg",
                    "https://olympustaff.com/uploads/manga_16790/163/bc4a31de20c5370ff85dd5363abaa0a5.jpg",
                    "https://olympustaff.com/uploads/manga_16790/163/b762b0a6a71753c11e013d5ac210e0bc.jpg",
                    "https://olympustaff.com/uploads/manga_16790/163/4ab807ab4e6cf4090bc18bab17de771a.jpg"
                ]
            },
            {
                "chapter": "164",
                "images": [
                    "https://olympustaff.com/uploads/manga_16790/164/a6628102153510b3c91b1febf4cfaf51.jpg",
                    "https://olympustaff.com/uploads/manga_16790/164/47f4ccf0eb2a62cbb3458d17a2c52245.jpg"
                ]
            },
            {
                "chapter": "165",
                "images": [
                    "https://olympustaff.com/uploads/manga_16790/165/c6ffd22f1ad0d4138023d51e01d48e98.jpg",
                    "https://olympustaff.com/uploads/manga_16790/165/b9cb42aed7550a8e8308c4f0c4955a67.jpg"
                ]
            },
            {
                "chapter": "166",
                "images": [
                    "https://olympustaff.com/uploads/manga_16790/166/a147ccb9fafd5c2fc379c4ef061d0d1c.jpg",
                    "https://olympustaff.com/uploads/manga_16790/166/37e87709fb0b2e93954755b5271c862d.jpg"
                ]
            },
            {
                "chapter": "167",
                "images": [
                    "https://olympustaff.com/uploads/manga_16790/167/679b3bf3f4f627faa3628ba9db0a0d79.jpg",
                    "https://olympustaff.com/uploads/manga_16790/167/6a88400f17d208a87cbc411ce3539301.jpg"
                ]
            },
            {
                "chapter": "168",
                "images": [
                    "https://olympustaff.com/uploads/manga_16790/168/a0da7040aab29ce27e6ff64069839c32.jpg",
                    "https://olympustaff.com/uploads/manga_16790/168/45383750877ea43298b0afafa5fccff1.jpg"
                ]
            },
            {
                "chapter": "169",
                "images": [
                    "https://olympustaff.com/uploads/manga_16790/169/dd48e737d88edc163bd393ac3368a189.jpg",
                    "https://olympustaff.com/uploads/manga_16790/169/b6f150bc429aac421197c06e456bca15.jpg"
                ]
            },
            {
                "chapter": "170",
                "images": [
                    "https://olympustaff.com/uploads/manga_16790/170/c56e0767659aab25414be3db826399e1.jpg",
                    "https://olympustaff.com/uploads/manga_16790/170/1fb97850d2293c07af168b35e801a4c5.jpg"
                ]
            },
            {
                "chapter": "171",
                "images": [
                    "https://olympustaff.com/uploads/manga_16790/171/e1e2222a87b0e6bcf621f7c2f8f93257.jpg",
                    "https://olympustaff.com/uploads/manga_16790/171/5ee8ee5c82699da4d77851cfb26c20ed.jpg",
                    "https://olympustaff.com/uploads/manga_16790/171/f3c4cbb0c0c6d0d67db127a8f7237609.jpg",
                    "https://olympustaff.com/uploads/manga_16790/171/887fb167516a7a684d1d03bf6db37c97.jpg",
                    "https://olympustaff.com/uploads/manga_16790/171/2d6028e5553ba7c8cfd72480641fcfb0.jpg",
                    "https://olympustaff.com/uploads/manga_16790/171/6ad5a5b7500413b25a67838d8c38a9b8.jpg",
                    "https://olympustaff.com/uploads/manga_16790/171/67fa37fdeb6eca05fb81b9b948b6683a.jpg",
                    "https://olympustaff.com/uploads/manga_16790/171/76366ff95b4991c91606a16b3cc73bfd.jpg",
                    "https://olympustaff.com/uploads/manga_16790/171/f7c4f1a0b55b545235d885f35d29a184.jpg",
                    "https://olympustaff.com/uploads/manga_16790/171/38a377457b6d3ed038a545b39ad0354f.jpg",
                    "https://olympustaff.com/uploads/manga_16790/171/5e48a78eac43c72b345c78bee74a30d7.jpg",
                    "https://olympustaff.com/uploads/manga_16790/171/a843217b0035c709d75f295baf29cfdb.jpg",
                    "https://olympustaff.com/uploads/manga_16790/171/5269d4fa51ad9af4fccde12ff4dbe665.jpg",
                    "https://olympustaff.com/uploads/manga_16790/171/851e955dcb0a57408e947331af9d7217.jpg",
                    "https://olympustaff.com/uploads/manga_16790/171/5cc36775b28a28f532422301d6adf97c.jpg",
                    "https://olympustaff.com/uploads/manga_16790/171/f89f9f03ef40fc1b744f914c7f3db66d.jpg",
                    "https://olympustaff.com/uploads/manga_16790/171/fadc9ae77e6ce93199fbf2fc2bea1f39.jpg",
                    "https://olympustaff.com/uploads/manga_16790/171/8bbca0d4054973151722ae9204aeb49d.jpg"
                ]
            },
            {
                "chapter": "172",
                "images": [
                    "https://olympustaff.com/uploads/manga_16790/172/c60205f3a05ab37457923af888594a10.jpg",
                    "https://olympustaff.com/uploads/manga_16790/172/bc2f1681d26e5fe7dd1a25febf7e1f1c.jpg",
                    "https://olympustaff.com/uploads/manga_16790/172/c7b71d03bcedcfde3a6e170137b6df30.jpg",
                    "https://olympustaff.com/uploads/manga_16790/172/3bbc70c9a844cea8f34c80b052c1c7f5.jpg",
                    "https://olympustaff.com/uploads/manga_16790/172/382f827c6cae5e551055e282aa3874bc.jpg",
                    "https://olympustaff.com/uploads/manga_16790/172/5ef80ae0f191d9937657af25866ab1ea.jpg",
                    "https://olympustaff.com/uploads/manga_16790/172/b849f35ae912dc460601b5798736caec.jpg",
                    "https://olympustaff.com/uploads/manga_16790/172/91883d3a744fa014d9df58ceb077e025.jpg",
                    "https://olympustaff.com/uploads/manga_16790/172/c3b2d98e2fd3f6ab643adf3fe592a40f.jpg",
                    "https://olympustaff.com/uploads/manga_16790/172/06b8c5f5410ed975b3ba14376020a8c6.jpg",
                    "https://olympustaff.com/uploads/manga_16790/172/8a29c75fedf2076a55074f764ae0fe1c.jpg",
                    "https://olympustaff.com/uploads/manga_16790/172/5bb4bb4a552ec3e16acd27012bdd9bf1.jpg",
                    "https://olympustaff.com/uploads/manga_16790/172/e81cb959b4537d6fdad5728d6af0fc69.jpg",
                    "https://olympustaff.com/uploads/manga_16790/172/278a44518c510c2d81dc43ec733c2b7c.jpg"
                ]
            },
            {
                "chapter": "173",
                "images": [
                    "https://olympustaff.com/uploads/manga_16790/173/9fd86db4b2c6ba18d3b61143bbecb28f.jpg",
                    "https://olympustaff.com/uploads/manga_16790/173/5bda14819b80622a5b4a865d34ffdccc.jpg",
                    "https://olympustaff.com/uploads/manga_16790/173/a87b8cc23aa0d38639723a52c7ca11e5.jpg",
                    "https://olympustaff.com/uploads/manga_16790/173/a8699ebd0f4c7f233923b2d0d2b4bdd5.jpg",
                    "https://olympustaff.com/uploads/manga_16790/173/5b53a1a677bd0d8661f62b215c326bdd.jpg",
                    "https://olympustaff.com/uploads/manga_16790/173/c5e001f652cd787b1cf2a10f3aac63d6.jpg",
                    "https://olympustaff.com/uploads/manga_16790/173/f376b0079f4655d52fffc095373dc197.jpg",
                    "https://olympustaff.com/uploads/manga_16790/173/5bd861bb127056d964b0b56529563eef.jpg",
                    "https://olympustaff.com/uploads/manga_16790/173/a3cde83e073556011e9edc59b685ee6a.jpg",
                    "https://olympustaff.com/uploads/manga_16790/173/25d33ba1a2d296743cd79544507b579d.jpg",
                    "https://olympustaff.com/uploads/manga_16790/173/0a8eeb2168d18a0b7ce51f12fb8aa826.jpg",
                    "https://olympustaff.com/uploads/manga_16790/173/a6c46d73b5b3dbba54e241a714b47056.jpg",
                    "https://olympustaff.com/uploads/manga_16790/173/577139dd24df27d64a576b95fd10e733.jpg",
                    "https://olympustaff.com/uploads/manga_16790/173/af7d77f92ebbe88517dd4f4280d866ab.jpg",
                    "https://olympustaff.com/uploads/manga_16790/173/ddca2d8972b6186d1e22b1b19e069bd4.jpg",
                    "https://olympustaff.com/uploads/manga_16790/173/9e223b88ddf60531e15e85a3a285da5e.jpg",
                    "https://olympustaff.com/uploads/manga_16790/173/34d3b10b2e1bc9fcc03cf9020333c934.jpg",
                    "https://olympustaff.com/uploads/manga_16790/173/cb99a1265b70feabc1ef84de58f58262.jpg",
                    "https://olympustaff.com/uploads/manga_16790/173/37e2e71763a401fd1fa65fd6e8208ed0.jpg",
                    "https://olympustaff.com/uploads/manga_16790/173/602e963f743176ad703bb7eb59df5c06.jpg"
                ]
            },
            {
                "chapter": "174",
                "images": [
                    "https://olympustaff.com/uploads/manga_16790/174/48599af80167841fa2ef4ae9df244256.jpg",
                    "https://olympustaff.com/uploads/manga_16790/174/0496921c5609d576fb2390d884119163.jpg",
                    "https://olympustaff.com/uploads/manga_16790/174/b3b26f67b5c436c2c8bf5696cdb89d6f.jpg",
                    "https://olympustaff.com/uploads/manga_16790/174/cbcd5cdc2fd10819fbd508e4e67ed518.jpg",
                    "https://olympustaff.com/uploads/manga_16790/174/26ff874e630f2ad0d829bf6ea2d4d2b0.jpg",
                    "https://olympustaff.com/uploads/manga_16790/174/4d620dfb25b04aaeedf3e4ee06120fe7.jpg",
                    "https://olympustaff.com/uploads/manga_16790/174/ee0a637f0ab2332ac506e69e01d14352.jpg",
                    "https://olympustaff.com/uploads/manga_16790/174/61223961b3fb6513d112e17c679d2f55.jpg",
                    "https://olympustaff.com/uploads/manga_16790/174/d4703959c710566d84b8668d3e0f2d6c.jpg",
                    "https://olympustaff.com/uploads/manga_16790/174/97ddd1161aa2fcf92c318eb176eb4a96.jpg",
                    "https://olympustaff.com/uploads/manga_16790/174/888ec57c42a06df4b5acb8e70602c347.jpg",
                    "https://olympustaff.com/uploads/manga_16790/174/8af9157a1cfaaa1f2ccc7d86395c04fc.jpg",
                    "https://olympustaff.com/uploads/manga_16790/174/cde0d82cbb35dc14f01473ce14d92fac.jpg",
                    "https://olympustaff.com/uploads/manga_16790/174/c790818bc3d7432d38a53d1bb7c6338c.jpg",
                    "https://olympustaff.com/uploads/manga_16790/174/ad4440c73d631c19cf0fb6ebc3d82d17.jpg",
                    "https://olympustaff.com/uploads/manga_16790/174/41cfaf7469116b1f0fa38aeae55f5c78.jpg",
                    "https://olympustaff.com/uploads/manga_16790/174/7d09270bcb7e87458f56f76209841c4e.jpg",
                    "https://olympustaff.com/uploads/manga_16790/174/287e3d05fbd52334716300669c3afbba.jpg",
                    "https://olympustaff.com/uploads/manga_16790/174/bcd06023e86f770eb4febdcb3e95cce3.jpg",
                    "https://olympustaff.com/uploads/manga_16790/174/11cbdb05e56fadc4328fa800bffdaf77.jpg",
                    "https://olympustaff.com/uploads/manga_16790/174/491eba76b139468a18812153dab4d1cb.jpg",
                    "https://olympustaff.com/uploads/manga_16790/174/d524ce04cf58ef39462fa0e338058e08.jpg",
                    "https://olympustaff.com/uploads/manga_16790/174/571aaa1853224c0b503cdab17d9f96ac.jpg"
                ]
            },
            {
                "chapter": "175",
                "images": [
                    "https://olympustaff.com/uploads/manga_16790/175/e36d6a8c72808ecdbf406ffbd1ac4e3c.jpg",
                    "https://olympustaff.com/uploads/manga_16790/175/26ece0bcd0100160310a7b2f575d25cb.jpg",
                    "https://olympustaff.com/uploads/manga_16790/175/ba4604cd99f11a9c0d0578e9a502df91.jpg",
                    "https://olympustaff.com/uploads/manga_16790/175/5cd1c59d6e536b357515a420e69fe7c9.jpg",
                    "https://olympustaff.com/uploads/manga_16790/175/7fcf3ba4553ab2fa056da98ac1724ef3.jpg",
                    "https://olympustaff.com/uploads/manga_16790/175/855768a886c565a06d039e6f7c48e99f.jpg",
                    "https://olympustaff.com/uploads/manga_16790/175/30389337213a238c92cd8e9f901713b5.jpg",
                    "https://olympustaff.com/uploads/manga_16790/175/3ab9f4b6d80ab220e53f707c3ff66811.jpg",
                    "https://olympustaff.com/uploads/manga_16790/175/d60941d03024183ed19d7d8c66f68be7.jpg",
                    "https://olympustaff.com/uploads/manga_16790/175/5a2ef24414d99c00eb499dc842f3c4be.jpg",
                    "https://olympustaff.com/uploads/manga_16790/175/9b6fbc43a69ff5758ee6f6b04e6aa448.jpg",
                    "https://olympustaff.com/uploads/manga_16790/175/7ebf0e3e6f9f7563f4b09ece7ff2de3e.jpg",
                    "https://olympustaff.com/uploads/manga_16790/175/c7be3b871cb0d5dc120f98156b772284.jpg",
                    "https://olympustaff.com/uploads/manga_16790/175/5c929af9a4966744ba6d9b87031e8381.jpg",
                    "https://olympustaff.com/uploads/manga_16790/175/e32bb71b9b7aa0e1ae66e09ee623fa0f.jpg",
                    "https://olympustaff.com/uploads/manga_16790/175/55801e6887f751cd6942451bc6f1727c.jpg",
                    "https://olympustaff.com/uploads/manga_16790/175/af9faf283dadb2ac66290b42886a7c49.jpg",
                    "https://olympustaff.com/uploads/manga_16790/175/47e161c0f8b42fe7d886ab3af2ed0d74.jpg"
                ]
            },
            {
                "chapter": "176",
                "images": [
                    "https://olympustaff.com/uploads/manga_16790/176/28f4acb873c4acf2e1bd0fe6ed5eedf0.jpg",
                    "https://olympustaff.com/uploads/manga_16790/176/506f3a964708c7e86d2d57031f6747b3.jpg",
                    "https://olympustaff.com/uploads/manga_16790/176/fb9c44c996eb95d71bef8351617f11db.jpg",
                    "https://olympustaff.com/uploads/manga_16790/176/553e2ceafd096974476537ba01ba482c.jpg",
                    "https://olympustaff.com/uploads/manga_16790/176/1d7c2b46c0c224675745f3b9f263e9a9.jpg",
                    "https://olympustaff.com/uploads/manga_16790/176/a912a677075420c44c71fe7f444da772.jpg",
                    "https://olympustaff.com/uploads/manga_16790/176/d277a672a8cef3bbdfd0ce217b786562.jpg",
                    "https://olympustaff.com/uploads/manga_16790/176/73c982205fc6238de74b9509b57fc0c7.jpg",
                    "https://olympustaff.com/uploads/manga_16790/176/c32a3fcc68b2d0b2d321e78669a6be0b.jpg",
                    "https://olympustaff.com/uploads/manga_16790/176/8b80d5c504ab2331ba4600e6f59a13a1.jpg",
                    "https://olympustaff.com/uploads/manga_16790/176/08d8f93b2e73205988ec455d3449b05e.jpg",
                    "https://olympustaff.com/uploads/manga_16790/176/30d6ac4a3fd604ac651bb896002b1d50.jpg",
                    "https://olympustaff.com/uploads/manga_16790/176/2ce100475ec683607cb2a4921853b06d.jpg"
                ]
            },
            {
                "chapter": "177",
                "images": [
                    "https://olympustaff.com/uploads/manga_16790/177/615d69a3e67fa379c403a6b192e2a920.00.jpg",
                    "https://olympustaff.com/uploads/manga_16790/177/4d5c64e84f573f9459ce0abe3fab18ae.01.jpg",
                    "https://olympustaff.com/uploads/manga_16790/177/98fbb67dc152fa59c76d062206805b20.02.jpg",
                    "https://olympustaff.com/uploads/manga_16790/177/db2910780f101099531a7399968ca3a3.03.jpg",
                    "https://olympustaff.com/uploads/manga_16790/177/3de0979fec1b8b432b4119c22806b0cf.04.jpg",
                    "https://olympustaff.com/uploads/manga_16790/177/2e101c084eb54da90c488d534128a4aa.05.jpg",
                    "https://olympustaff.com/uploads/manga_16790/177/3f528f76b2b9326a06d42e8843537eb0.06.jpg",
                    "https://olympustaff.com/uploads/manga_16790/177/a5cce072309aeec3b1020112af281500.07.jpg",
                    "https://olympustaff.com/uploads/manga_16790/177/f28c80a45a03f75fd06fbfe3bbddd984.08.jpg",
                    "https://olympustaff.com/uploads/manga_16790/177/e1c94683d6c66b6e7e5dffce17e0e92d.09.jpg",
                    "https://olympustaff.com/uploads/manga_16790/177/315e9cbccf8db3e0387bd7e4c7c6c103.10.jpg",
                    "https://olympustaff.com/uploads/manga_16790/177/f9c84c0b74179a2be04b4176ffed2184.11.jpg",
                    "https://olympustaff.com/uploads/manga_16790/177/0dc2d98c444a292023c7f1e5b2865ba9.12.jpg",
                    "https://olympustaff.com/uploads/manga_16790/177/b2abbe19a2cf6e1ac93d886042cf8d0e.13.jpg",
                    "https://olympustaff.com/uploads/manga_16790/177/ab31edbd21d94a6f0b860d0db27d4259.14.jpg",
                    "https://olympustaff.com/uploads/manga_16790/177/96597d5601b6ffb6f07d95edfd57fee5.15.jpg",
                    "https://olympustaff.com/uploads/manga_16790/177/551f275a66e2179fb5490eda1b0241b3.d778e901c98103c1.jpg"
                ]
            },
            {
                "chapter": "178",
                "images": [
                    "https://olympustaff.com/uploads/manga_16790/178/4eb63a15a2abaf7c4ae32e2debf3b1d4.jpg",
                    "https://olympustaff.com/uploads/manga_16790/178/5dae2619e3dbea9884f3b4f592d4df1e.jpg",
                    "https://olympustaff.com/uploads/manga_16790/178/29fa2b348fbff81a0f4c1e2ff0e43c8a.jpg",
                    "https://olympustaff.com/uploads/manga_16790/178/15549ea69075e63bc5ed6480a46f5366.jpg",
                    "https://olympustaff.com/uploads/manga_16790/178/0b4efa7048e163bba5e3b0d0a603f1dc.jpg",
                    "https://olympustaff.com/uploads/manga_16790/178/62611f3ec4e6fab623782bbc42e86458.jpg",
                    "https://olympustaff.com/uploads/manga_16790/178/06046ae054464cdc43a59d9aa60fced0.jpg",
                    "https://olympustaff.com/uploads/manga_16790/178/a600e61da3b9f7002ff719d01946d7ea.jpg",
                    "https://olympustaff.com/uploads/manga_16790/178/9bcba09157610d77ecbfa29e05456e3e.jpg",
                    "https://olympustaff.com/uploads/manga_16790/178/c1021f40058e58726f3252880c87450f.jpg",
                    "https://olympustaff.com/uploads/manga_16790/178/17a1790ddeb845227aed25c9322e8d3d.jpg",
                    "https://olympustaff.com/uploads/manga_16790/178/559b153ac95a7d1c7a8b28f804987a97.jpg",
                    "https://olympustaff.com/uploads/manga_16790/178/083659b79b80969e7628cfdc2333d2c1.jpg",
                    "https://olympustaff.com/uploads/manga_16790/178/220b7dbda364794d6f5ee88f2856fc27.jpg",
                    "https://olympustaff.com/uploads/manga_16790/178/7a7db18bd10488c93416bfe0fe109d3f.d778e901c98103c1.jpg"
                ]
            },
            {
                "chapter": "179",
                "images": [
                    "https://olympustaff.com/uploads/manga_16790/179/3213011fcd767e870ac1d461a15843b8.jpg",
                    "https://olympustaff.com/uploads/manga_16790/179/b07a1863ff10e73cbb1530d38f8b0997.jpg",
                    "https://olympustaff.com/uploads/manga_16790/179/b72911a7c8f0ad705b29968c5ce75eab.jpg",
                    "https://olympustaff.com/uploads/manga_16790/179/05f2b2fe4f46275f39ae95e4882a6276.jpg",
                    "https://olympustaff.com/uploads/manga_16790/179/994360e6f25e15fd34680208687e2a32.jpg",
                    "https://olympustaff.com/uploads/manga_16790/179/70995b987115cbaf6da3e11e64a24ded.jpg",
                    "https://olympustaff.com/uploads/manga_16790/179/6c5d0bc127e878ed2b164f5b9af364b6.jpg",
                    "https://olympustaff.com/uploads/manga_16790/179/bd61aec5540f567ad6aadacb7becd7ad.jpg",
                    "https://olympustaff.com/uploads/manga_16790/179/9f23ddf0fd9c5fbd05d93d71f582aa97.jpg",
                    "https://olympustaff.com/uploads/manga_16790/179/7d9c621f9cb8b0906ae7b66e0771a59a.jpg",
                    "https://olympustaff.com/uploads/manga_16790/179/f356feb15217a73741e3703f30052762.jpg",
                    "https://olympustaff.com/uploads/manga_16790/179/0d8d6bb2297eb32b7847fd1b719f367a.jpg",
                    "https://olympustaff.com/uploads/manga_16790/179/310a7fd19cee0affcda124d60ca32bc5.d778e901c98103c1.jpg"
                ]
            }
        ]
    }
}