{
    "anime1": {
        "info": {
            "title": "The Path Toward Heaven",
            "story": "مانجا The Path Toward Heaven مترجمةThe Path Toward Heaven نبضات القلب، والخيال اللامتناهي، والرياح تتأرجح بآلاف الموجات ، الشباب دمائهم مشتعلة مثل النار! قارة السماء، طائفة السيف الذروة، نور السيف انبثق من قمته وحيد...",
            "image": "https://olympustaff.com/images/manga/20793879581036741820.jpg"
        },
        "chapters": [
            {
                "chapter": "1",
                "images": [
                    "https://olympustaff.com/uploads/manga_34173/1/0d7771cffa9a885bfa59187f83545ccd.webp",
                    "https://olympustaff.com/uploads/manga_34173/1/abb99e4f216ec5008accde3e58c2e610.webp",
                    "https://olympustaff.com/uploads/manga_34173/1/a94080fff48cb58dff97448f34b79586.webp",
                    "https://olympustaff.com/uploads/manga_34173/1/df6152ba7956eae2d0cbaf53ae0796ba.webp",
                    "https://olympustaff.com/uploads/manga_34173/1/e13219188bbb82abc3df4f6b42c4eeb8.webp",
                    "https://olympustaff.com/uploads/manga_34173/1/5d7117f8c385e6b7a1768846480c89c9.webp"
                ]
            },
            {
                "chapter": "2",
                "images": [
                    "https://olympustaff.com/uploads/manga_34173/2/00.webp",
                    "https://olympustaff.com/uploads/manga_34173/2/01.webp",
                    "https://olympustaff.com/uploads/manga_34173/2/02.webp",
                    "https://olympustaff.com/uploads/manga_34173/2/03.webp",
                    "https://olympustaff.com/uploads/manga_34173/2/04.webp"
                ]
            },
            {
                "chapter": "3",
                "images": [
                    "https://olympustaff.com/uploads/manga_34173/3/00.webp",
                    "https://olympustaff.com/uploads/manga_34173/3/01.webp",
                    "https://olympustaff.com/uploads/manga_34173/3/02.webp",
                    "https://olympustaff.com/uploads/manga_34173/3/03.webp",
                    "https://olympustaff.com/uploads/manga_34173/3/04.webp"
                ]
            },
            {
                "chapter": "4",
                "images": [
                    "https://olympustaff.com/uploads/manga_34173/4/00.webp",
                    "https://olympustaff.com/uploads/manga_34173/4/01.webp",
                    "https://olympustaff.com/uploads/manga_34173/4/02.webp",
                    "https://olympustaff.com/uploads/manga_34173/4/03.webp",
                    "https://olympustaff.com/uploads/manga_34173/4/04.webp"
                ]
            },
            {
                "chapter": "5",
                "images": [
                    "https://olympustaff.com/uploads/manga_34173/5/00.webp",
                    "https://olympustaff.com/uploads/manga_34173/5/01.webp",
                    "https://olympustaff.com/uploads/manga_34173/5/02.webp",
                    "https://olympustaff.com/uploads/manga_34173/5/03.webp",
                    "https://olympustaff.com/uploads/manga_34173/5/04.webp"
                ]
            },
            {
                "chapter": "6",
                "images": [
                    "https://olympustaff.com/uploads/manga_34173/6/00.webp",
                    "https://olympustaff.com/uploads/manga_34173/6/01.webp",
                    "https://olympustaff.com/uploads/manga_34173/6/02.webp",
                    "https://olympustaff.com/uploads/manga_34173/6/03.webp",
                    "https://olympustaff.com/uploads/manga_34173/6/04.webp"
                ]
            },
            {
                "chapter": "7",
                "images": [
                    "https://olympustaff.com/uploads/manga_34173/7/00.webp",
                    "https://olympustaff.com/uploads/manga_34173/7/01.webp",
                    "https://olympustaff.com/uploads/manga_34173/7/02.webp",
                    "https://olympustaff.com/uploads/manga_34173/7/03.webp",
                    "https://olympustaff.com/uploads/manga_34173/7/04.webp"
                ]
            },
            {
                "chapter": "8",
                "images": [
                    "https://olympustaff.com/uploads/manga_34173/8/00.webp",
                    "https://olympustaff.com/uploads/manga_34173/8/01.webp",
                    "https://olympustaff.com/uploads/manga_34173/8/02.webp",
                    "https://olympustaff.com/uploads/manga_34173/8/03.webp",
                    "https://olympustaff.com/uploads/manga_34173/8/04.webp"
                ]
            },
            {
                "chapter": "9",
                "images": [
                    "https://olympustaff.com/uploads/manga_34173/9/00.webp",
                    "https://olympustaff.com/uploads/manga_34173/9/01.webp",
                    "https://olympustaff.com/uploads/manga_34173/9/02.webp",
                    "https://olympustaff.com/uploads/manga_34173/9/03.webp"
                ]
            },
            {
                "chapter": "10",
                "images": [
                    "https://olympustaff.com/uploads/manga_34173/10/00.webp",
                    "https://olympustaff.com/uploads/manga_34173/10/01.webp",
                    "https://olympustaff.com/uploads/manga_34173/10/02.webp",
                    "https://olympustaff.com/uploads/manga_34173/10/03.webp",
                    "https://olympustaff.com/uploads/manga_34173/10/04.webp"
                ]
            },
            {
                "chapter": "11",
                "images": [
                    "https://olympustaff.com/uploads/manga_34173/11/00.webp",
                    "https://olympustaff.com/uploads/manga_34173/11/01.webp",
                    "https://olympustaff.com/uploads/manga_34173/11/02.webp",
                    "https://olympustaff.com/uploads/manga_34173/11/03.webp"
                ]
            },
            {
                "chapter": "12",
                "images": [
                    "https://olympustaff.com/uploads/manga_34173/12/efb6458830b074e2d030fd7e90f885e8.01.webp",
                    "https://olympustaff.com/uploads/manga_34173/12/caff90e2013fbb5d712b41447a442bcb.02.webp",
                    "https://olympustaff.com/uploads/manga_34173/12/407aa267bc4ed1be536b0f1d6662551f.03.webp"
                ]
            },
            {
                "chapter": "13",
                "images": [
                    "https://olympustaff.com/uploads/manga_34173/13/f77abf2efd1e58107f58d582e617222f.01.webp",
                    "https://olympustaff.com/uploads/manga_34173/13/0b8b86426ff79109035452e11ccaf6f0.02.webp",
                    "https://olympustaff.com/uploads/manga_34173/13/7ce34e3affa5c6237e47c3e6ae49bd28.03.webp"
                ]
            },
            {
                "chapter": "14",
                "images": [
                    "https://olympustaff.com/uploads/manga_34173/14/79cce5730748a3b1a1409aae0e29a2ce.01.webp",
                    "https://olympustaff.com/uploads/manga_34173/14/b8ff6d60519550de8159e4cca9d02ad0.02.webp",
                    "https://olympustaff.com/uploads/manga_34173/14/a37eb286c09c3b3f1f3d42497786ab55.03.webp"
                ]
            },
            {
                "chapter": "15",
                "images": [
                    "https://olympustaff.com/uploads/manga_34173/15/1b61701b50f8dc8a812be9736842a64a.01.webp",
                    "https://olympustaff.com/uploads/manga_34173/15/2149bca550886884a86d22574d559e29.02.webp",
                    "https://olympustaff.com/uploads/manga_34173/15/9f9d36ee700d1fc11184e9d4a61be2ce.03.webp"
                ]
            },
            {
                "chapter": "16",
                "images": [
                    "https://olympustaff.com/uploads/manga_34173/16/b66a5b06fb28ec0f142a3f92f2b0f310.01_11zon.webp",
                    "https://olympustaff.com/uploads/manga_34173/16/ac2cb83ca5b1936188e9e309948c6e8f.02_11zon.webp",
                    "https://olympustaff.com/uploads/manga_34173/16/095dfa49d16bbaca794e82b1890de93d.03_11zon.jpeg"
                ]
            },
            {
                "chapter": "17",
                "images": [
                    "https://olympustaff.com/uploads/manga_34173/17/383ea1a5f55e87c2691c7895a5d3bee6.webp",
                    "https://olympustaff.com/uploads/manga_34173/17/d42372dae9420bffb504f12537a4a307.webp",
                    "https://olympustaff.com/uploads/manga_34173/17/46583439f9c5879ed59f26a8e584fa93.webp",
                    "https://olympustaff.com/uploads/manga_34173/17/9cb8db0b436dba0a3e2809219e179979.webp",
                    "https://olympustaff.com/uploads/manga_34173/17/854477966fb243b59419ee63af7ecbf2.webp"
                ]
            },
            {
                "chapter": "18",
                "images": [
                    "https://olympustaff.com/uploads/manga_34173/18/e0e3bc029b9ab8e61c581fa194931274.webp",
                    "https://olympustaff.com/uploads/manga_34173/18/7a4ddcc79c3f95a2a4c8f350e7432e98.webp",
                    "https://olympustaff.com/uploads/manga_34173/18/63a23c8dfac6b167c4f7472f9f1ecf29.webp",
                    "https://olympustaff.com/uploads/manga_34173/18/f17599902910b831cdd10d9ef2a680c3.webp",
                    "https://olympustaff.com/uploads/manga_34173/18/1af72de94012a949f56f0a5671b40fce.webp"
                ]
            },
            {
                "chapter": "19",
                "images": [
                    "https://olympustaff.com/uploads/manga_34173/19/057509ff5b0aa1d3957b8c1461d2d65f.webp",
                    "https://olympustaff.com/uploads/manga_34173/19/f54e54f9dc1c9a88a25d83b81f6fbcc0.webp",
                    "https://olympustaff.com/uploads/manga_34173/19/e7b00415e8da12c097b34b1f078791b2.webp"
                ]
            },
            {
                "chapter": "20",
                "images": [
                    "https://olympustaff.com/uploads/manga_34173/20/0e11a7f69f1a0fb09e19a1dd87500f92.01.webp",
                    "https://olympustaff.com/uploads/manga_34173/20/3ab6a1c7b23cbc0c84e3b7bfd87c728a.02.webp"
                ]
            },
            {
                "chapter": "21",
                "images": [
                    "https://olympustaff.com/uploads/manga_34173/21/59cb092e962a5e48ac2ed50a0da7d1c9.01.webp",
                    "https://olympustaff.com/uploads/manga_34173/21/6ec679898e6f10e111c75a24d37ad8e7.02.webp"
                ]
            },
            {
                "chapter": "22",
                "images": [
                    "https://olympustaff.com/uploads/manga_34173/22/da7e42e815d6c57924f97975c1649c39.webp",
                    "https://olympustaff.com/uploads/manga_34173/22/3e73b8a5047845574c362c009120b41a.webp",
                    "https://olympustaff.com/uploads/manga_34173/22/4dcb198b70c308f27c3d4a93fc4e6952.webp"
                ]
            },
            {
                "chapter": "23",
                "images": [
                    "https://olympustaff.com/uploads/manga_34173/23/1d7008cfda763db5ffedd6fce5c84105.webp",
                    "https://olympustaff.com/uploads/manga_34173/23/5e45605a3a7909380883eb2541094d25.webp",
                    "https://olympustaff.com/uploads/manga_34173/23/b3aa6d44fa864ad7c08c4e351046c82f.webp"
                ]
            },
            {
                "chapter": "24",
                "images": [
                    "https://olympustaff.com/uploads/manga_34173/24/b8deb294e2a9e79258d72488231108b8.webp",
                    "https://olympustaff.com/uploads/manga_34173/24/fa65f1f7746cce0685da9245156a678d.webp",
                    "https://olympustaff.com/uploads/manga_34173/24/eb1006b2ba5244d049ef80c53be1b2a2.webp"
                ]
            },
            {
                "chapter": "25",
                "images": [
                    "https://olympustaff.com/uploads/manga_34173/25/1b256b3faa3fade3b1ed48bde87f1b1e.0001 - 0-NyGZ9-nKfRyMB-m.jpg",
                    "https://olympustaff.com/uploads/manga_34173/25/ece9a5641a50a2bb1889b9e86fd701de.0002 - 1-zSVMm6VkvUUu--m.jpg",
                    "https://olympustaff.com/uploads/manga_34173/25/aff5dab4162ebd5229f2a94cc9bfb547.0003 - 2-sbAr3Um4-yv7U-m.jpg",
                    "https://olympustaff.com/uploads/manga_34173/25/69326f80f141525cb7039f0cdb14df2a.0004 - 3-49xbPnS2OOpMS-m.jpg",
                    "https://olympustaff.com/uploads/manga_34173/25/d5fa239719dc7445a17e60b2d3a3eef9.0005 - 4-0CzB_YsMN_Dbo-m.jpg"
                ]
            },
            {
                "chapter": "26",
                "images": [
                    "https://olympustaff.com/uploads/manga_34173/26/ffd8d9d1498e51a2190a393f233bcb72.01.jpg",
                    "https://olympustaff.com/uploads/manga_34173/26/3b220d34df816716d4654c5a24261e7d.02.jpg",
                    "https://olympustaff.com/uploads/manga_34173/26/f6a2bbb7a5ae8896d1e05b1e1655bc61.03.jpg"
                ]
            },
            {
                "chapter": "27",
                "images": [
                    "https://olympustaff.com/uploads/manga_34173/27/72cd8e454242ef19a801abf62e1c25ea.01 copy.jpg",
                    "https://olympustaff.com/uploads/manga_34173/27/834a0d79888d0603ac959a11b497e78f.02 copy.jpg",
                    "https://olympustaff.com/uploads/manga_34173/27/6aa8bca7ba16e6ece63606df50e0c04f.03 copy.jpg",
                    "https://olympustaff.com/uploads/manga_34173/27/a885786e7da22139e3e34396eec411df.04 copy.jpg"
                ]
            },
            {
                "chapter": "28",
                "images": [
                    "https://olympustaff.com/uploads/manga_34173/28/8c6b0ec7bff0319e7b4854c9262e250b.01 copy.jpg",
                    "https://olympustaff.com/uploads/manga_34173/28/004db1dd3f246443bdb2e6bca47c3832.02 copy.jpg",
                    "https://olympustaff.com/uploads/manga_34173/28/c1a3171f5ee8db128bfe32e6fa9292e3.03 copy.jpg",
                    "https://olympustaff.com/uploads/manga_34173/28/3561242725102d5e1eb84ea666ed43f4.04 copy.jpg"
                ]
            },
            {
                "chapter": "29",
                "images": [
                    "https://olympustaff.com/uploads/manga_34173/29/4bdc0751b6e2eb31af0607173b850644.01.jpg",
                    "https://olympustaff.com/uploads/manga_34173/29/ffd95847395f86c38786f43f5099d9a2.02.jpg",
                    "https://olympustaff.com/uploads/manga_34173/29/6b9b801de7dab12cb39e5edecb5fe002.03.jpg",
                    "https://olympustaff.com/uploads/manga_34173/29/8dd242cacd3331e255b149a083921948.04.jpg"
                ]
            },
            {
                "chapter": "30",
                "images": [
                    "https://olympustaff.com/uploads/manga_34173/30/b509c8eb1a2cd8a86b84a66dd430e8ab.DM_20250121030149_001.jpg",
                    "https://olympustaff.com/uploads/manga_34173/30/a4c5bf73723db0ccf62f394991897172.DM_20250121030149_002.jpg",
                    "https://olympustaff.com/uploads/manga_34173/30/4799305b43eae5a407f9df06096710c3.DM_20250121030149_003.jpg",
                    "https://olympustaff.com/uploads/manga_34173/30/12e7e8ad4a51ad93c9b18e1586fcff71.DM_20250121030149_004.jpg",
                    "https://olympustaff.com/uploads/manga_34173/30/de15772342b8b7a8aeea7d933198b4e9.DM_20250121030149_005.jpg",
                    "https://olympustaff.com/uploads/manga_34173/30/891f0d922c75841f46b19b8490bf719d.DM_20250121030149_006.jpg"
                ]
            },
            {
                "chapter": "31",
                "images": [
                    "https://olympustaff.com/uploads/manga_34173/31/fc496ee01d797ec0263bacb552ba837d.DM_20250121030214_001.jpg",
                    "https://olympustaff.com/uploads/manga_34173/31/d4ab925315b805ebf62cc8e4db451127.DM_20250121030214_002.jpg",
                    "https://olympustaff.com/uploads/manga_34173/31/6e537a5388871b41c2961061d6d84fe1.DM_20250121030214_003.jpg",
                    "https://olympustaff.com/uploads/manga_34173/31/c90e0799d83afec2c2a2b1e260c1b61b.DM_20250121030214_004.jpg",
                    "https://olympustaff.com/uploads/manga_34173/31/c81ee73b77f8685bad5c3f06a162ba84.DM_20250121030214_005.jpg",
                    "https://olympustaff.com/uploads/manga_34173/31/9e2dcfc6c473d7b9d089b5312280151b.DM_20250121030214_006.jpg"
                ]
            },
            {
                "chapter": "32",
                "images": [
                    "https://olympustaff.com/uploads/manga_34173/32/4956f85e6ee8191571d321b0517901b9.DM_20250126120213_001.jpg",
                    "https://olympustaff.com/uploads/manga_34173/32/cc8ef4e15e5dbb38dc393793233dbf91.DM_20250126120213_002.jpg",
                    "https://olympustaff.com/uploads/manga_34173/32/0841d27b3b4d10b41e274290b83496c9.DM_20250126120213_003.jpg"
                ]
            },
            {
                "chapter": "33",
                "images": [
                    "https://olympustaff.com/uploads/manga_34173/33/caa008db3467ff0de16ae6fa6703811f.DM_20250126120239_001.jpg",
                    "https://olympustaff.com/uploads/manga_34173/33/4956d68060007057c600f364f43e27cd.DM_20250126120239_002.jpg",
                    "https://olympustaff.com/uploads/manga_34173/33/071f2adc87a508ab4c74391364aca275.DM_20250126120239_003.jpg",
                    "https://olympustaff.com/uploads/manga_34173/33/94600f05c12c309d7971e7dcc4389724.DM_20250126120239_004.jpg",
                    "https://olympustaff.com/uploads/manga_34173/33/a24e2807b04cddfa48837edef2faf1c1.DM_20250126120239_005.jpg",
                    "https://olympustaff.com/uploads/manga_34173/33/104cfc535e981cf7073460903f57be9b.DM_20250126120239_006.jpg"
                ]
            },
            {
                "chapter": "34",
                "images": [
                    "https://olympustaff.com/uploads/manga_34173/34/dd07518b7d05d3a2906d7ad6b1429685.DM_20250209182241_001.jpg",
                    "https://olympustaff.com/uploads/manga_34173/34/6ad888002f75c2e6470374cc9c5814dc.DM_20250209182241_002.jpg",
                    "https://olympustaff.com/uploads/manga_34173/34/f4cc546b17cc0e3191cab024e8ef3793.DM_20250209182241_003.jpg",
                    "https://olympustaff.com/uploads/manga_34173/34/8b9724197ce8eb51967485150e381962.DM_20250209182241_004.jpg"
                ]
            },
            {
                "chapter": "35",
                "images": [
                    "https://olympustaff.com/uploads/manga_34173/35/907aabf005415a940f3d50687e72a92f.DM_20250209182301_001.jpg",
                    "https://olympustaff.com/uploads/manga_34173/35/e204c9b4bd69e56b2f0d4362e35b3ff2.DM_20250209182301_002.jpg",
                    "https://olympustaff.com/uploads/manga_34173/35/46bd846420f1dce0f403a62cf6ea077f.DM_20250209182301_003.jpg",
                    "https://olympustaff.com/uploads/manga_34173/35/984f3f3a7f06e90a025fe3f757a09125.DM_20250209182301_004.jpg",
                    "https://olympustaff.com/uploads/manga_34173/35/835ff08b2da9e73c54536ddbb69d2105.DM_20250209182301_005.jpg",
                    "https://olympustaff.com/uploads/manga_34173/35/7178ba12835ea696cc7c85b8db8b9604.DM_20250209182301_006.jpg"
                ]
            },
            {
                "chapter": "36",
                "images": [
                    "https://olympustaff.com/uploads/manga_34173/36/d73c148d9bda7d89c453dfa983686267.jpg",
                    "https://olympustaff.com/uploads/manga_34173/36/e236a608fb474b02951ae549a0459221.jpg"
                ]
            },
            {
                "chapter": "37",
                "images": [
                    "https://olympustaff.com/uploads/manga_34173/37/ee889a3fd574c289ae36d463f627e4cf.jpg",
                    "https://olympustaff.com/uploads/manga_34173/37/39c443c648e57c23e0c8fb5402ff2507.jpg",
                    "https://olympustaff.com/uploads/manga_34173/37/e6c023766dc8aaa929d9ce17e67658a0.jpg",
                    "https://olympustaff.com/uploads/manga_34173/37/9466737cd8ce3c9d70aa7b069e07a6c2.jpg"
                ]
            },
            {
                "chapter": "38",
                "images": [
                    "https://olympustaff.com/uploads/manga_34173/38/a80bcfc301d8ac3df096d5348640ab5e.jpg",
                    "https://olympustaff.com/uploads/manga_34173/38/d6d73de0f6e0a15e7359152100d7176d.jpg",
                    "https://olympustaff.com/uploads/manga_34173/38/cc1cf48cc977ee6d0e8c3271007d2d72.jpg",
                    "https://olympustaff.com/uploads/manga_34173/38/b5d54e9eebaeaef586f3c08435c37ea8.jpg",
                    "https://olympustaff.com/uploads/manga_34173/38/5c713a4c33516fe7911db8909122f4af.jpg"
                ]
            },
            {
                "chapter": "39",
                "images": [
                    "https://olympustaff.com/uploads/manga_34173/39/7437f1dfad39888d63743b93a5aa8dee.DM_20250209182551_001.jpg",
                    "https://olympustaff.com/uploads/manga_34173/39/030169c742658756042cd720775ece68.DM_20250209182551_002.jpg",
                    "https://olympustaff.com/uploads/manga_34173/39/6b7f79d3f4ffa7aad4a1c50132a38f21.DM_20250209182551_003.jpg"
                ]
            },
            {
                "chapter": "40",
                "images": [
                    "https://olympustaff.com/uploads/manga_34173/40/7d6f2cef4448e5529fb8588298ac7314.DM_20250220181304_002.jpg",
                    "https://olympustaff.com/uploads/manga_34173/40/d62c550b6d7f4c8b81e938a559430e3d.DM_20250220181304_003.jpg",
                    "https://olympustaff.com/uploads/manga_34173/40/31806538a24ac6446fff9285b74c73ac.DM_20250220181304_004.jpg"
                ]
            },
            {
                "chapter": "41",
                "images": [
                    "https://olympustaff.com/uploads/manga_34173/41/910e55ab1328d3067ca823331b8f87f1.DM_20250225011140_001.jpg",
                    "https://olympustaff.com/uploads/manga_34173/41/fd5b71fad1c53e20286c236bb45047ec.DM_20250225011140_002.jpg",
                    "https://olympustaff.com/uploads/manga_34173/41/b66313996208dcc51a10242e244c282f.DM_20250225011140_003.jpg",
                    "https://olympustaff.com/uploads/manga_34173/41/0018b1b602b2b471cf59f25f293e3558.DM_20250225011140_004.JPEG"
                ]
            },
            {
                "chapter": "42",
                "images": [
                    "https://olympustaff.com/uploads/manga_34173/42/ae99c83d9fc901b87e2b2c8816920167.01.jpg",
                    "https://olympustaff.com/uploads/manga_34173/42/dec09f3f666add770f206b88098d9e95.02.jpg",
                    "https://olympustaff.com/uploads/manga_34173/42/64c32066eb7dcc3db9b76bc35b8a52dd.03.jpg",
                    "https://olympustaff.com/uploads/manga_34173/42/16a08b9f82a17b69593431a14fae9093.04.jpg",
                    "https://olympustaff.com/uploads/manga_34173/42/5a59eab9018d4b733192dfcaa773e521.05.jpg",
                    "https://olympustaff.com/uploads/manga_34173/42/48fb2b584f4c19f13bc53ce69d0978e2.06.jpg",
                    "https://olympustaff.com/uploads/manga_34173/42/6823404d5b2fe24a23a13b83976597be.07.jpg"
                ]
            },
            {
                "chapter": "43",
                "images": [
                    "https://olympustaff.com/uploads/manga_34173/43/182a010473ca57d27df431a5cb05b08e.01.jpg",
                    "https://olympustaff.com/uploads/manga_34173/43/7302c344fde6872e79bd89c73c1b6194.02.jpg",
                    "https://olympustaff.com/uploads/manga_34173/43/fe92b28da99e00ea58c5bed3a769e9fc.03.jpg",
                    "https://olympustaff.com/uploads/manga_34173/43/459f994302c4546cd62cee0dab48c64e.04.jpg"
                ]
            },
            {
                "chapter": "44",
                "images": [
                    "https://olympustaff.com/uploads/manga_34173/44/aa603063439d7bdb69b2e60fa0bacfe8.01_1.jpg",
                    "https://olympustaff.com/uploads/manga_34173/44/c294e60a43f34d860e1a45a31333cb04.02_1.jpg",
                    "https://olympustaff.com/uploads/manga_34173/44/cefc634f35f4ff6777a85cd8f49ef66d.03_1.jpg",
                    "https://olympustaff.com/uploads/manga_34173/44/126a02bfcf8ecb374e6f92b42492605c.04_1.jpg"
                ]
            },
            {
                "chapter": "45",
                "images": [
                    "https://olympustaff.com/uploads/manga_34173/45/7a48489975413e5fb0273ec94dd2350a.DM_20250319204314_002.JPEG",
                    "https://olympustaff.com/uploads/manga_34173/45/b819b31c7effc13a9ac63ddfdf6c9d52.DM_20250319204314_003.jpg",
                    "https://olympustaff.com/uploads/manga_34173/45/74de7b08774e52b57ffeeb91627a8bde.DM_20250319204314_004.jpg",
                    "https://olympustaff.com/uploads/manga_34173/45/aace28f01e52dc371d03b99086b1dc3b.DM_20250319204314_005.JPEG",
                    "https://olympustaff.com/uploads/manga_34173/45/0602a3cba24b3a473ba83b89cd155af3.DM_20250319204314_006.JPEG",
                    "https://olympustaff.com/uploads/manga_34173/45/31dd4ff06d804a1fb75587d2439cc4d6.DM_20250319204314_007.JPEG",
                    "https://olympustaff.com/uploads/manga_34173/45/76a020868324e0130325d7daef026903.DM_20250319204314_008.JPEG",
                    "https://olympustaff.com/uploads/manga_34173/45/77ded784d0fe2add74a629afe2927e3c.DM_20250319204314_009.JPEG",
                    "https://olympustaff.com/uploads/manga_34173/45/32e125423c597bd75d177abec2682aef.DM_20250319204314_010.JPEG",
                    "https://olympustaff.com/uploads/manga_34173/45/c2651041980233ba2922144c54079d0f.DM_20250319204314_011.JPEG",
                    "https://olympustaff.com/uploads/manga_34173/45/fb53af14467de8cc261109f8b707b8d5.DM_20250319204314_012.JPEG",
                    "https://olympustaff.com/uploads/manga_34173/45/2aed27e182e6db6ec73af25d1e736690.DM_20250319204314_013.JPEG",
                    "https://olympustaff.com/uploads/manga_34173/45/2ef8555e04a4fcc40dd723536f017c19.DM_20250319204314_014.jpg",
                    "https://olympustaff.com/uploads/manga_34173/45/35f498ea8a2878a73a1434ee8c992f7e.DM_20250319204314_015.JPEG",
                    "https://olympustaff.com/uploads/manga_34173/45/4ec6d3f8096ce9b732050709205fe9be.DM_20250319204314_016.JPEG",
                    "https://olympustaff.com/uploads/manga_34173/45/05e983b2953538e82a3ddce30432ad0c.DM_20250319204314_017.JPEG",
                    "https://olympustaff.com/uploads/manga_34173/45/8f87c8841d86169add2a092f751965bd.DM_20250319204314_018.JPEG",
                    "https://olympustaff.com/uploads/manga_34173/45/d7f6aad69988c32a5ab497adfac225f6.DM_20250319204314_019.JPEG",
                    "https://olympustaff.com/uploads/manga_34173/45/981f15e8c22a8a95cd591cda80879373.DM_20250319204314_020.JPEG",
                    "https://olympustaff.com/uploads/manga_34173/45/9f25b6367a75a55406e7e8d1ab5e7d54.DM_20250319204314_021.JPEG",
                    "https://olympustaff.com/uploads/manga_34173/45/a45fe19e3945453773dde3c85d939284.DM_20250319204314_022.JPEG",
                    "https://olympustaff.com/uploads/manga_34173/45/4356b22b59dc0fe7cf19c399051c75bc.DM_20250319204314_023.JPEG",
                    "https://olympustaff.com/uploads/manga_34173/45/b46548e23d45121f9b05870560a227ab.DM_20250319204314_024.JPEG",
                    "https://olympustaff.com/uploads/manga_34173/45/00dd0678d05a56505fb94b4ff868e20c.DM_20250319204314_025.JPEG",
                    "https://olympustaff.com/uploads/manga_34173/45/c12dbabe4208435233d8fc06cf96bf7b.DM_20250319204314_026.JPEG",
                    "https://olympustaff.com/uploads/manga_34173/45/3132f06de61fa9a1f4b5f3385f56993d.DM_20250319204314_027.JPEG",
                    "https://olympustaff.com/uploads/manga_34173/45/384b74fc9ee2781e2bd9e41782e6029f.DM_20250319204314_028.JPEG",
                    "https://olympustaff.com/uploads/manga_34173/45/a6ff3160a8da9b829adc22d40329f741.DM_20250319204314_029.JPEG",
                    "https://olympustaff.com/uploads/manga_34173/45/2d7f005e948ba2796f5fd286a6902b62.DM_20250319204314_030.JPEG",
                    "https://olympustaff.com/uploads/manga_34173/45/281a04ed8df4afa3b84b425b184ed0de.DM_20250319204314_031.JPEG",
                    "https://olympustaff.com/uploads/manga_34173/45/ca0163dd1d3cd22490faebc084fff496.DM_20250319204314_032.JPEG",
                    "https://olympustaff.com/uploads/manga_34173/45/afd41832be0f91ac9e7582ba775ccf73.DM_20250319204314_033.JPEG",
                    "https://olympustaff.com/uploads/manga_34173/45/ef770d8f0d71fd04dc8ac2431011ec63.DM_20250319204314_034.JPEG"
                ]
            },
            {
                "chapter": "46",
                "images": [
                    "https://olympustaff.com/uploads/manga_34173/46/8801fdfce2dbc0dc18ee88da36c0e3a6.01.jpg",
                    "https://olympustaff.com/uploads/manga_34173/46/ac3b1d45ddfea14b362fdb74b195ca61.02.jpg",
                    "https://olympustaff.com/uploads/manga_34173/46/cafe1582ae9e8f78a714d90f25626032.03.jpg",
                    "https://olympustaff.com/uploads/manga_34173/46/fdcc8c18d9b1ca3389eed1d4ecf341f1.04.jpg",
                    "https://olympustaff.com/uploads/manga_34173/46/378ec2df8117096929aaa365b421e426.05.jpg"
                ]
            },
            {
                "chapter": "47",
                "images": [
                    "https://olympustaff.com/uploads/manga_34173/47/e0b396de80da4a1edc9304485be62d4c.01.jpg",
                    "https://olympustaff.com/uploads/manga_34173/47/b1523b36832dd01a16125d500b989ffc.02.jpg",
                    "https://olympustaff.com/uploads/manga_34173/47/d82ccc774fae4ddc521a78daccbea842.03.jpg",
                    "https://olympustaff.com/uploads/manga_34173/47/b751eaaf67c76aff9cab55e53d465494.04.jpg",
                    "https://olympustaff.com/uploads/manga_34173/47/acb3e4dd8eb601fee2142ed458714205.05.jpg"
                ]
            },
            {
                "chapter": "48",
                "images": [
                    "https://olympustaff.com/uploads/manga_34173/48/e1d0788765322132543dae11d7cadaa4.01.jpg",
                    "https://olympustaff.com/uploads/manga_34173/48/9b4221926d2e3276be11eb4a5f816dfe.02.jpg",
                    "https://olympustaff.com/uploads/manga_34173/48/d21dddf526995bbbd9a49bcf8fd66ae9.03.jpg",
                    "https://olympustaff.com/uploads/manga_34173/48/343a19f910314620309e208b30a12981.04.jpg",
                    "https://olympustaff.com/uploads/manga_34173/48/ecbb2d7e456658da58b86a4838dde286.05.jpg"
                ]
            }
        ]
    }
}