{
    "anime1": {
        "info": {
            "title": "المقاتل الأقوى",
            "story": "مانجا المقاتل الأقوى مترجمةالمقاتل الأقوى عندما فتحت عيناي من حادث مفاجئ خلال موعد غرامي، هل كان موقع تصوير درامي تاريخي؟! لا، لقد ولدت من جديد كطفل! .... أنا أدعى الآن \"غيون تشيونغ\" من طائفة جونغ نا...",
            "image": "https://olympustaff.com/images/manga/194994702.jpeg"
        },
        "chapters": [
            {
                "chapter": "1",
                "images": [
                    "https://olympustaff.com/uploads/manga_3fe94/1/00.webp",
                    "https://olympustaff.com/uploads/manga_3fe94/1/01.webp",
                    "https://olympustaff.com/uploads/manga_3fe94/1/02.webp",
                    "https://olympustaff.com/uploads/manga_3fe94/1/03.webp",
                    "https://olympustaff.com/uploads/manga_3fe94/1/04.webp",
                    "https://olympustaff.com/uploads/manga_3fe94/1/05.webp",
                    "https://olympustaff.com/uploads/manga_3fe94/1/06.webp",
                    "https://olympustaff.com/uploads/manga_3fe94/1/07.webp",
                    "https://olympustaff.com/uploads/manga_3fe94/1/08.webp"
                ]
            },
            {
                "chapter": "2",
                "images": [
                    "https://olympustaff.com/uploads/manga_3fe94/2/00.webp",
                    "https://olympustaff.com/uploads/manga_3fe94/2/01.webp",
                    "https://olympustaff.com/uploads/manga_3fe94/2/02.webp",
                    "https://olympustaff.com/uploads/manga_3fe94/2/03.webp",
                    "https://olympustaff.com/uploads/manga_3fe94/2/04.webp",
                    "https://olympustaff.com/uploads/manga_3fe94/2/05.webp",
                    "https://olympustaff.com/uploads/manga_3fe94/2/06.webp",
                    "https://olympustaff.com/uploads/manga_3fe94/2/07.webp"
                ]
            },
            {
                "chapter": "3",
                "images": [
                    "https://olympustaff.com/uploads/manga_3fe94/3/00.webp",
                    "https://olympustaff.com/uploads/manga_3fe94/3/01.webp",
                    "https://olympustaff.com/uploads/manga_3fe94/3/02.webp",
                    "https://olympustaff.com/uploads/manga_3fe94/3/03.webp",
                    "https://olympustaff.com/uploads/manga_3fe94/3/04.webp",
                    "https://olympustaff.com/uploads/manga_3fe94/3/05.webp",
                    "https://olympustaff.com/uploads/manga_3fe94/3/06.webp",
                    "https://olympustaff.com/uploads/manga_3fe94/3/07.webp",
                    "https://olympustaff.com/uploads/manga_3fe94/3/08.webp"
                ]
            },
            {
                "chapter": "4",
                "images": [
                    "https://olympustaff.com/uploads/manga_3fe94/4/00.webp",
                    "https://olympustaff.com/uploads/manga_3fe94/4/01.webp",
                    "https://olympustaff.com/uploads/manga_3fe94/4/02.webp",
                    "https://olympustaff.com/uploads/manga_3fe94/4/03.webp",
                    "https://olympustaff.com/uploads/manga_3fe94/4/04.webp",
                    "https://olympustaff.com/uploads/manga_3fe94/4/05.webp",
                    "https://olympustaff.com/uploads/manga_3fe94/4/06.webp",
                    "https://olympustaff.com/uploads/manga_3fe94/4/07.webp",
                    "https://olympustaff.com/uploads/manga_3fe94/4/08.webp"
                ]
            },
            {
                "chapter": "5",
                "images": [
                    "https://olympustaff.com/uploads/manga_3fe94/5/00.webp",
                    "https://olympustaff.com/uploads/manga_3fe94/5/01.webp",
                    "https://olympustaff.com/uploads/manga_3fe94/5/02.webp",
                    "https://olympustaff.com/uploads/manga_3fe94/5/03.webp",
                    "https://olympustaff.com/uploads/manga_3fe94/5/04.webp",
                    "https://olympustaff.com/uploads/manga_3fe94/5/05.webp",
                    "https://olympustaff.com/uploads/manga_3fe94/5/06.webp"
                ]
            },
            {
                "chapter": "6",
                "images": [
                    "https://olympustaff.com/uploads/manga_3fe94/6/00.webp",
                    "https://olympustaff.com/uploads/manga_3fe94/6/01.webp",
                    "https://olympustaff.com/uploads/manga_3fe94/6/02.webp",
                    "https://olympustaff.com/uploads/manga_3fe94/6/03.webp",
                    "https://olympustaff.com/uploads/manga_3fe94/6/04.webp",
                    "https://olympustaff.com/uploads/manga_3fe94/6/05.webp",
                    "https://olympustaff.com/uploads/manga_3fe94/6/06.webp"
                ]
            },
            {
                "chapter": "7",
                "images": [
                    "https://olympustaff.com/uploads/manga_3fe94/7/00.webp",
                    "https://olympustaff.com/uploads/manga_3fe94/7/01.webp",
                    "https://olympustaff.com/uploads/manga_3fe94/7/02.webp",
                    "https://olympustaff.com/uploads/manga_3fe94/7/03.webp",
                    "https://olympustaff.com/uploads/manga_3fe94/7/04.webp",
                    "https://olympustaff.com/uploads/manga_3fe94/7/05.webp"
                ]
            },
            {
                "chapter": "8",
                "images": [
                    "https://olympustaff.com/uploads/manga_3fe94/8/00.webp",
                    "https://olympustaff.com/uploads/manga_3fe94/8/01.webp",
                    "https://olympustaff.com/uploads/manga_3fe94/8/02.webp",
                    "https://olympustaff.com/uploads/manga_3fe94/8/03.webp",
                    "https://olympustaff.com/uploads/manga_3fe94/8/04.webp"
                ]
            },
            {
                "chapter": "9",
                "images": [
                    "https://olympustaff.com/uploads/manga_3fe94/9/00.webp",
                    "https://olympustaff.com/uploads/manga_3fe94/9/01.webp",
                    "https://olympustaff.com/uploads/manga_3fe94/9/02.webp",
                    "https://olympustaff.com/uploads/manga_3fe94/9/03.webp",
                    "https://olympustaff.com/uploads/manga_3fe94/9/04.webp"
                ]
            },
            {
                "chapter": "10",
                "images": [
                    "https://olympustaff.com/uploads/manga_3fe94/10/00.webp",
                    "https://olympustaff.com/uploads/manga_3fe94/10/01.webp",
                    "https://olympustaff.com/uploads/manga_3fe94/10/02.webp",
                    "https://olympustaff.com/uploads/manga_3fe94/10/03.webp",
                    "https://olympustaff.com/uploads/manga_3fe94/10/04.webp",
                    "https://olympustaff.com/uploads/manga_3fe94/10/05.webp",
                    "https://olympustaff.com/uploads/manga_3fe94/10/06.webp",
                    "https://olympustaff.com/uploads/manga_3fe94/10/07.webp",
                    "https://olympustaff.com/uploads/manga_3fe94/10/08.webp",
                    "https://olympustaff.com/uploads/manga_3fe94/10/09.webp",
                    "https://olympustaff.com/uploads/manga_3fe94/10/010.webp",
                    "https://olympustaff.com/uploads/manga_3fe94/10/011.webp",
                    "https://olympustaff.com/uploads/manga_3fe94/10/012.webp",
                    "https://olympustaff.com/uploads/manga_3fe94/10/013.webp",
                    "https://olympustaff.com/uploads/manga_3fe94/10/014.webp",
                    "https://olympustaff.com/uploads/manga_3fe94/10/015.webp",
                    "https://olympustaff.com/uploads/manga_3fe94/10/016.webp",
                    "https://olympustaff.com/uploads/manga_3fe94/10/017.webp",
                    "https://olympustaff.com/uploads/manga_3fe94/10/018.webp",
                    "https://olympustaff.com/uploads/manga_3fe94/10/019.webp",
                    "https://olympustaff.com/uploads/manga_3fe94/10/020.webp",
                    "https://olympustaff.com/uploads/manga_3fe94/10/021.webp",
                    "https://olympustaff.com/uploads/manga_3fe94/10/022.webp",
                    "https://olympustaff.com/uploads/manga_3fe94/10/023.webp",
                    "https://olympustaff.com/uploads/manga_3fe94/10/024.webp",
                    "https://olympustaff.com/uploads/manga_3fe94/10/025.webp",
                    "https://olympustaff.com/uploads/manga_3fe94/10/026.webp",
                    "https://olympustaff.com/uploads/manga_3fe94/10/027.webp",
                    "https://olympustaff.com/uploads/manga_3fe94/10/028.webp",
                    "https://olympustaff.com/uploads/manga_3fe94/10/029.webp",
                    "https://olympustaff.com/uploads/manga_3fe94/10/030.webp",
                    "https://olympustaff.com/uploads/manga_3fe94/10/031.webp",
                    "https://olympustaff.com/uploads/manga_3fe94/10/032.webp",
                    "https://olympustaff.com/uploads/manga_3fe94/10/033.webp",
                    "https://olympustaff.com/uploads/manga_3fe94/10/034.webp",
                    "https://olympustaff.com/uploads/manga_3fe94/10/035.webp",
                    "https://olympustaff.com/uploads/manga_3fe94/10/036.webp",
                    "https://olympustaff.com/uploads/manga_3fe94/10/037.webp",
                    "https://olympustaff.com/uploads/manga_3fe94/10/038.webp",
                    "https://olympustaff.com/uploads/manga_3fe94/10/039.webp",
                    "https://olympustaff.com/uploads/manga_3fe94/10/040.webp",
                    "https://olympustaff.com/uploads/manga_3fe94/10/041.webp",
                    "https://olympustaff.com/uploads/manga_3fe94/10/042.webp",
                    "https://olympustaff.com/uploads/manga_3fe94/10/043.webp",
                    "https://olympustaff.com/uploads/manga_3fe94/10/044.webp",
                    "https://olympustaff.com/uploads/manga_3fe94/10/045.webp",
                    "https://olympustaff.com/uploads/manga_3fe94/10/046.webp",
                    "https://olympustaff.com/uploads/manga_3fe94/10/047.webp",
                    "https://olympustaff.com/uploads/manga_3fe94/10/048.webp",
                    "https://olympustaff.com/uploads/manga_3fe94/10/049.webp",
                    "https://olympustaff.com/uploads/manga_3fe94/10/050.webp",
                    "https://olympustaff.com/uploads/manga_3fe94/10/051.webp",
                    "https://olympustaff.com/uploads/manga_3fe94/10/052.webp",
                    "https://olympustaff.com/uploads/manga_3fe94/10/053.webp",
                    "https://olympustaff.com/uploads/manga_3fe94/10/054.webp",
                    "https://olympustaff.com/uploads/manga_3fe94/10/055.webp",
                    "https://olympustaff.com/uploads/manga_3fe94/10/056.webp",
                    "https://olympustaff.com/uploads/manga_3fe94/10/057.webp",
                    "https://olympustaff.com/uploads/manga_3fe94/10/058.webp",
                    "https://olympustaff.com/uploads/manga_3fe94/10/059.webp",
                    "https://olympustaff.com/uploads/manga_3fe94/10/060.webp",
                    "https://olympustaff.com/uploads/manga_3fe94/10/061.webp",
                    "https://olympustaff.com/uploads/manga_3fe94/10/062.webp",
                    "https://olympustaff.com/uploads/manga_3fe94/10/063.webp",
                    "https://olympustaff.com/uploads/manga_3fe94/10/064.webp",
                    "https://olympustaff.com/uploads/manga_3fe94/10/065.webp",
                    "https://olympustaff.com/uploads/manga_3fe94/10/066.webp",
                    "https://olympustaff.com/uploads/manga_3fe94/10/067.webp",
                    "https://olympustaff.com/uploads/manga_3fe94/10/068.webp",
                    "https://olympustaff.com/uploads/manga_3fe94/10/069.webp",
                    "https://olympustaff.com/uploads/manga_3fe94/10/070.webp",
                    "https://olympustaff.com/uploads/manga_3fe94/10/071.webp",
                    "https://olympustaff.com/uploads/manga_3fe94/10/072.webp",
                    "https://olympustaff.com/uploads/manga_3fe94/10/073.webp",
                    "https://olympustaff.com/uploads/manga_3fe94/10/074.webp",
                    "https://olympustaff.com/uploads/manga_3fe94/10/075.webp",
                    "https://olympustaff.com/uploads/manga_3fe94/10/076.webp",
                    "https://olympustaff.com/uploads/manga_3fe94/10/077.webp",
                    "https://olympustaff.com/uploads/manga_3fe94/10/078.webp",
                    "https://olympustaff.com/uploads/manga_3fe94/10/079.webp",
                    "https://olympustaff.com/uploads/manga_3fe94/10/080.webp",
                    "https://olympustaff.com/uploads/manga_3fe94/10/081.webp",
                    "https://olympustaff.com/uploads/manga_3fe94/10/082.webp",
                    "https://olympustaff.com/uploads/manga_3fe94/10/083.webp",
                    "https://olympustaff.com/uploads/manga_3fe94/10/084.webp",
                    "https://olympustaff.com/uploads/manga_3fe94/10/085.webp",
                    "https://olympustaff.com/uploads/manga_3fe94/10/086.webp",
                    "https://olympustaff.com/uploads/manga_3fe94/10/087.webp",
                    "https://olympustaff.com/uploads/manga_3fe94/10/088.webp",
                    "https://olympustaff.com/uploads/manga_3fe94/10/089.webp",
                    "https://olympustaff.com/uploads/manga_3fe94/10/090.webp",
                    "https://olympustaff.com/uploads/manga_3fe94/10/091.webp",
                    "https://olympustaff.com/uploads/manga_3fe94/10/092.webp",
                    "https://olympustaff.com/uploads/manga_3fe94/10/093.webp",
                    "https://olympustaff.com/uploads/manga_3fe94/10/094.webp",
                    "https://olympustaff.com/uploads/manga_3fe94/10/095.webp",
                    "https://olympustaff.com/uploads/manga_3fe94/10/096.webp",
                    "https://olympustaff.com/uploads/manga_3fe94/10/097.webp",
                    "https://olympustaff.com/uploads/manga_3fe94/10/098.webp",
                    "https://olympustaff.com/uploads/manga_3fe94/10/099.webp"
                ]
            },
            {
                "chapter": "11",
                "images": [
                    "https://olympustaff.com/uploads/manga_3fe94/11/00.webp",
                    "https://olympustaff.com/uploads/manga_3fe94/11/01.webp",
                    "https://olympustaff.com/uploads/manga_3fe94/11/02.webp",
                    "https://olympustaff.com/uploads/manga_3fe94/11/03.webp",
                    "https://olympustaff.com/uploads/manga_3fe94/11/04.webp"
                ]
            },
            {
                "chapter": "12",
                "images": [
                    "https://olympustaff.com/uploads/manga_3fe94/12/00.webp",
                    "https://olympustaff.com/uploads/manga_3fe94/12/01.webp",
                    "https://olympustaff.com/uploads/manga_3fe94/12/02.webp",
                    "https://olympustaff.com/uploads/manga_3fe94/12/03.webp",
                    "https://olympustaff.com/uploads/manga_3fe94/12/04.webp"
                ]
            },
            {
                "chapter": "13",
                "images": [
                    "https://olympustaff.com/uploads/manga_3fe94/13/00.webp",
                    "https://olympustaff.com/uploads/manga_3fe94/13/01.webp",
                    "https://olympustaff.com/uploads/manga_3fe94/13/02.webp",
                    "https://olympustaff.com/uploads/manga_3fe94/13/03.webp",
                    "https://olympustaff.com/uploads/manga_3fe94/13/04.webp"
                ]
            },
            {
                "chapter": "14",
                "images": [
                    "https://olympustaff.com/uploads/manga_3fe94/14/00.webp",
                    "https://olympustaff.com/uploads/manga_3fe94/14/01.webp",
                    "https://olympustaff.com/uploads/manga_3fe94/14/02.webp",
                    "https://olympustaff.com/uploads/manga_3fe94/14/03.webp",
                    "https://olympustaff.com/uploads/manga_3fe94/14/04.webp"
                ]
            },
            {
                "chapter": "15",
                "images": [
                    "https://olympustaff.com/uploads/manga_3fe94/15/00.webp",
                    "https://olympustaff.com/uploads/manga_3fe94/15/01.webp",
                    "https://olympustaff.com/uploads/manga_3fe94/15/02.webp",
                    "https://olympustaff.com/uploads/manga_3fe94/15/03.webp",
                    "https://olympustaff.com/uploads/manga_3fe94/15/04.webp"
                ]
            },
            {
                "chapter": "16",
                "images": [
                    "https://olympustaff.com/uploads/manga_3fe94/16/00.webp",
                    "https://olympustaff.com/uploads/manga_3fe94/16/01.webp",
                    "https://olympustaff.com/uploads/manga_3fe94/16/02.webp",
                    "https://olympustaff.com/uploads/manga_3fe94/16/03.webp",
                    "https://olympustaff.com/uploads/manga_3fe94/16/04.webp"
                ]
            },
            {
                "chapter": "17",
                "images": [
                    "https://olympustaff.com/uploads/manga_3fe94/17/00.webp",
                    "https://olympustaff.com/uploads/manga_3fe94/17/01.webp",
                    "https://olympustaff.com/uploads/manga_3fe94/17/02.webp",
                    "https://olympustaff.com/uploads/manga_3fe94/17/03.webp",
                    "https://olympustaff.com/uploads/manga_3fe94/17/04.webp"
                ]
            },
            {
                "chapter": "18",
                "images": [
                    "https://olympustaff.com/uploads/manga_3fe94/18/00.webp",
                    "https://olympustaff.com/uploads/manga_3fe94/18/01.webp",
                    "https://olympustaff.com/uploads/manga_3fe94/18/02.webp",
                    "https://olympustaff.com/uploads/manga_3fe94/18/03.webp"
                ]
            },
            {
                "chapter": "19",
                "images": [
                    "https://olympustaff.com/uploads/manga_3fe94/19/00.webp",
                    "https://olympustaff.com/uploads/manga_3fe94/19/01.webp",
                    "https://olympustaff.com/uploads/manga_3fe94/19/02.webp",
                    "https://olympustaff.com/uploads/manga_3fe94/19/03.webp",
                    "https://olympustaff.com/uploads/manga_3fe94/19/04.webp"
                ]
            },
            {
                "chapter": "20",
                "images": [
                    "https://olympustaff.com/uploads/manga_3fe94/20/00.webp",
                    "https://olympustaff.com/uploads/manga_3fe94/20/01.webp",
                    "https://olympustaff.com/uploads/manga_3fe94/20/02.webp",
                    "https://olympustaff.com/uploads/manga_3fe94/20/03.webp",
                    "https://olympustaff.com/uploads/manga_3fe94/20/04.webp",
                    "https://olympustaff.com/uploads/manga_3fe94/20/05.webp",
                    "https://olympustaff.com/uploads/manga_3fe94/20/06.webp"
                ]
            },
            {
                "chapter": "21",
                "images": [
                    "https://olympustaff.com/uploads/manga_3fe94/21/00.webp",
                    "https://olympustaff.com/uploads/manga_3fe94/21/01.webp",
                    "https://olympustaff.com/uploads/manga_3fe94/21/02.webp",
                    "https://olympustaff.com/uploads/manga_3fe94/21/03.webp",
                    "https://olympustaff.com/uploads/manga_3fe94/21/04.webp",
                    "https://olympustaff.com/uploads/manga_3fe94/21/05.webp"
                ]
            },
            {
                "chapter": "22",
                "images": [
                    "https://olympustaff.com/uploads/manga_3fe94/22/00.webp",
                    "https://olympustaff.com/uploads/manga_3fe94/22/01.webp",
                    "https://olympustaff.com/uploads/manga_3fe94/22/02.webp",
                    "https://olympustaff.com/uploads/manga_3fe94/22/03.webp",
                    "https://olympustaff.com/uploads/manga_3fe94/22/04.webp",
                    "https://olympustaff.com/uploads/manga_3fe94/22/05.webp"
                ]
            },
            {
                "chapter": "23",
                "images": [
                    "https://olympustaff.com/uploads/manga_3fe94/23/00.webp",
                    "https://olympustaff.com/uploads/manga_3fe94/23/01.webp",
                    "https://olympustaff.com/uploads/manga_3fe94/23/02.webp",
                    "https://olympustaff.com/uploads/manga_3fe94/23/03.webp",
                    "https://olympustaff.com/uploads/manga_3fe94/23/04.webp",
                    "https://olympustaff.com/uploads/manga_3fe94/23/05.webp"
                ]
            },
            {
                "chapter": "24",
                "images": [
                    "https://olympustaff.com/uploads/manga_3fe94/24/00.webp",
                    "https://olympustaff.com/uploads/manga_3fe94/24/01.webp",
                    "https://olympustaff.com/uploads/manga_3fe94/24/02.webp",
                    "https://olympustaff.com/uploads/manga_3fe94/24/03.webp",
                    "https://olympustaff.com/uploads/manga_3fe94/24/04.webp",
                    "https://olympustaff.com/uploads/manga_3fe94/24/05.webp",
                    "https://olympustaff.com/uploads/manga_3fe94/24/06.webp",
                    "https://olympustaff.com/uploads/manga_3fe94/24/07.webp"
                ]
            },
            {
                "chapter": "25",
                "images": [
                    "https://olympustaff.com/uploads/manga_3fe94/25/00.webp",
                    "https://olympustaff.com/uploads/manga_3fe94/25/01.webp",
                    "https://olympustaff.com/uploads/manga_3fe94/25/02.webp",
                    "https://olympustaff.com/uploads/manga_3fe94/25/03.webp",
                    "https://olympustaff.com/uploads/manga_3fe94/25/04.webp",
                    "https://olympustaff.com/uploads/manga_3fe94/25/05.webp",
                    "https://olympustaff.com/uploads/manga_3fe94/25/06.webp"
                ]
            },
            {
                "chapter": "26",
                "images": [
                    "https://olympustaff.com/uploads/manga_3fe94/26/00.webp",
                    "https://olympustaff.com/uploads/manga_3fe94/26/01.webp",
                    "https://olympustaff.com/uploads/manga_3fe94/26/02.webp",
                    "https://olympustaff.com/uploads/manga_3fe94/26/03.webp",
                    "https://olympustaff.com/uploads/manga_3fe94/26/04.webp",
                    "https://olympustaff.com/uploads/manga_3fe94/26/05.webp",
                    "https://olympustaff.com/uploads/manga_3fe94/26/06.webp",
                    "https://olympustaff.com/uploads/manga_3fe94/26/07.webp",
                    "https://olympustaff.com/uploads/manga_3fe94/26/08.webp",
                    "https://olympustaff.com/uploads/manga_3fe94/26/09.webp"
                ]
            },
            {
                "chapter": "27",
                "images": [
                    "https://olympustaff.com/uploads/manga_3fe94/27/00.webp",
                    "https://olympustaff.com/uploads/manga_3fe94/27/01.webp",
                    "https://olympustaff.com/uploads/manga_3fe94/27/02.webp",
                    "https://olympustaff.com/uploads/manga_3fe94/27/03.webp",
                    "https://olympustaff.com/uploads/manga_3fe94/27/04.webp",
                    "https://olympustaff.com/uploads/manga_3fe94/27/05.webp",
                    "https://olympustaff.com/uploads/manga_3fe94/27/06.webp",
                    "https://olympustaff.com/uploads/manga_3fe94/27/07.webp",
                    "https://olympustaff.com/uploads/manga_3fe94/27/08.webp",
                    "https://olympustaff.com/uploads/manga_3fe94/27/09.webp"
                ]
            },
            {
                "chapter": "28",
                "images": [
                    "https://olympustaff.com/uploads/manga_3fe94/28/00.webp",
                    "https://olympustaff.com/uploads/manga_3fe94/28/01.webp",
                    "https://olympustaff.com/uploads/manga_3fe94/28/02.webp",
                    "https://olympustaff.com/uploads/manga_3fe94/28/03.webp",
                    "https://olympustaff.com/uploads/manga_3fe94/28/04.webp",
                    "https://olympustaff.com/uploads/manga_3fe94/28/05.webp",
                    "https://olympustaff.com/uploads/manga_3fe94/28/06.webp",
                    "https://olympustaff.com/uploads/manga_3fe94/28/07.webp",
                    "https://olympustaff.com/uploads/manga_3fe94/28/08.webp",
                    "https://olympustaff.com/uploads/manga_3fe94/28/09.webp",
                    "https://olympustaff.com/uploads/manga_3fe94/28/010.webp"
                ]
            },
            {
                "chapter": "29",
                "images": [
                    "https://olympustaff.com/uploads/manga_3fe94/29/00.webp",
                    "https://olympustaff.com/uploads/manga_3fe94/29/01.webp",
                    "https://olympustaff.com/uploads/manga_3fe94/29/02.webp",
                    "https://olympustaff.com/uploads/manga_3fe94/29/03.webp",
                    "https://olympustaff.com/uploads/manga_3fe94/29/04.webp",
                    "https://olympustaff.com/uploads/manga_3fe94/29/05.webp",
                    "https://olympustaff.com/uploads/manga_3fe94/29/06.webp",
                    "https://olympustaff.com/uploads/manga_3fe94/29/07.webp"
                ]
            },
            {
                "chapter": "30",
                "images": [
                    "https://olympustaff.com/uploads/manga_3fe94/30/00.webp",
                    "https://olympustaff.com/uploads/manga_3fe94/30/01.webp",
                    "https://olympustaff.com/uploads/manga_3fe94/30/02.webp",
                    "https://olympustaff.com/uploads/manga_3fe94/30/03.webp",
                    "https://olympustaff.com/uploads/manga_3fe94/30/04.webp",
                    "https://olympustaff.com/uploads/manga_3fe94/30/05.webp",
                    "https://olympustaff.com/uploads/manga_3fe94/30/06.webp",
                    "https://olympustaff.com/uploads/manga_3fe94/30/07.webp",
                    "https://olympustaff.com/uploads/manga_3fe94/30/08.webp",
                    "https://olympustaff.com/uploads/manga_3fe94/30/09.webp",
                    "https://olympustaff.com/uploads/manga_3fe94/30/010.webp",
                    "https://olympustaff.com/uploads/manga_3fe94/30/011.webp",
                    "https://olympustaff.com/uploads/manga_3fe94/30/012.webp",
                    "https://olympustaff.com/uploads/manga_3fe94/30/013.webp",
                    "https://olympustaff.com/uploads/manga_3fe94/30/014.webp",
                    "https://olympustaff.com/uploads/manga_3fe94/30/015.webp",
                    "https://olympustaff.com/uploads/manga_3fe94/30/016.webp",
                    "https://olympustaff.com/uploads/manga_3fe94/30/017.webp",
                    "https://olympustaff.com/uploads/manga_3fe94/30/018.webp",
                    "https://olympustaff.com/uploads/manga_3fe94/30/019.webp",
                    "https://olympustaff.com/uploads/manga_3fe94/30/020.webp",
                    "https://olympustaff.com/uploads/manga_3fe94/30/021.webp",
                    "https://olympustaff.com/uploads/manga_3fe94/30/022.webp",
                    "https://olympustaff.com/uploads/manga_3fe94/30/023.webp",
                    "https://olympustaff.com/uploads/manga_3fe94/30/024.webp",
                    "https://olympustaff.com/uploads/manga_3fe94/30/025.webp",
                    "https://olympustaff.com/uploads/manga_3fe94/30/026.webp",
                    "https://olympustaff.com/uploads/manga_3fe94/30/027.webp",
                    "https://olympustaff.com/uploads/manga_3fe94/30/028.webp",
                    "https://olympustaff.com/uploads/manga_3fe94/30/029.webp"
                ]
            },
            {
                "chapter": "31",
                "images": [
                    "https://olympustaff.com/uploads/manga_3fe94/31/00.webp",
                    "https://olympustaff.com/uploads/manga_3fe94/31/01.webp",
                    "https://olympustaff.com/uploads/manga_3fe94/31/02.webp",
                    "https://olympustaff.com/uploads/manga_3fe94/31/03.webp",
                    "https://olympustaff.com/uploads/manga_3fe94/31/04.webp",
                    "https://olympustaff.com/uploads/manga_3fe94/31/05.webp",
                    "https://olympustaff.com/uploads/manga_3fe94/31/06.webp",
                    "https://olympustaff.com/uploads/manga_3fe94/31/07.webp"
                ]
            },
            {
                "chapter": "32",
                "images": [
                    "https://olympustaff.com/uploads/manga_3fe94/32/00.webp",
                    "https://olympustaff.com/uploads/manga_3fe94/32/01.webp",
                    "https://olympustaff.com/uploads/manga_3fe94/32/02.webp",
                    "https://olympustaff.com/uploads/manga_3fe94/32/03.webp",
                    "https://olympustaff.com/uploads/manga_3fe94/32/04.webp",
                    "https://olympustaff.com/uploads/manga_3fe94/32/05.webp",
                    "https://olympustaff.com/uploads/manga_3fe94/32/06.webp",
                    "https://olympustaff.com/uploads/manga_3fe94/32/07.webp",
                    "https://olympustaff.com/uploads/manga_3fe94/32/08.webp",
                    "https://olympustaff.com/uploads/manga_3fe94/32/09.webp",
                    "https://olympustaff.com/uploads/manga_3fe94/32/010.webp",
                    "https://olympustaff.com/uploads/manga_3fe94/32/011.webp",
                    "https://olympustaff.com/uploads/manga_3fe94/32/012.webp",
                    "https://olympustaff.com/uploads/manga_3fe94/32/013.webp",
                    "https://olympustaff.com/uploads/manga_3fe94/32/014.webp",
                    "https://olympustaff.com/uploads/manga_3fe94/32/015.webp",
                    "https://olympustaff.com/uploads/manga_3fe94/32/016.webp",
                    "https://olympustaff.com/uploads/manga_3fe94/32/017.webp",
                    "https://olympustaff.com/uploads/manga_3fe94/32/018.webp",
                    "https://olympustaff.com/uploads/manga_3fe94/32/019.webp",
                    "https://olympustaff.com/uploads/manga_3fe94/32/020.webp",
                    "https://olympustaff.com/uploads/manga_3fe94/32/021.webp",
                    "https://olympustaff.com/uploads/manga_3fe94/32/022.webp"
                ]
            },
            {
                "chapter": "33",
                "images": [
                    "https://olympustaff.com/uploads/manga_3fe94/33/00.webp",
                    "https://olympustaff.com/uploads/manga_3fe94/33/01.webp",
                    "https://olympustaff.com/uploads/manga_3fe94/33/02.webp",
                    "https://olympustaff.com/uploads/manga_3fe94/33/03.webp",
                    "https://olympustaff.com/uploads/manga_3fe94/33/04.webp",
                    "https://olympustaff.com/uploads/manga_3fe94/33/05.webp"
                ]
            },
            {
                "chapter": "34",
                "images": [
                    "https://olympustaff.com/uploads/manga_3fe94/34/91b9af1ec0579f0024501ba13d03c302.01.jpg",
                    "https://olympustaff.com/uploads/manga_3fe94/34/1223078de9644729f79ceb29d318a158.02.jpg",
                    "https://olympustaff.com/uploads/manga_3fe94/34/3fcc67e5f8ef66dac98ba0869b4af307.03.jpg",
                    "https://olympustaff.com/uploads/manga_3fe94/34/3d911f9f389297e947c940d8923c28ce.04.jpg",
                    "https://olympustaff.com/uploads/manga_3fe94/34/2a67a2d34f168a2f7d35d5492d497dea.05.jpg",
                    "https://olympustaff.com/uploads/manga_3fe94/34/a4abe02bd2965ce638c4e919f2d4389b.06.jpg",
                    "https://olympustaff.com/uploads/manga_3fe94/34/1f357c316919d5d4565df48ed8283b08.07.jpg",
                    "https://olympustaff.com/uploads/manga_3fe94/34/f152e7e7bce20a03ab670414e5d660de.08.jpg",
                    "https://olympustaff.com/uploads/manga_3fe94/34/535b81c6422a896fe03c53d9a0e3357c.09.jpg",
                    "https://olympustaff.com/uploads/manga_3fe94/34/c84618d51a2ab192dd8ce62c3faa519d.10.jpg",
                    "https://olympustaff.com/uploads/manga_3fe94/34/61dcb90b972b1c133aa2fb6e86867c69.11.jpg",
                    "https://olympustaff.com/uploads/manga_3fe94/34/3bde4624df28f898bd657288f36c3585.12.jpg",
                    "https://olympustaff.com/uploads/manga_3fe94/34/1e23eb7cd4702930b51525dc2161f4ae.13.jpg",
                    "https://olympustaff.com/uploads/manga_3fe94/34/6b40388f3bc545e9e60ba1e654e20a2b.14.jpg",
                    "https://olympustaff.com/uploads/manga_3fe94/34/fa61879bf2266093cb26b1dbcee021bc.15.jpg",
                    "https://olympustaff.com/uploads/manga_3fe94/34/3c0a35d9a005bb0363ac1c328fa2d374.16.jpg",
                    "https://olympustaff.com/uploads/manga_3fe94/34/8946063c44dd0f97a409e8ba01b7bdce.17.jpg",
                    "https://olympustaff.com/uploads/manga_3fe94/34/c16c4fa0e31834bd0b4cf2b83240915b.18.jpg",
                    "https://olympustaff.com/uploads/manga_3fe94/34/00fd98ae995911d20012d6b5817c57ca.19.jpg",
                    "https://olympustaff.com/uploads/manga_3fe94/34/1bbf239e2fc68daaedb4d214460ea39d.20.jpg",
                    "https://olympustaff.com/uploads/manga_3fe94/34/2cba3f36204637ad87ddfbd1d8b06e19.21.jpg",
                    "https://olympustaff.com/uploads/manga_3fe94/34/9db61c680d967fc7fbb98ac5cbeceb0b.22.jpg",
                    "https://olympustaff.com/uploads/manga_3fe94/34/674030890bdf6de309cd47af078e7466.23.jpg",
                    "https://olympustaff.com/uploads/manga_3fe94/34/d16527bf9e59b7f7e9d4f3b2b20d812b.24.jpg",
                    "https://olympustaff.com/uploads/manga_3fe94/34/926407866dec8f2ce795e12b14b18436.25.jpg",
                    "https://olympustaff.com/uploads/manga_3fe94/34/3c86dd0ce690efeda5e8d46ead8e77bb.26.jpg",
                    "https://olympustaff.com/uploads/manga_3fe94/34/b737ce5b832bae3dc38a165d0e9e5c93.27.jpg",
                    "https://olympustaff.com/uploads/manga_3fe94/34/a7994e10335950e76705c8afd1efdd12.28.jpg",
                    "https://olympustaff.com/uploads/manga_3fe94/34/396365bb6e7fc9a8de0670e44b33c481.29.jpg",
                    "https://olympustaff.com/uploads/manga_3fe94/34/43ed5a368cd5960ff77fd41f20aced59.30.jpg",
                    "https://olympustaff.com/uploads/manga_3fe94/34/d93754d19c9e48d5f40b71dc3d987545.31.jpg",
                    "https://olympustaff.com/uploads/manga_3fe94/34/97d51661144c151feb660629ba5fa406.32.jpg"
                ]
            },
            {
                "chapter": "35",
                "images": [
                    "https://olympustaff.com/uploads/manga_3fe94/35/707a5a3fe4113153487131d7458e6c26.01.jpg",
                    "https://olympustaff.com/uploads/manga_3fe94/35/159f243e318564c1fef8cdb7f77a9706.02.jpg",
                    "https://olympustaff.com/uploads/manga_3fe94/35/86396e416ca8441c9d2044bdef084038.03.jpg",
                    "https://olympustaff.com/uploads/manga_3fe94/35/bd4d0377e220970212ae38d72597deab.04.jpg",
                    "https://olympustaff.com/uploads/manga_3fe94/35/27454df1afd188604824b47f36bf87df.05.jpg",
                    "https://olympustaff.com/uploads/manga_3fe94/35/93dbba23fae6fd753a019db08c1188ad.06.jpg",
                    "https://olympustaff.com/uploads/manga_3fe94/35/fcadd150e92ddd151e32c7655e45802d.07.jpg",
                    "https://olympustaff.com/uploads/manga_3fe94/35/ae4ffed9ed1eab02856153eb556ef774.08.jpg",
                    "https://olympustaff.com/uploads/manga_3fe94/35/fdeb1278ec89727bdef9389788a3d63a.09.jpg",
                    "https://olympustaff.com/uploads/manga_3fe94/35/564c0c3fe0455cd20c54dff608f4640e.10.jpg",
                    "https://olympustaff.com/uploads/manga_3fe94/35/43d5b84f65240d73e5620204d019160f.11.jpg",
                    "https://olympustaff.com/uploads/manga_3fe94/35/70bcb4c10f8a352e2a26a601ef98cba0.12.jpg",
                    "https://olympustaff.com/uploads/manga_3fe94/35/09235977e024d3c651e725eafc471f22.13.jpg",
                    "https://olympustaff.com/uploads/manga_3fe94/35/94be1de06e946adbe27644a9ce73a936.14.jpg",
                    "https://olympustaff.com/uploads/manga_3fe94/35/11230cea0d108eb224f13eaec4faccf3.15.jpg",
                    "https://olympustaff.com/uploads/manga_3fe94/35/a735f429db5cb1f691fc53bd9702c2ec.16.jpg"
                ]
            },
            {
                "chapter": "36",
                "images": [
                    "https://olympustaff.com/uploads/manga_3fe94/36/d008c3668a05a3106779d9de9bcba6d9.jpg",
                    "https://olympustaff.com/uploads/manga_3fe94/36/1df51369d8c4ca80d8c0e7c8e3b969c9.jpg",
                    "https://olympustaff.com/uploads/manga_3fe94/36/b52e5f49cc2e71e5556582f78826a08e.jpg",
                    "https://olympustaff.com/uploads/manga_3fe94/36/0dee71e050fe05f3a8c8768f7f3758b5.jpg",
                    "https://olympustaff.com/uploads/manga_3fe94/36/5da0e360f299247a139bd7a0dbdc5afb.jpg",
                    "https://olympustaff.com/uploads/manga_3fe94/36/4f5418a277841cda876a5d28c31a063b.jpg",
                    "https://olympustaff.com/uploads/manga_3fe94/36/ee0ab8d3ee5547e6957796da052e92eb.jpg",
                    "https://olympustaff.com/uploads/manga_3fe94/36/f4cfba267d02e940ec2f1579379d248e.jpg",
                    "https://olympustaff.com/uploads/manga_3fe94/36/9dc138be3fec3cdb5d2f5e9d767b9804.jpg",
                    "https://olympustaff.com/uploads/manga_3fe94/36/681590b9eadd607541ed9e60dff320dc.jpg"
                ]
            },
            {
                "chapter": "37",
                "images": [
                    "https://olympustaff.com/uploads/manga_3fe94/37/cc0ac1b3f9e10c28619a05ca4a1a2936.jpg",
                    "https://olympustaff.com/uploads/manga_3fe94/37/0b56fd309468a349d6f85b7a081bf096.jpg",
                    "https://olympustaff.com/uploads/manga_3fe94/37/d65a7b8819c2f5ff3ef426a5cacbcfa7.jpg",
                    "https://olympustaff.com/uploads/manga_3fe94/37/2231de9e3ae0635643d73fd48c82d50e.jpg",
                    "https://olympustaff.com/uploads/manga_3fe94/37/fba97abe2ec92c865c216792233c8fe0.jpg",
                    "https://olympustaff.com/uploads/manga_3fe94/37/f286dcbadcea1b6a5f51e7b63fd5eab1.jpg",
                    "https://olympustaff.com/uploads/manga_3fe94/37/e68853c8c448f84001ac8ae5b476928c.jpg",
                    "https://olympustaff.com/uploads/manga_3fe94/37/1726e166d8c2aaae8efd1386adbb9813.jpg",
                    "https://olympustaff.com/uploads/manga_3fe94/37/b8b932fa41fd82008ce7fea449c3b784.jpg"
                ]
            },
            {
                "chapter": "38",
                "images": [
                    "https://olympustaff.com/uploads/manga_3fe94/38/efd81ed77c140fab0d9f9a602f5c3a47.jpg",
                    "https://olympustaff.com/uploads/manga_3fe94/38/8244726cc12c30a8d2d74b436d729a43.jpg",
                    "https://olympustaff.com/uploads/manga_3fe94/38/0c644b42caac1d9886fd4a4cc58474fe.jpg",
                    "https://olympustaff.com/uploads/manga_3fe94/38/b6b6562cb25b185fd7a99a0db9a54d5e.jpg",
                    "https://olympustaff.com/uploads/manga_3fe94/38/82479b5a1016d071aae96210a8245ea9.jpg",
                    "https://olympustaff.com/uploads/manga_3fe94/38/675bef823aa7ca55232c592fd3056b0f.jpg",
                    "https://olympustaff.com/uploads/manga_3fe94/38/831efc75ff1687a466165e86fc538173.jpg",
                    "https://olympustaff.com/uploads/manga_3fe94/38/a81e361ef8965bc629ad0650f0050094.jpg"
                ]
            },
            {
                "chapter": "39",
                "images": [
                    "https://olympustaff.com/uploads/manga_3fe94/39/2265222bf5c21a4ebcde0fed5d04918f.jpg",
                    "https://olympustaff.com/uploads/manga_3fe94/39/8620ea2f2bcefc427cce87749a82860d.jpg",
                    "https://olympustaff.com/uploads/manga_3fe94/39/4ae4d174b08231380dba7760cbb037d0.jpg",
                    "https://olympustaff.com/uploads/manga_3fe94/39/c35ce9350ef2f0172bf733cff893f353.jpg",
                    "https://olympustaff.com/uploads/manga_3fe94/39/f3db793232d1d6ac2cc80a6f1002e4b6.jpg",
                    "https://olympustaff.com/uploads/manga_3fe94/39/33936d8481ba78001c6c235b412f5fe2.jpg",
                    "https://olympustaff.com/uploads/manga_3fe94/39/e599fea1c094ce0c2a2d475d239df2cd.jpg"
                ]
            },
            {
                "chapter": "40",
                "images": [
                    "https://olympustaff.com/uploads/manga_3fe94/40/efb8579a3fa47452aabca06acd16a9c2.jpg",
                    "https://olympustaff.com/uploads/manga_3fe94/40/252f566b7097f78f202595c1ac24f750.jpg",
                    "https://olympustaff.com/uploads/manga_3fe94/40/08c05d4cda0aba7caf4c99eafa9599d2.jpg",
                    "https://olympustaff.com/uploads/manga_3fe94/40/c9ac4a4182218f8c8ba9deedcd21654b.jpg",
                    "https://olympustaff.com/uploads/manga_3fe94/40/2cd32a0375f705e180c17b8d263e72bf.jpg",
                    "https://olympustaff.com/uploads/manga_3fe94/40/d3cf8dc5cff0fbef6e55a86025ae78ed.jpg",
                    "https://olympustaff.com/uploads/manga_3fe94/40/5c41f55b89823b4239cde31ff5252801.jpg",
                    "https://olympustaff.com/uploads/manga_3fe94/40/3d250d8798de6bf1e1ab5c80b5c4e579.jpg"
                ]
            },
            {
                "chapter": "41",
                "images": [
                    "https://olympustaff.com/uploads/manga_3fe94/41/71701dd86935ef991580e687bc263f25.jpg",
                    "https://olympustaff.com/uploads/manga_3fe94/41/e3fec261d8ad637389ab2ebaa1c2f12b.jpg",
                    "https://olympustaff.com/uploads/manga_3fe94/41/ff51d954c36a07e7fa4954d0fae4fe97.jpg",
                    "https://olympustaff.com/uploads/manga_3fe94/41/06317a81eb3d1b93af3dfbc43b6d8139.jpg",
                    "https://olympustaff.com/uploads/manga_3fe94/41/1360ac87fde6bf20b10a12f69b1bbaca.jpg",
                    "https://olympustaff.com/uploads/manga_3fe94/41/3737733903094b8e05784f3476e69e99.jpg",
                    "https://olympustaff.com/uploads/manga_3fe94/41/18e1453e513c893305c073db057713f7.jpg",
                    "https://olympustaff.com/uploads/manga_3fe94/41/e3f26035530e803db6e3d4060da1691a.jpg"
                ]
            },
            {
                "chapter": "42",
                "images": [
                    "https://olympustaff.com/uploads/manga_3fe94/42/58d7ee0746bb50ff204c60f219cc496f.jpg",
                    "https://olympustaff.com/uploads/manga_3fe94/42/3236738f0e758e64e38585126d4685ea.jpg",
                    "https://olympustaff.com/uploads/manga_3fe94/42/c0229dbfd346c27a39d2aac228d83825.jpg",
                    "https://olympustaff.com/uploads/manga_3fe94/42/5c4c861b34ee486e1cdd0d3615f572d0.jpg",
                    "https://olympustaff.com/uploads/manga_3fe94/42/62c948f2f4d84a38add47d347bbb3a5b.jpg",
                    "https://olympustaff.com/uploads/manga_3fe94/42/1e700da19014fe31f5016b879c520d58.jpg",
                    "https://olympustaff.com/uploads/manga_3fe94/42/310a2957e6ab215092a9f1b88a2059b0.jpg",
                    "https://olympustaff.com/uploads/manga_3fe94/42/85b712888a642a9d80403b855936a2d0.jpg",
                    "https://olympustaff.com/uploads/manga_3fe94/42/4fd74cd74632678b48b54f13d5d881a5.jpg",
                    "https://olympustaff.com/uploads/manga_3fe94/42/0b499cc689a3e3c70b5cb3aea9905014.jpg",
                    "https://olympustaff.com/uploads/manga_3fe94/42/5501e2e133318f0d0145d44c64f61eb4.jpg"
                ]
            },
            {
                "chapter": "43",
                "images": [
                    "https://olympustaff.com/uploads/manga_3fe94/43/1dbefaa9b7df476417290f4837d5e1f7.jpg",
                    "https://olympustaff.com/uploads/manga_3fe94/43/d55bec14ac3b27e5a2a8c77c4a07290f.jpg",
                    "https://olympustaff.com/uploads/manga_3fe94/43/e9279d409a6cf7600c99cadd7369893d.jpg",
                    "https://olympustaff.com/uploads/manga_3fe94/43/431f628c9afa3f0cae3fb7057604d46c.jpg",
                    "https://olympustaff.com/uploads/manga_3fe94/43/cfcae689f309d330c3b816fd3858925f.jpg",
                    "https://olympustaff.com/uploads/manga_3fe94/43/1df5f43fc3c2cf0c8ad97161d925997d.jpg",
                    "https://olympustaff.com/uploads/manga_3fe94/43/0821ed44db786ceb0f7d4737c691f592.jpg",
                    "https://olympustaff.com/uploads/manga_3fe94/43/d5eea763273eca8b41c0d318cf686677.jpg",
                    "https://olympustaff.com/uploads/manga_3fe94/43/fe8a0bca33fd8ebb4ec436e2b7195c3a.jpg",
                    "https://olympustaff.com/uploads/manga_3fe94/43/837f2c0c13b4578a0db02232045beb37.jpg"
                ]
            },
            {
                "chapter": "44",
                "images": [
                    "https://olympustaff.com/uploads/manga_3fe94/44/b27369b6d6c32149db0c6bc6fdd5e33f.jpg",
                    "https://olympustaff.com/uploads/manga_3fe94/44/0aeae93ffcea9e50d10263b7249b25d9.jpg",
                    "https://olympustaff.com/uploads/manga_3fe94/44/e25a760259394898bbcd2a8a11306919.jpg",
                    "https://olympustaff.com/uploads/manga_3fe94/44/b895df24a34c2a334fd4517b92dab98d.jpg",
                    "https://olympustaff.com/uploads/manga_3fe94/44/7255d72f02fb554ba2c9a1a4fa326840.jpg",
                    "https://olympustaff.com/uploads/manga_3fe94/44/631b02739f2574780fd8c3248ea0a9ab.jpg",
                    "https://olympustaff.com/uploads/manga_3fe94/44/672d9d5489ea880a4a688b495c886892.jpg",
                    "https://olympustaff.com/uploads/manga_3fe94/44/da4d3683e42f26e74a510334d51c2c73.jpg",
                    "https://olympustaff.com/uploads/manga_3fe94/44/45635e2ea4b2e12079d1deb551732035.jpg",
                    "https://olympustaff.com/uploads/manga_3fe94/44/9c5e69f96a435811d7d0c0c3fe1e8fa0.jpg"
                ]
            },
            {
                "chapter": "45",
                "images": [
                    "https://olympustaff.com/uploads/manga_3fe94/45/85f07abfda5464521a79b4f29aa51644.jpg",
                    "https://olympustaff.com/uploads/manga_3fe94/45/401a23a2fa3748a22143f738f7f85e6f.jpg",
                    "https://olympustaff.com/uploads/manga_3fe94/45/6ff9b9c53682a9c08650abe94de44d5b.jpg",
                    "https://olympustaff.com/uploads/manga_3fe94/45/8e47267d9dcea8c8d2d1a0065d1355de.jpg",
                    "https://olympustaff.com/uploads/manga_3fe94/45/0adff0c252933af9a8c6af369f96857b.jpg",
                    "https://olympustaff.com/uploads/manga_3fe94/45/f6911f449d0436d624f17dcafaa76021.jpg",
                    "https://olympustaff.com/uploads/manga_3fe94/45/2670b73e8992c99611b5f997b84b957b.jpg",
                    "https://olympustaff.com/uploads/manga_3fe94/45/67f6848b469e88d8c2d4c7368206cb98.jpg",
                    "https://olympustaff.com/uploads/manga_3fe94/45/e7a7b3517ab5338caa0a4ec43a6c5a2b.jpg"
                ]
            },
            {
                "chapter": "46",
                "images": [
                    "https://olympustaff.com/uploads/manga_3fe94/46/e21d1dae0228d745d515d333740dbabd.jpg",
                    "https://olympustaff.com/uploads/manga_3fe94/46/e27e94bb388453e859c851faf0a64749.jpg",
                    "https://olympustaff.com/uploads/manga_3fe94/46/419d69314e582d53d39f561b1be6422b.jpg",
                    "https://olympustaff.com/uploads/manga_3fe94/46/2395263d0bd17d7a35759ff7e4b59cb3.jpg",
                    "https://olympustaff.com/uploads/manga_3fe94/46/896f022892bc5732d757724b55e4c864.jpg",
                    "https://olympustaff.com/uploads/manga_3fe94/46/1364aaa04e1f0b028f449d7bed7fff47.jpg",
                    "https://olympustaff.com/uploads/manga_3fe94/46/33913726a8d8b8dd3350fdd057e6596d.jpg",
                    "https://olympustaff.com/uploads/manga_3fe94/46/c808a4d865ee2954f81044b7b3113b18.jpg",
                    "https://olympustaff.com/uploads/manga_3fe94/46/917960dd4459ea79ecad2fe0a79e4108.jpg",
                    "https://olympustaff.com/uploads/manga_3fe94/46/4ceca0a805fe46d6f4e36283001ddd0a.jpg"
                ]
            },
            {
                "chapter": "47",
                "images": [
                    "https://olympustaff.com/uploads/manga_3fe94/47/9808162809ad504369ff422a495934b8.jpg",
                    "https://olympustaff.com/uploads/manga_3fe94/47/2d29ed7d4015740f375ca6f0c870e79a.jpg",
                    "https://olympustaff.com/uploads/manga_3fe94/47/631f290d8d8f8555d3da19fa4e25c969.jpg",
                    "https://olympustaff.com/uploads/manga_3fe94/47/19000613776714f384aaff4e6fc4fab6.jpg",
                    "https://olympustaff.com/uploads/manga_3fe94/47/5b76f14185129c340c76e47f674a3a58.jpg",
                    "https://olympustaff.com/uploads/manga_3fe94/47/178ce5b12cb31f9569f2e9e6501a3023.jpg",
                    "https://olympustaff.com/uploads/manga_3fe94/47/1c4fac4b2e2d2b2fb09804abd6fdce3c.jpg",
                    "https://olympustaff.com/uploads/manga_3fe94/47/7d39573c27323b609b5ca1b67d3e8dc5.jpg",
                    "https://olympustaff.com/uploads/manga_3fe94/47/31b64c6410b4164a3f77eb10a242fe71.jpg",
                    "https://olympustaff.com/uploads/manga_3fe94/47/61301fab5ae5959c0adb414d1c5c9ea4.jpg"
                ]
            },
            {
                "chapter": "48",
                "images": [
                    "https://olympustaff.com/uploads/manga_3fe94/48/ba02dd6d3276a928982b41fa943a3203.jpg",
                    "https://olympustaff.com/uploads/manga_3fe94/48/9b52ef22e7fea8aee9a79b56d7a017f7.jpg",
                    "https://olympustaff.com/uploads/manga_3fe94/48/9ddeee904edda0fcc4149a79c66b9b2e.jpg",
                    "https://olympustaff.com/uploads/manga_3fe94/48/4163e848d3170768ca52724d470951c0.jpg",
                    "https://olympustaff.com/uploads/manga_3fe94/48/72c820e14a51031f34ce737ac39693e5.jpg",
                    "https://olympustaff.com/uploads/manga_3fe94/48/eb8832026ba6256530095c05c60b9cda.jpg",
                    "https://olympustaff.com/uploads/manga_3fe94/48/99f2dbcc23c83866285144874936edc9.jpg"
                ]
            },
            {
                "chapter": "49",
                "images": [
                    "https://olympustaff.com/uploads/manga_3fe94/49/e7337bd79e970593b8c97c8665655f0b.jpg",
                    "https://olympustaff.com/uploads/manga_3fe94/49/2a2fd31a1ce52cb9af36a20238338b9a.jpg",
                    "https://olympustaff.com/uploads/manga_3fe94/49/893756c5bf6423a0233fe80d613d1ffe.jpg",
                    "https://olympustaff.com/uploads/manga_3fe94/49/0850468d64bf7cf605798910efd502cc.jpg",
                    "https://olympustaff.com/uploads/manga_3fe94/49/58c96e1b05371ca582f65637cd36c02e.jpg",
                    "https://olympustaff.com/uploads/manga_3fe94/49/e38775e9c5c0ca2813d0877e0fd7dbd4.jpg",
                    "https://olympustaff.com/uploads/manga_3fe94/49/f4bc0871024e812b701e789922488b31.jpg",
                    "https://olympustaff.com/uploads/manga_3fe94/49/43e2c822519b494f08facd67797eac9f.jpg"
                ]
            },
            {
                "chapter": "50",
                "images": [
                    "https://olympustaff.com/uploads/manga_3fe94/50/3c9a9ecedf48a1fc50efec7762faa43e.jpg",
                    "https://olympustaff.com/uploads/manga_3fe94/50/0d9bb86af9e54ef4e0ab6f8ba69813b0.jpg",
                    "https://olympustaff.com/uploads/manga_3fe94/50/dcacb54acfa4f96aa1dc33aa01f5c6ed.jpg",
                    "https://olympustaff.com/uploads/manga_3fe94/50/5aaf15a10b13733a2c72457964a4f591.jpg",
                    "https://olympustaff.com/uploads/manga_3fe94/50/8d85f52cab8b51f11f185422adf19732.jpg",
                    "https://olympustaff.com/uploads/manga_3fe94/50/812d04a1fd509979c95c14242d276b95.jpg",
                    "https://olympustaff.com/uploads/manga_3fe94/50/5b7b7c6783839dcfb932d4514a40b957.jpg"
                ]
            },
            {
                "chapter": "51",
                "images": [
                    "https://olympustaff.com/uploads/manga_3fe94/51/8f7aae1fe3bda2ebb385156cb6ab0350.jpg",
                    "https://olympustaff.com/uploads/manga_3fe94/51/ec0bab627a71c2ddfc4c9c1bca57a867.jpg",
                    "https://olympustaff.com/uploads/manga_3fe94/51/d75f6d35c9491d2c36624e81f3127ed1.jpg",
                    "https://olympustaff.com/uploads/manga_3fe94/51/f658cd774a742741dcecebed5089d19a.jpg",
                    "https://olympustaff.com/uploads/manga_3fe94/51/c4a2442db5b6f42eaa0c376d52b4cd90.jpg",
                    "https://olympustaff.com/uploads/manga_3fe94/51/faf0f12877d005c634af7ceba4924129.jpg",
                    "https://olympustaff.com/uploads/manga_3fe94/51/f2a0948e2f409b108522beccdcea159c.jpg",
                    "https://olympustaff.com/uploads/manga_3fe94/51/5a44e9ee56261b6a9bb560734c7a2d34.jpg"
                ]
            },
            {
                "chapter": "52",
                "images": [
                    "https://olympustaff.com/uploads/manga_3fe94/52/93eb1b30030f838c38645d5fad888174.jpg",
                    "https://olympustaff.com/uploads/manga_3fe94/52/badb5a29a3ad40ff1676bdeabc572663.jpg",
                    "https://olympustaff.com/uploads/manga_3fe94/52/72c9197c2bfe13b5e2756f54fb6b7d74.jpg",
                    "https://olympustaff.com/uploads/manga_3fe94/52/16869ad5b70eccaf8fdb80f3e37c36fd.jpg",
                    "https://olympustaff.com/uploads/manga_3fe94/52/a31d2e6d6ac2c188da0839516b0b797a.jpg",
                    "https://olympustaff.com/uploads/manga_3fe94/52/4737412b48fbeaacee1affea5e6fc349.jpg",
                    "https://olympustaff.com/uploads/manga_3fe94/52/fc9c47675fce799f1e3c0e17bfc17536.jpg",
                    "https://olympustaff.com/uploads/manga_3fe94/52/87271502077547c39aa9e53aed518ade.jpg"
                ]
            },
            {
                "chapter": "53",
                "images": [
                    "https://olympustaff.com/uploads/manga_3fe94/53/191007108bb29e7b2ed3cda17c1cb351.jpg",
                    "https://olympustaff.com/uploads/manga_3fe94/53/e92eb2fa71ed5f6d8f5a1e0c3c9dbb8c.jpg",
                    "https://olympustaff.com/uploads/manga_3fe94/53/d97c3cc248a9d59489081c6925d31cae.jpg",
                    "https://olympustaff.com/uploads/manga_3fe94/53/2b53b7a3d6ad3b495e17f81b9ae63adb.jpg",
                    "https://olympustaff.com/uploads/manga_3fe94/53/5caaaa9aceaea2b3f3ab17664cb9a651.jpg",
                    "https://olympustaff.com/uploads/manga_3fe94/53/1ebc0e5229feec5aaf7d325297b5ec50.jpg",
                    "https://olympustaff.com/uploads/manga_3fe94/53/5b1360a95ea40f708f35295282a51019.jpg"
                ]
            },
            {
                "chapter": "54",
                "images": [
                    "https://olympustaff.com/uploads/manga_3fe94/54/f4a77661cff850e61638ff9644b58711.jpg",
                    "https://olympustaff.com/uploads/manga_3fe94/54/140c34dbb588b171588e164252010cbf.jpg",
                    "https://olympustaff.com/uploads/manga_3fe94/54/ace66b38820df323ea1cf92086c6d346.jpg",
                    "https://olympustaff.com/uploads/manga_3fe94/54/9961aee87dcc7c51aae8a731d8978f65.jpg",
                    "https://olympustaff.com/uploads/manga_3fe94/54/6ea723135ef54c99281231e618e13254.jpg",
                    "https://olympustaff.com/uploads/manga_3fe94/54/158ef4d6221811b8e0b1e5a2c60ec137.jpg",
                    "https://olympustaff.com/uploads/manga_3fe94/54/7321015027e08e3b6a7999d4aabe9ace.jpg",
                    "https://olympustaff.com/uploads/manga_3fe94/54/64f63d12136830f75168c0b35e35e166.jpg"
                ]
            },
            {
                "chapter": "55",
                "images": [
                    "https://olympustaff.com/uploads/manga_3fe94/55/fb3220a197aacbc4385f08babaad5dd3.jpg",
                    "https://olympustaff.com/uploads/manga_3fe94/55/eb057690c8ab5f9758a9d97617d90a56.jpg",
                    "https://olympustaff.com/uploads/manga_3fe94/55/c541bd1c9f1d56ad3c66754309c1907b.jpg",
                    "https://olympustaff.com/uploads/manga_3fe94/55/07f9983ed79c7ea868d768d058746df2.jpg",
                    "https://olympustaff.com/uploads/manga_3fe94/55/a61fcc45a3febdc576fa9ca4b117c30a.jpg",
                    "https://olympustaff.com/uploads/manga_3fe94/55/d2ad7089285cafa5fb0e2ad67f7bd15f.jpg",
                    "https://olympustaff.com/uploads/manga_3fe94/55/12870dba505a8cea158725da27d0e6b4.jpg",
                    "https://olympustaff.com/uploads/manga_3fe94/55/d9ca58d44ab10116ff642ca4b2329ba4.jpg"
                ]
            },
            {
                "chapter": "56",
                "images": [
                    "https://olympustaff.com/uploads/manga_3fe94/56/cf205c0ac2d02aee637ef46b6b21de85.jpg",
                    "https://olympustaff.com/uploads/manga_3fe94/56/fe7324b253ceb1b25280d77b159242bc.jpg",
                    "https://olympustaff.com/uploads/manga_3fe94/56/c0cce615cffed0f261324105ac142950.jpg",
                    "https://olympustaff.com/uploads/manga_3fe94/56/c340df5d76309848721efa02b2dfadd3.jpg",
                    "https://olympustaff.com/uploads/manga_3fe94/56/07be1075d51e598f91f8364721056948.jpg",
                    "https://olympustaff.com/uploads/manga_3fe94/56/99b45998b5b8fbe47d3d67dcacf4a5be.jpg",
                    "https://olympustaff.com/uploads/manga_3fe94/56/20b8f3b7b61600ea29b411b773d52c83.jpg"
                ]
            },
            {
                "chapter": "57",
                "images": [
                    "https://olympustaff.com/uploads/manga_3fe94/57/566ae823dc9c89cfd6ef6d2e451ad63a.jpg",
                    "https://olympustaff.com/uploads/manga_3fe94/57/cbc68643b2bc1d9970fc630667c68ec2.jpg",
                    "https://olympustaff.com/uploads/manga_3fe94/57/ca74d5a6361d999482717b504193d299.jpg",
                    "https://olympustaff.com/uploads/manga_3fe94/57/f660d96d455f3daec94a3948d08def29.jpg",
                    "https://olympustaff.com/uploads/manga_3fe94/57/944fb5690e5472a31e62de4abd081e84.jpg",
                    "https://olympustaff.com/uploads/manga_3fe94/57/a984315e68c84541b2a81b806b0f5f74.jpg",
                    "https://olympustaff.com/uploads/manga_3fe94/57/98afbc1ea3213278655cd136832eb2cd.jpg",
                    "https://olympustaff.com/uploads/manga_3fe94/57/04be3f110201c507bdf6e0db992abd83.jpg"
                ]
            },
            {
                "chapter": "58",
                "images": [
                    "https://olympustaff.com/uploads/manga_3fe94/58/0b02d96d93e2117dab325b3544b63577.jpg",
                    "https://olympustaff.com/uploads/manga_3fe94/58/54c8c72fc00fc458d00d6f4d8d1e68f4.jpg",
                    "https://olympustaff.com/uploads/manga_3fe94/58/7a38a40569e18dbca045e382631139e3.jpg",
                    "https://olympustaff.com/uploads/manga_3fe94/58/7a0637d63b2ffb62bcfd095881d6417c.jpg",
                    "https://olympustaff.com/uploads/manga_3fe94/58/d3be37cb94124ec6debdc65c4cd4f712.jpg",
                    "https://olympustaff.com/uploads/manga_3fe94/58/bbb6901365e723d61855a22b296ab87d.jpg"
                ]
            },
            {
                "chapter": "59",
                "images": [
                    "https://olympustaff.com/uploads/manga_3fe94/59/14c431ac537ca712c98bbea472e4dd33.jpg",
                    "https://olympustaff.com/uploads/manga_3fe94/59/002a198fce12b281d02b5889a67c6cdc.jpg",
                    "https://olympustaff.com/uploads/manga_3fe94/59/dbd63a518b33876a146bc1189d72e720.jpg",
                    "https://olympustaff.com/uploads/manga_3fe94/59/d14739d5573ae735dce2e34f17832476.jpg",
                    "https://olympustaff.com/uploads/manga_3fe94/59/4d678b121fb60b9c5c49cda0f7e7bb5b.jpg",
                    "https://olympustaff.com/uploads/manga_3fe94/59/1b8fe11524a0400af3668fb9cfb53de4.jpg",
                    "https://olympustaff.com/uploads/manga_3fe94/59/e9fe7ad9b82d02f5c8be78f50911622c.jpg"
                ]
            },
            {
                "chapter": "60",
                "images": [
                    "https://olympustaff.com/uploads/manga_3fe94/60/e91e7688e98e85051c818bb5cbe722f3.jpg",
                    "https://olympustaff.com/uploads/manga_3fe94/60/810e7d674f7c8657d7a467299bdae37f.jpg",
                    "https://olympustaff.com/uploads/manga_3fe94/60/966b548eafb78fdac59a6c41e557849a.jpg",
                    "https://olympustaff.com/uploads/manga_3fe94/60/fbcb45c8ed8109135343c8cf2083421a.jpg",
                    "https://olympustaff.com/uploads/manga_3fe94/60/c7322722a2a87ddae082920ee524036b.jpg",
                    "https://olympustaff.com/uploads/manga_3fe94/60/ebe3b25c305a4accb1d8793db332cff3.jpg",
                    "https://olympustaff.com/uploads/manga_3fe94/60/ef1f072c5cd45bbc8b2d5d314016ec61.jpg",
                    "https://olympustaff.com/uploads/manga_3fe94/60/4d0c5093cb39af4c20c30a1afea3d672.jpg"
                ]
            },
            {
                "chapter": "61",
                "images": [
                    "https://olympustaff.com/uploads/manga_3fe94/61/9f4c9b3933d0fe3df46edda25b6cf35e.jpg",
                    "https://olympustaff.com/uploads/manga_3fe94/61/0c30ba8cba6addcf9f8515bf0093648b.jpg",
                    "https://olympustaff.com/uploads/manga_3fe94/61/74fe57b58bd1c448e41884a364cc9695.jpg",
                    "https://olympustaff.com/uploads/manga_3fe94/61/ea2b74a010b9fab56a3e4698e88fb6db.jpg",
                    "https://olympustaff.com/uploads/manga_3fe94/61/fdffa941fb6018b4d749b529acde4249.jpg",
                    "https://olympustaff.com/uploads/manga_3fe94/61/a25f582a4a507777351c57f52d45c597.jpg",
                    "https://olympustaff.com/uploads/manga_3fe94/61/985329e935869efdb795d4df62ba3627.jpg",
                    "https://olympustaff.com/uploads/manga_3fe94/61/fc2fa692996e7d2bb1d6a7e85bcba26c.jpg",
                    "https://olympustaff.com/uploads/manga_3fe94/61/ff468040dd04458983de3f075bae088c.jpg"
                ]
            },
            {
                "chapter": "62",
                "images": [
                    "https://olympustaff.com/uploads/manga_3fe94/62/94fc7103553c3520aa36a24bea0f81a1.jpg",
                    "https://olympustaff.com/uploads/manga_3fe94/62/8e170c188fa2888172502948681642fc.jpg",
                    "https://olympustaff.com/uploads/manga_3fe94/62/1e71ae19141476c1fe5451fdbd3efe61.jpg",
                    "https://olympustaff.com/uploads/manga_3fe94/62/a691d8ad4eef453af55704ff7faa58b7.jpg",
                    "https://olympustaff.com/uploads/manga_3fe94/62/f6b13c78a76b6412297213d763f800d5.jpg",
                    "https://olympustaff.com/uploads/manga_3fe94/62/00b4c16bc0db242187acf8dba4dc7596.jpg",
                    "https://olympustaff.com/uploads/manga_3fe94/62/1cb1e9f5c7c00c168e52c6b395db2a36.jpg",
                    "https://olympustaff.com/uploads/manga_3fe94/62/cd10c4f7416faa4c780d285d64f585f3.jpg"
                ]
            },
            {
                "chapter": "63",
                "images": [
                    "https://olympustaff.com/uploads/manga_3fe94/63/a78b972afc85749195d3ef9c3f89cdaa.webp",
                    "https://olympustaff.com/uploads/manga_3fe94/63/cc0a6b3d6ff3765ecf7ead0b66d6af11.webp",
                    "https://olympustaff.com/uploads/manga_3fe94/63/e5de9818b2c6f179c10105f490f95eaa.webp",
                    "https://olympustaff.com/uploads/manga_3fe94/63/fd2cbe6a3056ed93dc5029079b38c8bb.webp",
                    "https://olympustaff.com/uploads/manga_3fe94/63/e97999ba8c62937f50994d160e7b1bc3.webp",
                    "https://olympustaff.com/uploads/manga_3fe94/63/a48862bdba35758843350a2670e87bf3.webp",
                    "https://olympustaff.com/uploads/manga_3fe94/63/cd69d93fe026670a4783d4f4964fbc2b.webp",
                    "https://olympustaff.com/uploads/manga_3fe94/63/33d8477baa87c8271c5c1bdf8da97b0d.webp",
                    "https://olympustaff.com/uploads/manga_3fe94/63/5ec3f6c098e90703816cbb41bb7427bd.webp"
                ]
            },
            {
                "chapter": "64",
                "images": [
                    "https://olympustaff.com/uploads/manga_3fe94/64/7b68a25589d6e5cdb975c7b703474c4b.webp",
                    "https://olympustaff.com/uploads/manga_3fe94/64/007cf11f1f845c5c340b49bd158b7135.webp",
                    "https://olympustaff.com/uploads/manga_3fe94/64/63d9b8fd1fd3859d3cfc27e49e6ed76d.webp",
                    "https://olympustaff.com/uploads/manga_3fe94/64/169c9a0f9e61896dfdc80d2b04385b0a.webp",
                    "https://olympustaff.com/uploads/manga_3fe94/64/0f0de0cf373a37b87dc3158186f0cefd.webp",
                    "https://olympustaff.com/uploads/manga_3fe94/64/95c352a99604ff7b1cd3e8f8a3dc9d8d.webp",
                    "https://olympustaff.com/uploads/manga_3fe94/64/33f7d16222de59ef92e080aa45211ad2.webp"
                ]
            },
            {
                "chapter": "65",
                "images": [
                    "https://olympustaff.com/uploads/manga_3fe94/65/6aad7dc0bee4096aeddabbb6505c2bab.webp",
                    "https://olympustaff.com/uploads/manga_3fe94/65/ea11979ad93af98a8a95e1aee4ed0493.webp",
                    "https://olympustaff.com/uploads/manga_3fe94/65/1654728f6b5d095a698389a034a36db5.webp",
                    "https://olympustaff.com/uploads/manga_3fe94/65/ce2ca4f65d164cc5dedbadbb88ebab5b.webp",
                    "https://olympustaff.com/uploads/manga_3fe94/65/b56fcc39c1686b27ca95d216458b2309.webp",
                    "https://olympustaff.com/uploads/manga_3fe94/65/69567acb80afe852a60d4a29ec116c9a.webp",
                    "https://olympustaff.com/uploads/manga_3fe94/65/86dabebd5a5d1cca148e151b418a85d7.webp",
                    "https://olympustaff.com/uploads/manga_3fe94/65/300e92c3a809655c11d0be73205e4f52.webp"
                ]
            },
            {
                "chapter": "66",
                "images": [
                    "https://olympustaff.com/uploads/manga_3fe94/66/47e90741b6e55cca4dac4b6d14f7fb9b.jpg",
                    "https://olympustaff.com/uploads/manga_3fe94/66/6ffbddad639e78afd2fde91d3c1f85dc.jpg",
                    "https://olympustaff.com/uploads/manga_3fe94/66/866ca4ad6be3daff0bd9540b53c229f0.jpg",
                    "https://olympustaff.com/uploads/manga_3fe94/66/dc28791747b8f81cc9bce1b95333cf69.jpg",
                    "https://olympustaff.com/uploads/manga_3fe94/66/08a27e0e844c20b9b7f40379318c5149.jpg",
                    "https://olympustaff.com/uploads/manga_3fe94/66/461b52bc83383897b21017d8fb46313b.jpg",
                    "https://olympustaff.com/uploads/manga_3fe94/66/0492f29cc1ad5e64c6c8d8d9d0a9b8cb.jpg"
                ]
            },
            {
                "chapter": "67",
                "images": [
                    "https://olympustaff.com/uploads/manga_3fe94/67/c90ad08a5761247a5fedaa75d75d90fe.jpg",
                    "https://olympustaff.com/uploads/manga_3fe94/67/e71ecd01f376c7b9b6bfd2f5750b4304.jpg",
                    "https://olympustaff.com/uploads/manga_3fe94/67/faf19e7f8a30f1c49ea1411936a42f51.jpg",
                    "https://olympustaff.com/uploads/manga_3fe94/67/5333fd2b12d946303e8bea9fd01cdd6d.jpg",
                    "https://olympustaff.com/uploads/manga_3fe94/67/ec528ff08af0786cd68fb8c6fa6179f1.jpg",
                    "https://olympustaff.com/uploads/manga_3fe94/67/885b8e591ea03458e1c4cdf92d3323b4.jpg",
                    "https://olympustaff.com/uploads/manga_3fe94/67/643a1bec4a0928f51164f99c7e232eb2.jpg"
                ]
            },
            {
                "chapter": "68",
                "images": [
                    "https://olympustaff.com/uploads/manga_3fe94/68/b1f09cde6e4b851746b0b04608c1c204.jpg",
                    "https://olympustaff.com/uploads/manga_3fe94/68/942ad3f6eb0895f7c7f091ef3b46c457.jpg",
                    "https://olympustaff.com/uploads/manga_3fe94/68/6c4777d545b5d772fce2e057e86f342b.jpg",
                    "https://olympustaff.com/uploads/manga_3fe94/68/642abdb8004a361752a80e79007b31ea.jpg",
                    "https://olympustaff.com/uploads/manga_3fe94/68/c479e8044023f1039a0d26976f5cd5e1.jpg",
                    "https://olympustaff.com/uploads/manga_3fe94/68/6a53352e9009993c9bb95f75e6348990.jpg",
                    "https://olympustaff.com/uploads/manga_3fe94/68/2847fa1695fd808753ce4b9dd372eff6.jpg"
                ]
            },
            {
                "chapter": "69",
                "images": [
                    "https://olympustaff.com/uploads/manga_3fe94/69/bcc3bb4f1156bd669b84d176c398cdcd.jpg",
                    "https://olympustaff.com/uploads/manga_3fe94/69/9ae6e433094cb5d852822f428f4019dd.jpg",
                    "https://olympustaff.com/uploads/manga_3fe94/69/3f75dbe9ef247a31d51182d483e988e8.jpg",
                    "https://olympustaff.com/uploads/manga_3fe94/69/5832c77d2ff06ebe68aa2917348fdd07.jpg",
                    "https://olympustaff.com/uploads/manga_3fe94/69/4d98d6eb4d407d44b18c27d53c166d1f.jpg",
                    "https://olympustaff.com/uploads/manga_3fe94/69/0612664bfc83b915d12319ee17b27808.jpg",
                    "https://olympustaff.com/uploads/manga_3fe94/69/fb9072f274d1cdb3b29709d41d8c25af.jpg"
                ]
            },
            {
                "chapter": "70",
                "images": [
                    "https://olympustaff.com/uploads/manga_3fe94/70/c5202ef6e8864fe274ec7cd587c11f41.jpg",
                    "https://olympustaff.com/uploads/manga_3fe94/70/ff6d510a6c7af144dd65501f51ecb2ba.jpg",
                    "https://olympustaff.com/uploads/manga_3fe94/70/92163b28f5043919849e6d83f6d76fa6.jpg",
                    "https://olympustaff.com/uploads/manga_3fe94/70/6ec4b0acbb457be88ba3a50d2190c2e7.jpg",
                    "https://olympustaff.com/uploads/manga_3fe94/70/e9401e9619178e547ab37900260b22ed.jpg",
                    "https://olympustaff.com/uploads/manga_3fe94/70/07d1b635be50436753275f6f194bceb3.jpg",
                    "https://olympustaff.com/uploads/manga_3fe94/70/447669f0ced733b84c6585f79fd644d8.jpg"
                ]
            },
            {
                "chapter": "71",
                "images": [
                    "https://olympustaff.com/uploads/manga_3fe94/71/6f73da7a11e84e6ddbecd2000dcde5a1.jpg",
                    "https://olympustaff.com/uploads/manga_3fe94/71/9cd96460c4d68b1da5d7091bed8dcafb.jpg",
                    "https://olympustaff.com/uploads/manga_3fe94/71/878517727e18c921315960a235233ce2.jpg",
                    "https://olympustaff.com/uploads/manga_3fe94/71/6c3a82a57a1f7721d7eb119032eb33bf.jpg",
                    "https://olympustaff.com/uploads/manga_3fe94/71/019d888c369a5acbb91edccdd155e944.jpg",
                    "https://olympustaff.com/uploads/manga_3fe94/71/0c6ae08f7071f3bd4afc6f5a92a2d802.jpg"
                ]
            },
            {
                "chapter": "72",
                "images": [
                    "https://olympustaff.com/uploads/manga_3fe94/72/cd6ae2b7c5ff0adaf08dbbd8ca86cec3.jpg",
                    "https://olympustaff.com/uploads/manga_3fe94/72/b4f2b312889ee62ecc04c09519b14624.jpg",
                    "https://olympustaff.com/uploads/manga_3fe94/72/2748e6f96e0f3c167440738f16ccafd2.jpg",
                    "https://olympustaff.com/uploads/manga_3fe94/72/8ce353201f29a6d72ad27ad231fd304c.jpg",
                    "https://olympustaff.com/uploads/manga_3fe94/72/04daeecd2c66e7892a51af122c9e715d.jpg",
                    "https://olympustaff.com/uploads/manga_3fe94/72/35a64128fab30e0c963abcccefa9d397.jpg",
                    "https://olympustaff.com/uploads/manga_3fe94/72/e93e6fafffa82e3ec6ea97d2ee4f3b2b.jpg"
                ]
            },
            {
                "chapter": "73",
                "images": [
                    "https://olympustaff.com/uploads/manga_3fe94/73/c81d0ff22334d745c430a9c025f7406e.jpg",
                    "https://olympustaff.com/uploads/manga_3fe94/73/8c54e09ad42565a00bb87e93f366cde7.jpg",
                    "https://olympustaff.com/uploads/manga_3fe94/73/86ce72812c23db392404dcfb3d2f728f.jpg",
                    "https://olympustaff.com/uploads/manga_3fe94/73/dc38d70e824fc28df4ed03e7ecfd2bae.jpg",
                    "https://olympustaff.com/uploads/manga_3fe94/73/f007d4481b72c5bca3dcf42ae5b9339e.jpg",
                    "https://olympustaff.com/uploads/manga_3fe94/73/1eb0c19bb7abbc7299b1ee03994a0e74.jpg",
                    "https://olympustaff.com/uploads/manga_3fe94/73/294f07808c7502324a31ba80ee4d3545.jpg"
                ]
            },
            {
                "chapter": "74",
                "images": [
                    "https://olympustaff.com/uploads/manga_3fe94/74/3a8d2832ff8fd218146883d9cc5e0029.webp",
                    "https://olympustaff.com/uploads/manga_3fe94/74/6ab4cb2e543ae70f70ea7934ad342e56.webp",
                    "https://olympustaff.com/uploads/manga_3fe94/74/2c1f617b366976fbcd0f19d0beda7775.webp",
                    "https://olympustaff.com/uploads/manga_3fe94/74/6187db28af98473bb3838da4e92a62eb.webp",
                    "https://olympustaff.com/uploads/manga_3fe94/74/c0fbe320a02bd7137e67537e2c20ad95.webp",
                    "https://olympustaff.com/uploads/manga_3fe94/74/e07f6bc6ab2e07415ee40f6ffee350aa.webp",
                    "https://olympustaff.com/uploads/manga_3fe94/74/79af3c6bae085d19f6ccbb20e2a53bf8.webp"
                ]
            },
            {
                "chapter": "75",
                "images": [
                    "https://olympustaff.com/uploads/manga_3fe94/75/68d1cb90507c996d17f86b414a397e8d.webp",
                    "https://olympustaff.com/uploads/manga_3fe94/75/5bdb907f34a846aac5ce9180ac871252.webp",
                    "https://olympustaff.com/uploads/manga_3fe94/75/0909c478992158682f058e812870d60d.webp",
                    "https://olympustaff.com/uploads/manga_3fe94/75/5f1ad1b689282703191279ae5cc197c8.webp",
                    "https://olympustaff.com/uploads/manga_3fe94/75/e09952fa33dbbd59a606ae7556b882a0.webp",
                    "https://olympustaff.com/uploads/manga_3fe94/75/d2d289010409ad56852b9892d415eea6.webp",
                    "https://olympustaff.com/uploads/manga_3fe94/75/eb59f98fda2d90e679aee3a3192ccb18.webp"
                ]
            },
            {
                "chapter": "76",
                "images": [
                    "https://olympustaff.com/uploads/manga_3fe94/76/b1ead17c7b33370baaf22873579a174a.webp",
                    "https://olympustaff.com/uploads/manga_3fe94/76/b71208d0366d9cde9cbaae02eb0f63d2.webp",
                    "https://olympustaff.com/uploads/manga_3fe94/76/da787c55bc213bc42f7262b68f349a28.webp",
                    "https://olympustaff.com/uploads/manga_3fe94/76/1664cb076130a562cb4f83a9f524793c.webp",
                    "https://olympustaff.com/uploads/manga_3fe94/76/814782011b77347aebe1d420eb87a330.webp",
                    "https://olympustaff.com/uploads/manga_3fe94/76/c14e274048a9c03cc1230a0a3b0be1c5.webp",
                    "https://olympustaff.com/uploads/manga_3fe94/76/4ae30e6a9198324e3d7262f106eba3de.webp"
                ]
            },
            {
                "chapter": "77",
                "images": [
                    "https://olympustaff.com/uploads/manga_3fe94/77/fe6b1b8de549cf99bde294f7ef9d9600.webp",
                    "https://olympustaff.com/uploads/manga_3fe94/77/5caf4178e19943d855c5b6362efccc94.webp",
                    "https://olympustaff.com/uploads/manga_3fe94/77/726697fd71228e6136044efd29a93017.webp",
                    "https://olympustaff.com/uploads/manga_3fe94/77/d233bedcf2ebce29fb19aab3f2238e10.webp",
                    "https://olympustaff.com/uploads/manga_3fe94/77/22fd8c6807f3bc0f452f7b8081c279db.webp",
                    "https://olympustaff.com/uploads/manga_3fe94/77/105170fa40b78ac65f593c94214c9432.webp",
                    "https://olympustaff.com/uploads/manga_3fe94/77/e77e00c85c6c9fd264aa947a13efd001.webp"
                ]
            },
            {
                "chapter": "78",
                "images": [
                    "https://olympustaff.com/uploads/manga_3fe94/78/2d9acc5f1587b674846de462bb2cc439.webp",
                    "https://olympustaff.com/uploads/manga_3fe94/78/ad28eb949549924b54443f0d41af051b.webp",
                    "https://olympustaff.com/uploads/manga_3fe94/78/ff28f4aa4e96927d240b621b8bb4439a.webp",
                    "https://olympustaff.com/uploads/manga_3fe94/78/37776e4f22dbbafffd9f01948b436b95.webp",
                    "https://olympustaff.com/uploads/manga_3fe94/78/9085923227f334b0a4742a34f69a4943.webp",
                    "https://olympustaff.com/uploads/manga_3fe94/78/d0ce775486e07b3754737804bc7d0878.webp",
                    "https://olympustaff.com/uploads/manga_3fe94/78/f49fa097c188f85e23e60ec78fdfbfee.webp",
                    "https://olympustaff.com/uploads/manga_3fe94/78/c19ff68d379e53c8a1647b537f67fbc4.webp"
                ]
            },
            {
                "chapter": "79",
                "images": [
                    "https://olympustaff.com/uploads/manga_3fe94/79/c4b3671b9832e962aabc21a193336eef.webp",
                    "https://olympustaff.com/uploads/manga_3fe94/79/1b522a2d5b672b08f0b0d2ee5a5da935.webp",
                    "https://olympustaff.com/uploads/manga_3fe94/79/c763b325e833eb1fdce6da4f42f1b2c7.webp",
                    "https://olympustaff.com/uploads/manga_3fe94/79/50561eb2dc2c476ae093c3bdf2184288.webp",
                    "https://olympustaff.com/uploads/manga_3fe94/79/b0d94db6a59b10f4da4affae1514d051.webp",
                    "https://olympustaff.com/uploads/manga_3fe94/79/53d5e44298d3f10cf624f94ad8fc53fc.webp",
                    "https://olympustaff.com/uploads/manga_3fe94/79/a4a03249d67b5a0fe16f137773e5366a.webp",
                    "https://olympustaff.com/uploads/manga_3fe94/79/1aeea6d39343240aa764e6b9ec1c7058.webp"
                ]
            },
            {
                "chapter": "80",
                "images": [
                    "https://olympustaff.com/uploads/manga_3fe94/80/4a05b5e460d36ecc2f02b23a552f9411.webp",
                    "https://olympustaff.com/uploads/manga_3fe94/80/b9788e2f3793a194a70fd0679202fba6.webp",
                    "https://olympustaff.com/uploads/manga_3fe94/80/12fcf9e4a29a8d2c0f9674670031ce5d.webp",
                    "https://olympustaff.com/uploads/manga_3fe94/80/8b8b044b3a31005953490a45d7e33316.webp",
                    "https://olympustaff.com/uploads/manga_3fe94/80/c574c38a7911b5282cf7b2faf7b2a712.webp",
                    "https://olympustaff.com/uploads/manga_3fe94/80/189b65dd2e9c169c649d1b166015927b.webp",
                    "https://olympustaff.com/uploads/manga_3fe94/80/167dd8e26eb94a39276c2654662f1bba.webp"
                ]
            },
            {
                "chapter": "81",
                "images": [
                    "https://olympustaff.com/uploads/manga_3fe94/81/53755fe57806950e866d1d5677351cf7.webp",
                    "https://olympustaff.com/uploads/manga_3fe94/81/e7fb9102c1f82447bbed280a2a941e2f.webp",
                    "https://olympustaff.com/uploads/manga_3fe94/81/c88ea4c7f8496b1877aa6f230e53e98d.webp",
                    "https://olympustaff.com/uploads/manga_3fe94/81/35fc48a64d7ddbb419ead507d82eb9f6.webp",
                    "https://olympustaff.com/uploads/manga_3fe94/81/4800702e9f59c37d1464dd37d5e9a2dc.webp",
                    "https://olympustaff.com/uploads/manga_3fe94/81/19abb458f040ad6b5466d63f1a8128da.webp",
                    "https://olympustaff.com/uploads/manga_3fe94/81/22c55b372ec68bd86eb23ea636d2d569.webp",
                    "https://olympustaff.com/uploads/manga_3fe94/81/ef531fcf154eb4255b39fbb61f4e80cd.webp"
                ]
            },
            {
                "chapter": "82",
                "images": [
                    "https://olympustaff.com/uploads/manga_3fe94/82/a4fa8dd76b7b2cc6d6da0d1b55ba724a.webp",
                    "https://olympustaff.com/uploads/manga_3fe94/82/49f2ce3db7d12db8aac9ad341052b3ba.webp",
                    "https://olympustaff.com/uploads/manga_3fe94/82/4d3c8ba170ef09ed614bb070e58faa27.webp",
                    "https://olympustaff.com/uploads/manga_3fe94/82/23fabc0a32d51f29deb476f34a7f89be.webp",
                    "https://olympustaff.com/uploads/manga_3fe94/82/895037632a81bd469304c680ad956ce9.webp",
                    "https://olympustaff.com/uploads/manga_3fe94/82/485a77dcde9de7e61cc12eae10753466.webp",
                    "https://olympustaff.com/uploads/manga_3fe94/82/77286d11fa6192973b3f30e214aae861.webp",
                    "https://olympustaff.com/uploads/manga_3fe94/82/b020c9c20bc55815f17bd1bb69a4d1e2.webp"
                ]
            },
            {
                "chapter": "83",
                "images": [
                    "https://olympustaff.com/uploads/manga_3fe94/83/0da794f94b62c4caa8f781278a47153e.webp",
                    "https://olympustaff.com/uploads/manga_3fe94/83/33001c33887a7d18c75e4ffc0a63b61f.webp",
                    "https://olympustaff.com/uploads/manga_3fe94/83/6aa95fb03aaa1e9acbeeb54d2d17e835.webp",
                    "https://olympustaff.com/uploads/manga_3fe94/83/d014b35ab370547e7ef6cf33c8e23058.webp",
                    "https://olympustaff.com/uploads/manga_3fe94/83/0c159bfbf9742d76bf68f8a114924b03.webp",
                    "https://olympustaff.com/uploads/manga_3fe94/83/8ed7174c2eff54a9b592b20b09f2d877.webp",
                    "https://olympustaff.com/uploads/manga_3fe94/83/3a8f2af2a68018a8df11a04272269655.webp",
                    "https://olympustaff.com/uploads/manga_3fe94/83/928a3130d852b3345ce14d7b0db11af4.webp"
                ]
            },
            {
                "chapter": "84",
                "images": [
                    "https://olympustaff.com/uploads/manga_3fe94/84/8d65832348aacdb895f7f2c72aed95d0.webp",
                    "https://olympustaff.com/uploads/manga_3fe94/84/522e31cf076493fd5ac02043f075cabf.webp",
                    "https://olympustaff.com/uploads/manga_3fe94/84/e9ea94816f7c76c2a9ec3640666d5aa8.webp",
                    "https://olympustaff.com/uploads/manga_3fe94/84/9299b1f5bca0087b76d323f31b0328a9.webp",
                    "https://olympustaff.com/uploads/manga_3fe94/84/5226c2980221518ffb29cdc2af02dac6.webp",
                    "https://olympustaff.com/uploads/manga_3fe94/84/bc8d3383801091211d2d872914b98e8a.webp",
                    "https://olympustaff.com/uploads/manga_3fe94/84/6fbe0d4c35fd40f9f70b4a74d504c62f.webp",
                    "https://olympustaff.com/uploads/manga_3fe94/84/21b1af1fcd17879232d8a93844e2e4ef.webp"
                ]
            },
            {
                "chapter": "85",
                "images": [
                    "https://olympustaff.com/uploads/manga_3fe94/85/c8e7bb76461c73670eb27dba60ed8695.webp",
                    "https://olympustaff.com/uploads/manga_3fe94/85/292418112803dcf04615bb2f3bb4b75f.webp",
                    "https://olympustaff.com/uploads/manga_3fe94/85/3acd45ea3c692c0febbb493b76867b49.webp",
                    "https://olympustaff.com/uploads/manga_3fe94/85/338f49a8ef3fc9fa272ecdff727e621d.webp",
                    "https://olympustaff.com/uploads/manga_3fe94/85/261125a79ce1353fcc021cb46db0874f.webp",
                    "https://olympustaff.com/uploads/manga_3fe94/85/b256f5695f7a8f7476c8910b4a78d3ad.webp",
                    "https://olympustaff.com/uploads/manga_3fe94/85/aa9c78979f0cb4f314fb12e43c593ecc.webp"
                ]
            },
            {
                "chapter": "86",
                "images": [
                    "https://olympustaff.com/uploads/manga_3fe94/86/b2adf45ba4e0a5c4d4a69ca1456bfc05.webp",
                    "https://olympustaff.com/uploads/manga_3fe94/86/7507ed6d00e3a9ad8daddb91c05ec01d.webp",
                    "https://olympustaff.com/uploads/manga_3fe94/86/23e5ea1740af0e176c5900993a143fcc.webp",
                    "https://olympustaff.com/uploads/manga_3fe94/86/77fc4cdc763e279558d766c1b7c8b3ea.webp",
                    "https://olympustaff.com/uploads/manga_3fe94/86/cf3deddf0a11e6d0302428c5cd9c3aca.webp",
                    "https://olympustaff.com/uploads/manga_3fe94/86/6e6c3d1a1414e40df0ff6aa0587b9186.webp",
                    "https://olympustaff.com/uploads/manga_3fe94/86/1d98cadf0fd3a0fcd718337bc8740777.webp",
                    "https://olympustaff.com/uploads/manga_3fe94/86/7c00b3ef9e11cc8acdffc6502aeee78a.webp"
                ]
            },
            {
                "chapter": "87",
                "images": [
                    "https://olympustaff.com/uploads/manga_3fe94/87/1dd4c789d3001d59a50db3f585f588c7.webp",
                    "https://olympustaff.com/uploads/manga_3fe94/87/81cd4eea89aa04e9dfc1803010bfd631.webp",
                    "https://olympustaff.com/uploads/manga_3fe94/87/f344783e5d05b6a853e36abb229a1209.webp",
                    "https://olympustaff.com/uploads/manga_3fe94/87/58e42eb71256dc09deb408324bb4237c.webp",
                    "https://olympustaff.com/uploads/manga_3fe94/87/0b8ae290581b4dae80d85de929eb38d4.webp",
                    "https://olympustaff.com/uploads/manga_3fe94/87/049f91f4045986d74fc650c082ac7492.webp",
                    "https://olympustaff.com/uploads/manga_3fe94/87/509ea5ee92a658069fd8cf1ce519b294.webp",
                    "https://olympustaff.com/uploads/manga_3fe94/87/d21042d6855775a30777bf7250d11828.webp",
                    "https://olympustaff.com/uploads/manga_3fe94/87/210f47f8ea1309e17720cc9444cbfe25.webp"
                ]
            },
            {
                "chapter": "88",
                "images": [
                    "https://olympustaff.com/uploads/manga_3fe94/88/a2a9df4918be29d619aec67909b81d95.webp",
                    "https://olympustaff.com/uploads/manga_3fe94/88/bfa66535cb2dc5a87281216c71823e9c.webp",
                    "https://olympustaff.com/uploads/manga_3fe94/88/802cc15778c3132499ea8f05ed7b56f6.webp",
                    "https://olympustaff.com/uploads/manga_3fe94/88/96dac64222c789fd1730569f11d2ec2c.webp",
                    "https://olympustaff.com/uploads/manga_3fe94/88/3e70129ab33e85f1f3e64ca0c60d91a6.webp",
                    "https://olympustaff.com/uploads/manga_3fe94/88/166417a796e061a4888ed2bb7a8e77f3.webp",
                    "https://olympustaff.com/uploads/manga_3fe94/88/bbe7bfc9444e8ca2cda62c21488fc37f.webp",
                    "https://olympustaff.com/uploads/manga_3fe94/88/f290e4bff60a7b6dd9d377d105bf31a1.webp"
                ]
            },
            {
                "chapter": "89",
                "images": [
                    "https://olympustaff.com/uploads/manga_3fe94/89/e9b1eb66006c7873ab3cf536ae873d6e.webp",
                    "https://olympustaff.com/uploads/manga_3fe94/89/f59cd08ce7cfced7e49706cbad79cb34.webp",
                    "https://olympustaff.com/uploads/manga_3fe94/89/8f556a12248df3b1e1f0a850e23ac805.webp",
                    "https://olympustaff.com/uploads/manga_3fe94/89/5f0ff5b470ee7b24184c0da99ee177d7.webp",
                    "https://olympustaff.com/uploads/manga_3fe94/89/7a54099b7f2e9a62dc06aa2e7f31d46d.webp",
                    "https://olympustaff.com/uploads/manga_3fe94/89/7c5c04eb9ec165276e420811e38a484a.webp",
                    "https://olympustaff.com/uploads/manga_3fe94/89/f04a65ac532a621ae894cd5681da9544.webp",
                    "https://olympustaff.com/uploads/manga_3fe94/89/bef7c68113b5f8900f4e8537de3bfa5a.webp"
                ]
            },
            {
                "chapter": "90",
                "images": [
                    "https://olympustaff.com/uploads/manga_3fe94/90/bb73450f8d510d8962103eb15450a96e.webp",
                    "https://olympustaff.com/uploads/manga_3fe94/90/3bca62ab9ebcff2a74ba84d339c8560c.webp",
                    "https://olympustaff.com/uploads/manga_3fe94/90/a298e166f9710e348df8079ca58eb069.webp",
                    "https://olympustaff.com/uploads/manga_3fe94/90/2701875298f40fb7c97577c2280adf40.webp",
                    "https://olympustaff.com/uploads/manga_3fe94/90/df5f4d05a03172ee6ec843fb47ee4f89.webp",
                    "https://olympustaff.com/uploads/manga_3fe94/90/053d77cd3df647999bc7b283d9ed8b73.webp",
                    "https://olympustaff.com/uploads/manga_3fe94/90/b434f5b7bf3efb197dc03af1d5b50bf4.webp",
                    "https://olympustaff.com/uploads/manga_3fe94/90/451b6ed2f597edb74c3f0330e6a3a543.webp",
                    "https://olympustaff.com/uploads/manga_3fe94/90/f5daa8f658e15508ac04f9698e5b83a1.webp"
                ]
            },
            {
                "chapter": "91",
                "images": [
                    "https://olympustaff.com/uploads/manga_3fe94/91/b1b0fa4da1dd7249aa746c754b2d9738.webp",
                    "https://olympustaff.com/uploads/manga_3fe94/91/08ab25a5cc154a4ff95d275a4a4da6b2.webp",
                    "https://olympustaff.com/uploads/manga_3fe94/91/d39255492ee6bc1836cd1bd1e2fcf5f2.webp",
                    "https://olympustaff.com/uploads/manga_3fe94/91/ab92ab124c496b5f6a69b4b72f1c5aa5.4_1.webp",
                    "https://olympustaff.com/uploads/manga_3fe94/91/6805ca03164b4fd6ecff395385327823.5_1.webp",
                    "https://olympustaff.com/uploads/manga_3fe94/91/727afe7231a786f921961de05955bc9d.webp",
                    "https://olympustaff.com/uploads/manga_3fe94/91/fa19019ebf9c92df77f3908549af35d4.webp",
                    "https://olympustaff.com/uploads/manga_3fe94/91/48117a372661530af1a91e3ca68f8992.webp",
                    "https://olympustaff.com/uploads/manga_3fe94/91/e320f1d11ce4c2a5d0e279603887a1f9.webp"
                ]
            },
            {
                "chapter": "92",
                "images": [
                    "https://olympustaff.com/uploads/manga_3fe94/92/0033dca232a4c047da5e6b015bdc6873.webp",
                    "https://olympustaff.com/uploads/manga_3fe94/92/9ca702b0cdba3b33c14f673585b8f63e.webp",
                    "https://olympustaff.com/uploads/manga_3fe94/92/0891cbc52b797d648a088c7a2777d44c.webp",
                    "https://olympustaff.com/uploads/manga_3fe94/92/f274bc999f9e884963025b04c27314cc.webp",
                    "https://olympustaff.com/uploads/manga_3fe94/92/8e6d3c444a63ea77e27a103965ca4b48.webp",
                    "https://olympustaff.com/uploads/manga_3fe94/92/04fdf0b46a72f471c2f853e1c3974131.webp",
                    "https://olympustaff.com/uploads/manga_3fe94/92/de8b128a635361e862b5717fa8f805ca.webp",
                    "https://olympustaff.com/uploads/manga_3fe94/92/21c9a7f9a913e09ef7543857c1a9bc97.webp"
                ]
            },
            {
                "chapter": "93",
                "images": [
                    "https://olympustaff.com/uploads/manga_3fe94/93/8fb2f9024854001c4917e0d6c2db76a7.webp",
                    "https://olympustaff.com/uploads/manga_3fe94/93/56635e874e20074f808773c39c99d9f8.webp",
                    "https://olympustaff.com/uploads/manga_3fe94/93/07a7ec05fd0a89fdac90b03ecaf20a5c.webp",
                    "https://olympustaff.com/uploads/manga_3fe94/93/c4a63b9c34b17ab815f25072a9581889.webp",
                    "https://olympustaff.com/uploads/manga_3fe94/93/afc3af17ac71b27b2678b2e8842827f7.webp",
                    "https://olympustaff.com/uploads/manga_3fe94/93/6e9288cef6c914aacfc79380b40d9500.webp",
                    "https://olympustaff.com/uploads/manga_3fe94/93/36f47340b4ba4764b7cc71a8749f489e.webp",
                    "https://olympustaff.com/uploads/manga_3fe94/93/0d2772364864c9d0bb88fcdeeffd5cc5.webp",
                    "https://olympustaff.com/uploads/manga_3fe94/93/414915111b597be3c477e74977f5b02f.webp"
                ]
            },
            {
                "chapter": "94",
                "images": [
                    "https://olympustaff.com/uploads/manga_3fe94/94/6659f578396ac16bc2aa3b8e685912bc.webp",
                    "https://olympustaff.com/uploads/manga_3fe94/94/9a7b5ccaed3c542f3a05855d8decc9e3.webp",
                    "https://olympustaff.com/uploads/manga_3fe94/94/f3f11f4cf2c343d8d471c462420ef9bc.webp",
                    "https://olympustaff.com/uploads/manga_3fe94/94/c90568966434f33539a9da5c72bcf1c1.webp",
                    "https://olympustaff.com/uploads/manga_3fe94/94/d3a0d547f5ba69a73e8d9cd359ffaa0d.webp",
                    "https://olympustaff.com/uploads/manga_3fe94/94/3ec34026faa2325f894ea5dfae867548.webp",
                    "https://olympustaff.com/uploads/manga_3fe94/94/5abb82f4eb182fb8b488bf8d5e83fa52.webp",
                    "https://olympustaff.com/uploads/manga_3fe94/94/f43ae4d08a0117b23a08c5e0f3f529db.webp"
                ]
            },
            {
                "chapter": "95",
                "images": [
                    "https://olympustaff.com/uploads/manga_3fe94/95/8a2a820d4be8ec2c934011d7986ea840.webp",
                    "https://olympustaff.com/uploads/manga_3fe94/95/e41e6e931bdd4a89b31f780f8f58d613.webp",
                    "https://olympustaff.com/uploads/manga_3fe94/95/c484a39d8b1c456208b3bdeeced3a6e5.webp",
                    "https://olympustaff.com/uploads/manga_3fe94/95/76b7ef0d9eb4512fa5fc19d0ec1181cb.webp",
                    "https://olympustaff.com/uploads/manga_3fe94/95/2345d75972b6589cae593a3a14c4de7f.webp",
                    "https://olympustaff.com/uploads/manga_3fe94/95/24d827dffea01c2fe6de4c76fdfb345c.webp",
                    "https://olympustaff.com/uploads/manga_3fe94/95/329702bde582ba5fee9a2a0a0f66bc46.webp",
                    "https://olympustaff.com/uploads/manga_3fe94/95/8e17f3d57b5def25fea395a1b119f4f6.webp"
                ]
            },
            {
                "chapter": "96",
                "images": [
                    "https://olympustaff.com/uploads/manga_3fe94/96/e6f41723e81f98ab7f8399b6e2a93d19.webp",
                    "https://olympustaff.com/uploads/manga_3fe94/96/23c5c52d3db2c654045f01dd45d80452.webp",
                    "https://olympustaff.com/uploads/manga_3fe94/96/9ce0573c0faeade84e51504cda826683.webp",
                    "https://olympustaff.com/uploads/manga_3fe94/96/84ecc064388bb81bbfdc6345530637e2.webp",
                    "https://olympustaff.com/uploads/manga_3fe94/96/ef6c86765e33427c979b41a3f8b4dfa0.webp",
                    "https://olympustaff.com/uploads/manga_3fe94/96/0113c95a3856e693d725d1a483d902ce.webp",
                    "https://olympustaff.com/uploads/manga_3fe94/96/a203b84e75f9236247919a6451fc791c.webp",
                    "https://olympustaff.com/uploads/manga_3fe94/96/659bb2732b73389004d4af3a9a6d95fc.webp"
                ]
            }
        ]
    }
}